Workbook
Name P_Regio: Parameters!$C$5
Name P_RJ: Parameters!$C$6
Name P_Peildatum: Parameters!$C$7
Name P_PeilMaand: Parameters!$C$8
Name P_PeilTxt: Parameters!$C$9
Name P_UploadVJ: Parameters!$C$10
Name P_UploadVersie: Parameters!$C$11
Name P_VJ: Parameters!$C$12
Name P_Eenheid: Parameters!$C$13
Name P_Factor: Parameters!$C$14
Name P_Demo: Parameters!$C$15
Name P_ImportID: Parameters!$C$16
Name P_BronZ: Parameters!$C$17
Name P_BronE: Parameters!$C$18
Name P_Importdatum: Parameters!$C$19
Name P_RegelsZ: Parameters!$C$20
Name P_RegelsE: Parameters!$C$21
Name P_StatusVastleg: Parameters!$C$22
Name P_ToelCorrectie: Parameters!$C$23
Name P_Tol: Parameters!$C$24
Name V_List: Parameters!$B$28:$B$32
Name V_Maand: Parameters!$D$28:$D$32
Name L_TypeList: Parameters!$C$34:$E$34
Name L_EenheidList: Parameters!$C$35:$E$35
Name L_JaNee: Parameters!$C$36:$D$36
Name L_StatusList: Parameters!$C$37:$D$37
Name L_AanvStatus: Parameters!$C$38:$F$38
Name L_Rubrieken: Parameters!$C$39:$I$39
Name L_Soort: Parameters!$C$40:$D$40
Name L_Niveau: Parameters!$C$41:$D$41
Name L_Doeljaar: Vastlegging!$I$6:$I$5005
Name L_Projecten: Parameters!$C$44:$C$144
Name L_ProjectenDet: Parameters!$C$45:$C$144
Name YM_Intern: Veldwoordenboek!$B$6:$B$14
Name YM_Header: Veldwoordenboek!$C$6:$C$14
Name Map_WBS: Mapping!$A$5:$A$104
Name Map_Projdef: Mapping!$B$5:$B$104
Name Map_Naam: Mapping!$C$5:$C$104
Name Map_Aantal: Mapping!$D$5:$D$104
Name Map_Aandeel: Mapping!$E$5:$E$104
Name Map_Type: Mapping!$F$5:$F$104
Name Map_Meetellen: Mapping!$G$5:$G$104
Name Map_Segment: Mapping!$H$5:$H$104
Name L_ImportID: Vastlegging!$A$6:$A$5005
Name L_Bronbestand: Vastlegging!$B$6:$B$5005
Name L_Importdatum: Vastlegging!$C$6:$C$5005
Name L_Status: Vastlegging!$D$6:$D$5005
Name L_Versiejaar: Vastlegging!$E$6:$E$5005
Name L_Versie: Vastlegging!$F$6:$F$5005
Name L_Revisie: Vastlegging!$G$6:$G$5005
Name L_Peildatum: Vastlegging!$H$6:$H$5005
Name L_WBS: Vastlegging!$J$6:$J$5005
Name L_Projectdefinitie: Vastlegging!$K$6:$K$5005
Name L_Projectnaam: Vastlegging!$L$6:$L$5005
Name L_Type: Vastlegging!$M$6:$M$5005
Name L_IFRS: Vastlegging!$N$6:$N$5005
Name L_Kengetal: Vastlegging!$O$6:$O$5005
Name L_Waarde: Vastlegging!$P$6:$P$5005
Name L_Eenheid: Vastlegging!$Q$6:$Q$5005
Name L_Toelichting: Vastlegging!$R$6:$R$5005

Sheet Start
B1: RDFO-prototype — fictieve demodata
B2: Werkend prototype op uitsluitend fictieve data. Demo-aannames zijn geen vastgestelde SAP-definities.
B4: Status | C4: =IF(Controle!$D$4>0,"✖ "&Controle!$D$4&" FOUT(en) — zie Controle",IF(Controle!$D$5>0,"▲ geen fouten, "&Controle!$D$5&" waarschuwing(en)","✔ geen fouten of waarschuwingen")) -> ✔ geen fouten of waarschuwingen
C5: ="Upload: "&P_UploadVersie&" "&P_UploadVJ&" · peildatum "&P_PeilTxt&" · Import-ID "&P_ImportID&" · rapportage: doeljaar "&Sel_Doeljaar&", "&Sel_Label -> Upload: Q3 2026 · peildatum 30-09-2026 · Import-ID IMP-2026-Q3-01 · rapportage: doeljaar 2026, Q3 2026 (vastgesteld)
E7: Legenda
B8: Rapportage | E8: Invoercel (blauw cijfer, lichtgeel)
B9: Dashboard | C9: Regiodashboard: filters (doeljaar, versie, type, project), KPI-tegels, prognoseverloop, mutaties, doorkijk. | E9: Geselecteerde versie (geel vlak)
B10: RDFO | C10: Volledige RDFO-opbouw: Budget, Q1–Q4 vastgelegd, upload-concept, realisatie YTD, to go, delta’s. | E10: Realisatie / actual (groen, cursief)
B11: Projecten | C11: Per project: versies, realisatie, to go, BOR, marge, verschillen + toelichting. | E11: Subtotaal onvolledig (bevat n.b.)
B12: Projectdetail | C12: Eén project: kerngegevens, versieverloop, planning omzet/BOR, woningverkopen. | E12: KPI-tegel / totaal
B13: Woningen | C13: Verkopen per maand/kwartaal, jaarverwachting per versie, koperstype, segment, projectmatrix. | E13: Bronkop
B14: Controle | C14: Alle controles met status en uitzonderingslijsten.
E15: n.b. = niet beschikbaar · n.v.t. = niet van toepassing
B16: Invoer | E16: Bedragen bron: EUR, volle precisie
B17: Parameters | C17: Rapportagejaar, peildatum, uploadversie, eenheid, Import-ID, status bij vastleggen. | E17: Omzet/winst positief, verlies negatief
B18: Invoer_Aanvullend | C18: Posten die niet uit de bronnen komen (taakstelling, eliminaties, AK-dekking, fees …).
B19: Invoer_Toelichting | C19: Toelichtingen op verschillen per project en versie.
B20: Invoer_Koperstype | C20: Optionele koperstype-verdeling voor toekomstige verkopen.
B21: Mapping | C21: Projectmapping WBS → projectdefinitie, type, segment, woningen meetellen.
B23: Versiebeheer
B24: Vastlegging | C24: Onveranderlijk versiegrootboek (alleen toevoegen).
B25: Vastleggen | C25: Concept van de huidige upload in grootboekformaat — HANDMATIG kopiëren/plakken als waarden.
B26: Importlog | C26: Audittrail per import/vastlegging.
B28: Bron en verwerking (niet wijzigen)
B29: SRC_ZPMW03 | C29: Ongewijzigde export ZPMW03 — hier plakken.
B30: SRC_Woningetalage | C30: Ongewijzigde export Woningetalage — hier plakken.
B31: STG_ZPMW03 | C31: Staging: velden gezocht op kolomnaam, tekenomzetting, regelcontroles.
B32: STG_Woningetalage | C32: Staging: dubbele headers op positie, jaarheaders via mapping, regelcontroles.
B33: VERW_Project | C33: Eén regel per gemapt WBS; elke bron eerst per WBS geaggregeerd.
B34: CALC_Versies | C34: Totalen per versie (regio en gefilterd), geselecteerde en vorige versie.
B36: Documentatie
B37: Handleiding | C37: Bronvervanging, verversen, kwartaalvastlegging, correcties.
B38: Rapportagemapping | C38: Elke rapportageregel → bron / berekening / aanvullende invoer + open definities.
B39: Productievragen | C39: Openstaande vragen vóór productie.
B40: Veldwoordenboek | C40: Interne veldnamen, aliassen, dubbele headers, jaarheader-mapping.
B41: Testresultaten | C41: Uitgevoerde scenario-tests (nieuwe upload, dubbele import, correctie, weging, verlies).
B43: Ontwerpkeuze
B44: Keuze | C44: Excel met gestructureerde lagen en formule-staging op kolomnaam; géén Power Query, géén macro's.
B45: Waarom geen Power Query (nu) | C45: De bronnen worden per ronde handmatig vervangen en zijn klein (tientallen tot honderden regels). Een plak-tabblad met staging op kolomnaam geeft hetzelfde voordeel als Power Query (kolomvolgorde mag wijzigen, aliassen, dubbele headers op positie) maar werkt in elke Excelversie, rekent direct mee, is cel-voor-cel controleerbaar en kon in dit prototype automatisch getest worden. Power Query-queries kunnen in deze bouwomgeving niet worden uitgevoerd of getest; een ongeteste query opleveren past niet bij 'beloof niets dat niet werkt'.
B46: Wanneer wél Power Query | C46: Als bronnen uit een vaste map/SharePoint komen of groter worden dan ~500 regels. De staginglaag (STG_*) is dan 1-op-1 te vervangen door een query die dezelfde interne veldnamen (Veldwoordenboek) oplevert; rapportage en versiebeheer blijven ongewijzigd.
B47: Waarom geen macro's | C47: Vastleggen is bewust een handmatige plak-als-waarden-stap met automatische revisie, dubbel-detectie en controles. Er is dus geen upload- of snapshotknop; dat wordt nergens gesuggereerd.
B48: Waarom een grootboek (long format) | C48: Elke vastgelegde waarde is één regel: Import-ID, bronbestand, importdatum, status, versiejaar, versie, revisie, peildatum, doeljaar, WBS, historische projectnaam/type/IFRS, kengetal, waarde, eenheid, toelichting. Nieuwe kengetallen of versies vragen geen nieuwe kolommen of bladen; rapportage leest alleen actieve vastgestelde regels.

Sheet Dashboard
B1: ="Regiodashboard "&P_Regio&" — doeljaar "&Sel_Doeljaar&" · versie "&Sel_Label -> Regiodashboard Demo Regio — doeljaar 2026 · versie Q3 2026 (vastgesteld)
B2: ="Bedragen in EUR mln (bron: EUR, volledige precisie) · upload peildatum "&P_PeilTxt&" · filter: "&Sel_FiltLabel -> Bedragen in EUR mln (bron: EUR, volledige precisie) · upload peildatum 30-09-2026 · filter: geen filter
B4: Doeljaar | E4: Versie | H4: Opstal / deelneming | K4: Project | P4: Controlestatus
B5: 2026 | E5: Q3 | H5: Alle | K5: Alle | P5: =IF(Controle!$D$4>0,"✖ "&Controle!$D$4&" fout(en)",IF(Controle!$D$5>0,"▲ "&Controle!$D$5&" waarschuwing(en)","✔ geen fouten")) -> ✔ geen fouten
B7: ="Omzet FY "&Sel_Doeljaar&" · "&Sel_Versie -> Omzet FY 2026 · Q3 | E7: ="BOR FY "&Sel_Doeljaar&" · "&Sel_Versie -> BOR FY 2026 · Q3 | H7: Realisatie YTD (zelfde peildatum) | K7: Omzet to go (FY − realisatie) | N7: ="Woningverkopen "&Sel_Doeljaar&" · "&Sel_Versie -> Woningverkopen 2026 · Q3 | Q7: Etalage (upload, onverkocht)
B8: =IF(ISNUMBER(CALC_Versies!$S$11),CALC_Versies!$S$11/1000000,"n.b.") -> 114.0968 | E8: =IF(ISNUMBER(CALC_Versies!$T$11),CALC_Versies!$T$11/1000000,"n.b.") -> 10.477198 | H8: =IF(ISNUMBER(CALC_Versies!$U$11),CALC_Versies!$U$11/1000000,CALC_Versies!$U$11) -> 74.16292 | K8: =IF(CALC_Versies!$U$11="n.v.t.",IF(ISNUMBER(CALC_Versies!$S$11),CALC_Versies!$S$11/1000000,"n.b."),IF(AND(ISNUMBER(CALC_Versies!$S$11),ISNUMBER(CALC_Versies!$U$11)),(CALC_Versies!$S$11-CALC_Versies!$U$11)/1000000,"n.b.")) -> 39.93388 | N8: =CALC_Versies!$W$11 -> 360 | Q8: =SUMIFS(V_W_Etalage,V_Meetellen,"Ja",V_Type,Sel_TypeCrit,V_WBS,Sel_WBS) -> 902
B9: ="Δ budget: "&IF(AND(ISNUMBER(CALC_Versies!$S$11),ISNUMBER(CALC_Versies!$S$5)),FIXED((CALC_Versies!$S$11-CALC_Versies!$S$5)/1000000,1)&" mln","n.b.") -> Δ budget: -4.4 mln | E9: ="BOR %: "&IF(AND(ISNUMBER(CALC_Versies!$T$11),ISNUMBER(CALC_Versies!$S$11)),IF(CALC_Versies!$S$11<>0,FIXED(CALC_Versies!$T$11/CALC_Versies!$S$11*100,1)&"%","n.b."),"n.b.") -> BOR %: 9.2% | H9: =IF(AND(ISNUMBER(CALC_Versies!$U$11),ISNUMBER(CALC_Versies!$S$11)),IF(CALC_Versies!$S$11<>0,FIXED(CALC_Versies!$U$11/CALC_Versies!$S$11*100,0)&"% van FY-prognose","n.b."),"voortgang n.b.") -> 65% van FY-prognose | K9: ="BOR to go: "&IF(CALC_Versies!$V$11="n.v.t.",IF(ISNUMBER(CALC_Versies!$T$11),FIXED(CALC_Versies!$T$11/1000000,1),"n.b."),IF(AND(ISNUMBER(CALC_Versies!$T$11),ISNUMBER(CALC_Versies!$V$11)),FIXED((CALC_Versies!$T$11-CALC_Versies!$V$11)/1000000,1),"n.b."))&" mln" -> BOR to go: 3.7 mln | N9: ="actual YTD: "&CALC_Versies!$X$11 -> actual YTD: 193 | Q9: ="verkocht: "&IF(SUMIFS(V_W_Aantal,V_Meetellen,"Ja",V_Type,Sel_TypeCrit,V_WBS,Sel_WBS)=0,"n.b.",FIXED(SUMIFS(V_W_Cum_T,V_Meetellen,"Ja",V_Type,Sel_TypeCrit,V_WBS,Sel_WBS)/SUMIFS(V_W_Aantal,V_Meetellen,"Ja",V_Type,Sel_TypeCrit,V_WBS,Sel_WBS)*100,0)&"%") -> verkocht: 22%
B10: ="Δ "&IF(Sel_Prev="","vorige",Sel_Prev)&": "&IF(AND(ISNUMBER(CALC_Versies!$S$11),ISNUMBER(CALC_Versies!$S$12)),FIXED((CALC_Versies!$S$11-CALC_Versies!$S$12)/1000000,1)&" mln","n.b.") -> Δ Q2: 1.3 mln | E10: ="Δ budget: "&IF(AND(ISNUMBER(CALC_Versies!$T$11),ISNUMBER(CALC_Versies!$T$5)),FIXED((CALC_Versies!$T$11-CALC_Versies!$T$5)/1000000,1)&" mln","n.b.") -> Δ budget: -0.3 mln | H10: =IF(AND(ISNUMBER(CALC_Versies!$U$11),ISNUMBER(CALC_Versies!$S$11)),IF(CALC_Versies!$S$11<>0,CALC_Versies!$U$11/CALC_Versies!$S$11,0),0) -> 0.65 | K10: ="nooit oude prognose − nieuwe actual" -> nooit oude prognose − nieuwe actual | N10: ="budget: "&CALC_Versies!$W$5 -> budget: 372 | Q10: ="verliesprojecten (upload): "&SUMIFS(V_Verlies,V_Type,Sel_TypeCrit,V_WBS,Sel_WBS) -> verliesprojecten (upload): 2
B12: ="Jaarprognoseverloop "&Sel_Doeljaar&": FY-omzet en BOR per vastgelegde versie (EUR mln)" -> Jaarprognoseverloop 2026: FY-omzet en BOR per vastgelegde versie (EUR mln) | K12: ="Realisatie vs resterende prognose — top 10 projecten, "&Sel_Label&" (EUR mln)" -> Realisatie vs resterende prognose — top 10 projecten, Q3 2026 (vastgesteld) (EUR mln)
B30: ="Grootste projectmutaties "&Sel_Versie&" vs "&IF(Sel_Prev="","–",Sel_Prev)&" (Δ FY-omzet, EUR mln)" -> Grootste projectmutaties Q3 vs Q2 (Δ FY-omzet, EUR mln) | K30: ="Meerjarendoorkijk upload "&P_PeilTxt&" (EUR mln)" -> Meerjarendoorkijk upload 30-09-2026 (EUR mln)
B47: Kolommen met '(n.b.)' in het label hebben geen vastgelegde versie: de staaf ontbreekt bewust (niet nul). Realisatie (donkerblauw) en resterende prognose (geel) zijn gescheiden.
B48: Grafiekdata (gekoppeld aan CALC_Versies / Projecten / VERW_Project — niet overschrijven)
B49: A. Jaarprognoseverloop (EUR mln) | H49: B. Top 10 projecten: realisatie vs to go (EUR mln, geselecteerde versie) | N49: C. Grootste mutaties vs vorige versie (EUR mln)
B50: Versie | C50: Label | D50: Omzet FY | E50: BOR FY | F50: BOR % | H50: # | I50: Project | J50: Realisatie YTD | K50: To go | L50: FY | N50: # | O50: Project | P50: Δ omzet FY
B51: Budget | C51: =B51&IF(ISNUMBER(CALC_Versies!$S$5),""," (n.b.)") -> Budget | D51: =IF(ISNUMBER(CALC_Versies!$S$5),CALC_Versies!$S$5/1000000,0) -> 118.52544 | E51: =IF(ISNUMBER(CALC_Versies!$T$5),CALC_Versies!$T$5/1000000,0) -> 10.769875 | F51: =IF(AND(ISNUMBER(CALC_Versies!$S$5),ISNUMBER(CALC_Versies!$T$5)),IF(CALC_Versies!$S$5<>0,CALC_Versies!$T$5/CALC_Versies!$S$5,"n.b."),"n.b.") -> 0.090865514 | H51: 1 | I51: =IF($Q51=0,"",INDEX(Projecten!$B$10:$B$109,$Q51)) -> Duinwaard, Duinrand | J51: =IF($Q51=0,0,IF(ISNUMBER(INDEX(Projecten!$L$10:$L$109,$Q51)),INDEX(Projecten!$L$10:$L$109,$Q51)*P_Factor/1000000,0)) -> 10.8108 | K51: =IF($Q51=0,0,IF(ISNUMBER(INDEX(Projecten!$M$10:$M$109,$Q51)),INDEX(Projecten!$M$10:$M$109,$Q51)*P_Factor/1000000,0)) -> 5.8212 | L51: =IF($Q51=0,0,INDEX(Projecten!$K$10:$K$109,$Q51)*P_Factor/1000000) -> 16.632 | N51: 1 | O51: =IF($R51=0,"",INDEX(Projecten!$B$10:$B$109,$R51)) -> Duinwaard, Duinrand | P51: =IF($R51=0,0,INDEX(Projecten!$Q$10:$Q$109,$R51)*P_Factor/1000000) -> 0.49896 | Q51: =IFERROR(MATCH(LARGE(Projecten!$U$10:$U$109,1),Projecten!$U$10:$U$109,0),0) -> 9 | R51: =IFERROR(MATCH(LARGE(Projecten!$V$10:$V$109,1),Projecten!$V$10:$V$109,0),0) -> 9
B52: Q1 | C52: =B52&IF(ISNUMBER(CALC_Versies!$S$6),""," (n.b.)") -> Q1 | D52: =IF(ISNUMBER(CALC_Versies!$S$6),CALC_Versies!$S$6/1000000,0) -> 116.75398 | E52: =IF(ISNUMBER(CALC_Versies!$T$6),CALC_Versies!$T$6/1000000,0) -> 10.652804 | F52: =IF(AND(ISNUMBER(CALC_Versies!$S$6),ISNUMBER(CALC_Versies!$T$6)),IF(CALC_Versies!$S$6<>0,CALC_Versies!$T$6/CALC_Versies!$S$6,"n.b."),"n.b.") -> 0.091241462 | H52: 2 | I52: =IF($Q52=0,"",INDEX(Projecten!$B$10:$B$109,$Q52)) -> Meerhovenstad, Hofstaete | J52: =IF($Q52=0,0,IF(ISNUMBER(INDEX(Projecten!$L$10:$L$109,$Q52)),INDEX(Projecten!$L$10:$L$109,$Q52)*P_Factor/1000000,0)) -> 9.4848 | K52: =IF($Q52=0,0,IF(ISNUMBER(INDEX(Projecten!$M$10:$M$109,$Q52)),INDEX(Projecten!$M$10:$M$109,$Q52)*P_Factor/1000000,0)) -> 5.1072 | L52: =IF($Q52=0,0,INDEX(Projecten!$K$10:$K$109,$Q52)*P_Factor/1000000) -> 14.592 | N52: 2 | O52: =IF($R52=0,"",INDEX(Projecten!$B$10:$B$109,$R52)) -> Meerhovenstad, Hofstaete | P52: =IF($R52=0,0,INDEX(Projecten!$Q$10:$Q$109,$R52)*P_Factor/1000000) -> 0.43776 | Q52: =IFERROR(MATCH(LARGE(Projecten!$U$10:$U$109,2),Projecten!$U$10:$U$109,0),0) -> 11 | R52: =IFERROR(MATCH(LARGE(Projecten!$V$10:$V$109,2),Projecten!$V$10:$V$109,0),0) -> 11
B53: Q2 | C53: =B53&IF(ISNUMBER(CALC_Versies!$S$7),""," (n.b.)") -> Q2 | D53: =IF(ISNUMBER(CALC_Versies!$S$7),CALC_Versies!$S$7/1000000,0) -> 112.76821 | E53: =IF(ISNUMBER(CALC_Versies!$T$7),CALC_Versies!$T$7/1000000,0) -> 10.389395 | F53: =IF(AND(ISNUMBER(CALC_Versies!$S$7),ISNUMBER(CALC_Versies!$T$7)),IF(CALC_Versies!$S$7<>0,CALC_Versies!$T$7/CALC_Versies!$S$7,"n.b."),"n.b.") -> 0.092130531 | H53: 3 | I53: =IF($Q53=0,"",INDEX(Projecten!$B$10:$B$109,$Q53)) -> Veldendam, Spoorpark | J53: =IF($Q53=0,0,IF(ISNUMBER(INDEX(Projecten!$L$10:$L$109,$Q53)),INDEX(Projecten!$L$10:$L$109,$Q53)*P_Factor/1000000,0)) -> 7.644 | K53: =IF($Q53=0,0,IF(ISNUMBER(INDEX(Projecten!$M$10:$M$109,$Q53)),INDEX(Projecten!$M$10:$M$109,$Q53)*P_Factor/1000000,0)) -> 4.116 | L53: =IF($Q53=0,0,INDEX(Projecten!$K$10:$K$109,$Q53)*P_Factor/1000000) -> 11.76 | N53: 3 | O53: =IF($R53=0,"",INDEX(Projecten!$B$10:$B$109,$R53)) -> Veldendam, Spoorpark | P53: =IF($R53=0,0,INDEX(Projecten!$Q$10:$Q$109,$R53)*P_Factor/1000000) -> 0.3528 | Q53: =IFERROR(MATCH(LARGE(Projecten!$U$10:$U$109,3),Projecten!$U$10:$U$109,0),0) -> 17 | R53: =IFERROR(MATCH(LARGE(Projecten!$V$10:$V$109,3),Projecten!$V$10:$V$109,0),0) -> 17
B54: Q3 | C54: =B54&IF(ISNUMBER(CALC_Versies!$S$8),""," (n.b.)") -> Q3 | D54: =IF(ISNUMBER(CALC_Versies!$S$8),CALC_Versies!$S$8/1000000,0) -> 114.0968 | E54: =IF(ISNUMBER(CALC_Versies!$T$8),CALC_Versies!$T$8/1000000,0) -> 10.477198 | F54: =IF(AND(ISNUMBER(CALC_Versies!$S$8),ISNUMBER(CALC_Versies!$T$8)),IF(CALC_Versies!$S$8<>0,CALC_Versies!$T$8/CALC_Versies!$S$8,"n.b."),"n.b.") -> 0.091827273 | H54: 4 | I54: =IF($Q54=0,"",INDEX(Projecten!$B$10:$B$109,$Q54)) -> Rietdam, Rietoevers | J54: =IF($Q54=0,0,IF(ISNUMBER(INDEX(Projecten!$L$10:$L$109,$Q54)),INDEX(Projecten!$L$10:$L$109,$Q54)*P_Factor/1000000,0)) -> 5.70024 | K54: =IF($Q54=0,0,IF(ISNUMBER(INDEX(Projecten!$M$10:$M$109,$Q54)),INDEX(Projecten!$M$10:$M$109,$Q54)*P_Factor/1000000,0)) -> 3.06936 | L54: =IF($Q54=0,0,INDEX(Projecten!$K$10:$K$109,$Q54)*P_Factor/1000000) -> 8.7696 | N54: 4 | O54: =IF($R54=0,"",INDEX(Projecten!$B$10:$B$109,$R54)) -> Rietdam, Rietoevers | P54: =IF($R54=0,0,INDEX(Projecten!$Q$10:$Q$109,$R54)*P_Factor/1000000) -> -0.263088 | Q54: =IFERROR(MATCH(LARGE(Projecten!$U$10:$U$109,4),Projecten!$U$10:$U$109,0),0) -> 14 | R54: =IFERROR(MATCH(LARGE(Projecten!$V$10:$V$109,4),Projecten!$V$10:$V$109,0),0) -> 14
B55: Q4 | C55: =B55&IF(ISNUMBER(CALC_Versies!$S$9),""," (n.b.)") -> Q4 (n.b.) | D55: =IF(ISNUMBER(CALC_Versies!$S$9),CALC_Versies!$S$9/1000000,0) -> 0 | E55: =IF(ISNUMBER(CALC_Versies!$T$9),CALC_Versies!$T$9/1000000,0) -> 0 | F55: =IF(AND(ISNUMBER(CALC_Versies!$S$9),ISNUMBER(CALC_Versies!$T$9)),IF(CALC_Versies!$S$9<>0,CALC_Versies!$T$9/CALC_Versies!$S$9,"n.b."),"n.b.") -> n.b. | H55: 5 | I55: =IF($Q55=0,"",INDEX(Projecten!$B$10:$B$109,$Q55)) -> Zilverdam, Kadezicht | J55: =IF($Q55=0,0,IF(ISNUMBER(INDEX(Projecten!$L$10:$L$109,$Q55)),INDEX(Projecten!$L$10:$L$109,$Q55)*P_Factor/1000000,0)) -> 4.368 | K55: =IF($Q55=0,0,IF(ISNUMBER(INDEX(Projecten!$M$10:$M$109,$Q55)),INDEX(Projecten!$M$10:$M$109,$Q55)*P_Factor/1000000,0)) -> 2.352 | L55: =IF($Q55=0,0,INDEX(Projecten!$K$10:$K$109,$Q55)*P_Factor/1000000) -> 6.72 | N55: 5 | O55: =IF($R55=0,"",INDEX(Projecten!$B$10:$B$109,$R55)) -> Zilverdam, Kadezicht | P55: =IF($R55=0,0,INDEX(Projecten!$Q$10:$Q$109,$R55)*P_Factor/1000000) -> 0.2016 | Q55: =IFERROR(MATCH(LARGE(Projecten!$U$10:$U$109,5),Projecten!$U$10:$U$109,0),0) -> 5 | R55: =IFERROR(MATCH(LARGE(Projecten!$V$10:$V$109,5),Projecten!$V$10:$V$109,0),0) -> 5
B56: Upload | C56: ="Upload "&P_PeilTxt&IF(ISNUMBER(CALC_Versies!$S$10),""," (n.b.)") -> Upload 30-09-2026 | D56: =IF(ISNUMBER(CALC_Versies!$S$10),CALC_Versies!$S$10/1000000,0) -> 114.0968 | E56: =IF(ISNUMBER(CALC_Versies!$T$10),CALC_Versies!$T$10/1000000,0) -> 10.477198 | F56: =IF(AND(ISNUMBER(CALC_Versies!$S$10),ISNUMBER(CALC_Versies!$T$10)),IF(CALC_Versies!$S$10<>0,CALC_Versies!$T$10/CALC_Versies!$S$10,"n.b."),"n.b.") -> 0.091827273 | H56: 6 | I56: =IF($Q56=0,"",INDEX(Projecten!$B$10:$B$109,$Q56)) -> Boswaard, De Eiken | J56: =IF($Q56=0,0,IF(ISNUMBER(INDEX(Projecten!$L$10:$L$109,$Q56)),INDEX(Projecten!$L$10:$L$109,$Q56)*P_Factor/1000000,0)) -> 4.26816 | K56: =IF($Q56=0,0,IF(ISNUMBER(INDEX(Projecten!$M$10:$M$109,$Q56)),INDEX(Projecten!$M$10:$M$109,$Q56)*P_Factor/1000000,0)) -> 2.29824 | L56: =IF($Q56=0,0,INDEX(Projecten!$K$10:$K$109,$Q56)*P_Factor/1000000) -> 6.5664 | N56: 6 | O56: =IF($R56=0,"",INDEX(Projecten!$B$10:$B$109,$R56)) -> Boswaard, De Eiken | P56: =IF($R56=0,0,INDEX(Projecten!$Q$10:$Q$109,$R56)*P_Factor/1000000) -> -0.196992 | Q56: =IFERROR(MATCH(LARGE(Projecten!$U$10:$U$109,6),Projecten!$U$10:$U$109,0),0) -> 6 | R56: =IFERROR(MATCH(LARGE(Projecten!$V$10:$V$109,6),Projecten!$V$10:$V$109,0),0) -> 6
H57: 7 | I57: =IF($Q57=0,"",INDEX(Projecten!$B$10:$B$109,$Q57)) -> Zilverdam, Havenlicht | J57: =IF($Q57=0,0,IF(ISNUMBER(INDEX(Projecten!$L$10:$L$109,$Q57)),INDEX(Projecten!$L$10:$L$109,$Q57)*P_Factor/1000000,0)) -> 4.0131 | K57: =IF($Q57=0,0,IF(ISNUMBER(INDEX(Projecten!$M$10:$M$109,$Q57)),INDEX(Projecten!$M$10:$M$109,$Q57)*P_Factor/1000000,0)) -> 2.1609 | L57: =IF($Q57=0,0,INDEX(Projecten!$K$10:$K$109,$Q57)*P_Factor/1000000) -> 6.174 | N57: 7 | O57: =IF($R57=0,"",INDEX(Projecten!$B$10:$B$109,$R57)) -> Zilverdam, Havenlicht | P57: =IF($R57=0,0,INDEX(Projecten!$Q$10:$Q$109,$R57)*P_Factor/1000000) -> 0.18522 | Q57: =IFERROR(MATCH(LARGE(Projecten!$U$10:$U$109,7),Projecten!$U$10:$U$109,0),0) -> 19 | R57: =IFERROR(MATCH(LARGE(Projecten!$V$10:$V$109,7),Projecten!$V$10:$V$109,0),0) -> 19
H58: 8 | I58: =IF($Q58=0,"",INDEX(Projecten!$B$10:$B$109,$Q58)) -> Rietdam, Havenkwartier | J58: =IF($Q58=0,0,IF(ISNUMBER(INDEX(Projecten!$L$10:$L$109,$Q58)),INDEX(Projecten!$L$10:$L$109,$Q58)*P_Factor/1000000,0)) -> 3.952 | K58: =IF($Q58=0,0,IF(ISNUMBER(INDEX(Projecten!$M$10:$M$109,$Q58)),INDEX(Projecten!$M$10:$M$109,$Q58)*P_Factor/1000000,0)) -> 2.128 | L58: =IF($Q58=0,0,INDEX(Projecten!$K$10:$K$109,$Q58)*P_Factor/1000000) -> 6.08 | N58: 8 | O58: =IF($R58=0,"",INDEX(Projecten!$B$10:$B$109,$R58)) -> Rietdam, Havenkwartier | P58: =IF($R58=0,0,INDEX(Projecten!$Q$10:$Q$109,$R58)*P_Factor/1000000) -> 0.1824 | Q58: =IFERROR(MATCH(LARGE(Projecten!$U$10:$U$109,8),Projecten!$U$10:$U$109,0),0) -> 7 | R58: =IFERROR(MATCH(LARGE(Projecten!$V$10:$V$109,8),Projecten!$V$10:$V$109,0),0) -> 7
H59: 9 | I59: =IF($Q59=0,"",INDEX(Projecten!$B$10:$B$109,$Q59)) -> Lindehaven, Parkzoom fase 1 | J59: =IF($Q59=0,0,IF(ISNUMBER(INDEX(Projecten!$L$10:$L$109,$Q59)),INDEX(Projecten!$L$10:$L$109,$Q59)*P_Factor/1000000,0)) -> 3.63584 | K59: =IF($Q59=0,0,IF(ISNUMBER(INDEX(Projecten!$M$10:$M$109,$Q59)),INDEX(Projecten!$M$10:$M$109,$Q59)*P_Factor/1000000,0)) -> 1.95776 | L59: =IF($Q59=0,0,INDEX(Projecten!$K$10:$K$109,$Q59)*P_Factor/1000000) -> 5.5936 | Q59: =IFERROR(MATCH(LARGE(Projecten!$U$10:$U$109,9),Projecten!$U$10:$U$109,0),0) -> 1
H60: 10 | I60: =IF($Q60=0,"",INDEX(Projecten!$B$10:$B$109,$Q60)) -> Duinwaard, De Lantaarn | J60: =IF($Q60=0,0,IF(ISNUMBER(INDEX(Projecten!$L$10:$L$109,$Q60)),INDEX(Projecten!$L$10:$L$109,$Q60)*P_Factor/1000000,0)) -> 3.1616 | K60: =IF($Q60=0,0,IF(ISNUMBER(INDEX(Projecten!$M$10:$M$109,$Q60)),INDEX(Projecten!$M$10:$M$109,$Q60)*P_Factor/1000000,0)) -> 1.7024 | L60: =IF($Q60=0,0,INDEX(Projecten!$K$10:$K$109,$Q60)*P_Factor/1000000) -> 4.864 | N60: =IF(Sel_Prev="","Budget heeft geen vorige versie: geen mutaties.",IF(COUNT(Projecten!$V$10:$V$109)=0,"Geen mutaties beschikbaar (vorige versie n.b.).","")) | Q60: =IFERROR(MATCH(LARGE(Projecten!$U$10:$U$109,10),Projecten!$U$10:$U$109,0),0) -> 16
B62: D. Meerjarendoorkijk huidige upload (EUR mln, niet vastgelegd)
B63: Jaar | C63: Omzet | D63: BOR
B64: =P_RJ&" FY" -> 2026 FY | C64: =SUMIFS(V_OmzFY,V_Type,Sel_TypeCrit,V_WBS,Sel_WBS)/1000000 -> 114.0968 | D64: =SUMIFS(V_BorFY,V_Type,Sel_TypeCrit,V_WBS,Sel_WBS)/1000000 -> 10.477198
B65: =(P_RJ+1)&"" -> 2027 | C65: =SUMIFS(V_OmzFY1,V_Type,Sel_TypeCrit,V_WBS,Sel_WBS)/1000000 -> 218.82848 | D65: =SUMIFS(V_BorFY1,V_Type,Sel_TypeCrit,V_WBS,Sel_WBS)/1000000 -> 18.301141
B66: =(P_RJ+2)&"" -> 2028 | C66: =SUMIFS(V_OmzRJ2,V_Type,Sel_TypeCrit,V_WBS,Sel_WBS)/1000000 -> 117.83072 | D66: =SUMIFS(V_BorRJ2,V_Type,Sel_TypeCrit,V_WBS,Sel_WBS)/1000000 -> 9.8544607
B67: =(P_RJ+3)&"" -> 2029 | C67: =SUMIFS(V_OmzRJ3,V_Type,Sel_TypeCrit,V_WBS,Sel_WBS)/1000000 -> 0 | D67: =SUMIFS(V_BorRJ3,V_Type,Sel_TypeCrit,V_WBS,Sel_WBS)/1000000 -> 0
B68: =(P_RJ+4)&"" -> 2030 | C68: =SUMIFS(V_OmzRJ4,V_Type,Sel_TypeCrit,V_WBS,Sel_WBS)/1000000 -> 0 | D68: =SUMIFS(V_BorRJ4,V_Type,Sel_TypeCrit,V_WBS,Sel_WBS)/1000000 -> 0
B69: =(P_RJ+5)&"" -> 2031 | C69: =SUMIFS(V_OmzRJ5,V_Type,Sel_TypeCrit,V_WBS,Sel_WBS)/1000000 -> 0 | D69: =SUMIFS(V_BorRJ5,V_Type,Sel_TypeCrit,V_WBS,Sel_WBS)/1000000 -> 0
B70: =(P_RJ+6)&"" -> 2032 | C70: =SUMIFS(V_OmzRJ6,V_Type,Sel_TypeCrit,V_WBS,Sel_WBS)/1000000 -> 0 | D70: =SUMIFS(V_BorRJ6,V_Type,Sel_TypeCrit,V_WBS,Sel_WBS)/1000000 -> 0
B71: =(P_RJ+7)&"" -> 2033 | C71: =SUMIFS(V_OmzRJ7,V_Type,Sel_TypeCrit,V_WBS,Sel_WBS)/1000000 -> 0 | D71: =SUMIFS(V_BorRJ7,V_Type,Sel_TypeCrit,V_WBS,Sel_WBS)/1000000 -> 0
B72: =(P_RJ+8)&"" -> 2034 | C72: =SUMIFS(V_OmzRJ8,V_Type,Sel_TypeCrit,V_WBS,Sel_WBS)/1000000 -> 0 | D72: =SUMIFS(V_BorRJ8,V_Type,Sel_TypeCrit,V_WBS,Sel_WBS)/1000000 -> 0
B73: Onverdeeld | C73: =SUMIFS(V_OmzONV,V_Type,Sel_TypeCrit,V_WBS,Sel_WBS)/1000000 -> 0 | D73: =SUMIFS(V_BorONV,V_Type,Sel_TypeCrit,V_WBS,Sel_WBS)/1000000 -> 0

Sheet RDFO
B1: ="RDFO "&P_Regio&" — doeljaar "&Sel_Doeljaar&" · bedragen in "&P_Eenheid -> RDFO Demo Regio — doeljaar 2026 · bedragen in EUR x 1.000
B2: ="Versiejaar "&P_VJ&" · geselecteerde versie: "&Sel_Label&" · vergeleken met "&IF(Sel_Prev="","–",Sel_Prev)&" · upload peildatum "&P_PeilTxt&" · selectie wijzigen op Dashboard" -> Versiejaar 2026 · geselecteerde versie: Q3 2026 (vastgesteld) · vergeleken met Q2 · upload peildatum 30-09-2026 · selectie wijzigen op Dashboard
C5: Budget | D5: Q1 | E5: Q2 | F5: Q3 | G5: Q4 | H5: Upload | J5: Sel | O5: Vorige
B6: Rubriek | C6: ="Budget"&CHAR(10)&"FY "&Sel_Doeljaar -> Budget FY 2026 | D6: ="Q1 "&P_VJ&CHAR(10)&"FY-prognose"&IF(CALC_Versies!$F$6>0," ●","") -> Q1 2026 FY-prognose | E6: ="Q2 "&P_VJ&CHAR(10)&"FY-prognose"&IF(CALC_Versies!$F$7>0," ●","") -> Q2 2026 FY-prognose | F6: ="Q3 "&P_VJ&CHAR(10)&"FY-prognose"&IF(CALC_Versies!$F$8>0," ●","") -> Q3 2026 FY-prognose | G6: ="Q4 "&P_VJ&CHAR(10)&"FY-prognose"&IF(CALC_Versies!$F$9>0," ●","") -> Q4 2026 FY-prognose | H6: ="Upload "&P_PeilTxt&CHAR(10)&"concept" -> Upload 30-09-2026 concept | J6: ="Geselecteerd"&CHAR(10)&Sel_Versie&" FY" -> Geselecteerd Q3 FY | K6: ="Realisatie YTD"&CHAR(10)&"zelfde peildatum" -> Realisatie YTD zelfde peildatum | L6: ="To go"&CHAR(10)&"(FY − YTD)" -> To go (FY − YTD) | M6: ="Δ geselect."&CHAR(10)&"vs Budget" -> Δ geselect. vs Budget | N6: ="Δ geselect."&CHAR(10)&"vs "&IF(Sel_Prev="","vorige",Sel_Prev) -> Δ geselect. vs Q2 | O6: Vorige versie (hulp) | P6: Definitie / bron
B7: Omzet opstal | C7: =IF(ISNUMBER(CALC_Versies!$G$5),CALC_Versies!$G$5/P_Factor,CALC_Versies!$G$5) -> 113431.26 | D7: =IF(ISNUMBER(CALC_Versies!$G$6),CALC_Versies!$G$6/P_Factor,CALC_Versies!$G$6) -> 111433.4 | E7: =IF(ISNUMBER(CALC_Versies!$G$7),CALC_Versies!$G$7/P_Factor,CALC_Versies!$G$7) -> 106938.2 | F7: =IF(ISNUMBER(CALC_Versies!$G$8),CALC_Versies!$G$8/P_Factor,CALC_Versies!$G$8) -> 108436.6 | G7: =IF(ISNUMBER(CALC_Versies!$G$9),CALC_Versies!$G$9/P_Factor,CALC_Versies!$G$9) -> n.b. | H7: =IF(ISNUMBER(CALC_Versies!$G$10),CALC_Versies!$G$10/P_Factor,CALC_Versies!$G$10) -> 108436.6 | J7: =IF(ISNUMBER(CALC_Versies!$G$11),CALC_Versies!$G$11/P_Factor,CALC_Versies!$G$11) -> 108436.6 | K7: =IF(ISNUMBER(CALC_Versies!$K$11),CALC_Versies!$K$11/P_Factor,CALC_Versies!$K$11) -> 70483.79 | L7: =IF(K7="n.v.t.",J7,IF(AND(ISNUMBER(J7),ISNUMBER(K7)),J7-K7,"n.b.")) -> 37952.81 | M7: =IF(AND(ISNUMBER(J7),ISNUMBER(C7)),J7-C7,"n.b.") -> -4994.66 | N7: =IF(AND(ISNUMBER(J7),ISNUMBER(O7)),J7-O7,"n.b.") -> 1498.398 | O7: =IF(ISNUMBER(CALC_Versies!$G$12),CALC_Versies!$G$12/P_Factor,CALC_Versies!$G$12) -> 106938.2 | P7: ZPMW03, Type=Opstal (Mapping). FY RJ = −Bedrijfsopbrengsten LJ − OP.BOB RJ; RJ+1 = −OP.BOB RJ+1
B8: Omzet deelnemingen | C8: =IF(ISNUMBER(CALC_Versies!$H$5),CALC_Versies!$H$5/P_Factor,CALC_Versies!$H$5) -> 5094.18 | D8: =IF(ISNUMBER(CALC_Versies!$H$6),CALC_Versies!$H$6/P_Factor,CALC_Versies!$H$6) -> 5320.588 | E8: =IF(ISNUMBER(CALC_Versies!$H$7),CALC_Versies!$H$7/P_Factor,CALC_Versies!$H$7) -> 5830.006 | F8: =IF(ISNUMBER(CALC_Versies!$H$8),CALC_Versies!$H$8/P_Factor,CALC_Versies!$H$8) -> 5660.2 | G8: =IF(ISNUMBER(CALC_Versies!$H$9),CALC_Versies!$H$9/P_Factor,CALC_Versies!$H$9) -> n.b. | H8: =IF(ISNUMBER(CALC_Versies!$H$10),CALC_Versies!$H$10/P_Factor,CALC_Versies!$H$10) -> 5660.2 | J8: =IF(ISNUMBER(CALC_Versies!$H$11),CALC_Versies!$H$11/P_Factor,CALC_Versies!$H$11) -> 5660.2 | K8: =IF(ISNUMBER(CALC_Versies!$L$11),CALC_Versies!$L$11/P_Factor,CALC_Versies!$L$11) -> 3679.13 | L8: =IF(K8="n.v.t.",J8,IF(AND(ISNUMBER(J8),ISNUMBER(K8)),J8-K8,"n.b.")) -> 1981.07 | M8: =IF(AND(ISNUMBER(J8),ISNUMBER(C8)),J8-C8,"n.b.") -> 566.02 | N8: =IF(AND(ISNUMBER(J8),ISNUMBER(O8)),J8-O8,"n.b.") -> -169.806 | O8: =IF(ISNUMBER(CALC_Versies!$H$12),CALC_Versies!$H$12/P_Factor,CALC_Versies!$H$12) -> 5830.006 | P8: ZPMW03, Type=Deelneming (Mapping). Al op aandeelbasis; geen aandeel toegepast
B9: Taakstelling omzet | C9: =IF(ISNUMBER(CALC_Versies!$Y$5),CALC_Versies!$Y$5/P_Factor,CALC_Versies!$Y$5) -> n.b. | D9: =IF(ISNUMBER(CALC_Versies!$Y$6),CALC_Versies!$Y$6/P_Factor,CALC_Versies!$Y$6) -> n.b. | E9: =IF(ISNUMBER(CALC_Versies!$Y$7),CALC_Versies!$Y$7/P_Factor,CALC_Versies!$Y$7) -> n.b. | F9: =IF(ISNUMBER(CALC_Versies!$Y$8),CALC_Versies!$Y$8/P_Factor,CALC_Versies!$Y$8) -> n.b. | G9: =IF(ISNUMBER(CALC_Versies!$Y$9),CALC_Versies!$Y$9/P_Factor,CALC_Versies!$Y$9) -> n.b. | H9: =IF(ISNUMBER(CALC_Versies!$Y$10),CALC_Versies!$Y$10/P_Factor,CALC_Versies!$Y$10) -> n.b. | J9: =IF(ISNUMBER(CALC_Versies!$Y$11),CALC_Versies!$Y$11/P_Factor,CALC_Versies!$Y$11) -> n.b. | K9: =IF(ISNUMBER(CALC_Versies!$AF$11),CALC_Versies!$AF$11/P_Factor,CALC_Versies!$AF$11) -> n.b. | L9: ="" | M9: =IF(AND(ISNUMBER(J9),ISNUMBER(C9)),J9-C9,"n.b.") -> n.b. | N9: =IF(AND(ISNUMBER(J9),ISNUMBER(O9)),J9-O9,"n.b.") -> n.b. | O9: =IF(ISNUMBER(CALC_Versies!$Y$12),CALC_Versies!$Y$12/P_Factor,CALC_Versies!$Y$12) -> n.b. | P9: Invoer_Aanvullend (rubriek Taakstelling omzet)
B10: Interne eliminaties | C10: =IF(ISNUMBER(CALC_Versies!$Z$5),CALC_Versies!$Z$5/P_Factor,CALC_Versies!$Z$5) -> n.b. | D10: =IF(ISNUMBER(CALC_Versies!$Z$6),CALC_Versies!$Z$6/P_Factor,CALC_Versies!$Z$6) -> n.b. | E10: =IF(ISNUMBER(CALC_Versies!$Z$7),CALC_Versies!$Z$7/P_Factor,CALC_Versies!$Z$7) -> n.b. | F10: =IF(ISNUMBER(CALC_Versies!$Z$8),CALC_Versies!$Z$8/P_Factor,CALC_Versies!$Z$8) -> n.b. | G10: =IF(ISNUMBER(CALC_Versies!$Z$9),CALC_Versies!$Z$9/P_Factor,CALC_Versies!$Z$9) -> n.b. | H10: =IF(ISNUMBER(CALC_Versies!$Z$10),CALC_Versies!$Z$10/P_Factor,CALC_Versies!$Z$10) -> n.b. | J10: =IF(ISNUMBER(CALC_Versies!$Z$11),CALC_Versies!$Z$11/P_Factor,CALC_Versies!$Z$11) -> n.b. | K10: =IF(ISNUMBER(CALC_Versies!$AG$11),CALC_Versies!$AG$11/P_Factor,CALC_Versies!$AG$11) -> n.b. | L10: ="" | M10: =IF(AND(ISNUMBER(J10),ISNUMBER(C10)),J10-C10,"n.b.") -> n.b. | N10: =IF(AND(ISNUMBER(J10),ISNUMBER(O10)),J10-O10,"n.b.") -> n.b. | O10: =IF(ISNUMBER(CALC_Versies!$Z$12),CALC_Versies!$Z$12/P_Factor,CALC_Versies!$Z$12) -> n.b. | P10: Invoer_Aanvullend
B11: Omzet old | C11: =IF(ISNUMBER(C7),SUM(C7,C8,C9,C10),C7) -> 118525.44 | D11: =IF(ISNUMBER(D7),SUM(D7,D8,D9,D10),D7) -> 116753.98 | E11: =IF(ISNUMBER(E7),SUM(E7,E8,E9,E10),E7) -> 112768.21 | F11: =IF(ISNUMBER(F7),SUM(F7,F8,F9,F10),F7) -> 114096.8 | G11: =IF(ISNUMBER(G7),SUM(G7,G8,G9,G10),G7) -> n.b. | H11: =IF(ISNUMBER(H7),SUM(H7,H8,H9,H10),H7) -> 114096.8 | J11: =IF(ISNUMBER(J7),SUM(J7,J8,J9,J10),J7) -> 114096.8 | K11: =IF(ISNUMBER(K7),SUM(K7,K8,K9,K10),K7) -> 74162.92 | L11: =IF(K11="n.v.t.",J11,IF(AND(ISNUMBER(J11),ISNUMBER(K11)),J11-K11,"n.b.")) -> 39933.88 | M11: =IF(AND(ISNUMBER(J11),ISNUMBER(C11)),J11-C11,"n.b.") -> -4428.64 | N11: =IF(AND(ISNUMBER(J11),ISNUMBER(O11)),J11-O11,"n.b.") -> 1328.592 | O11: =IF(ISNUMBER(O7),SUM(O7,O8,O9,O10),O7) -> 112768.21 | P11: Subtotaal: opstal + deelnemingen + taakstelling + interne eliminaties
B12: IFRS-eliminaties | C12: =IF(ISNUMBER(CALC_Versies!$AA$5),CALC_Versies!$AA$5/P_Factor,CALC_Versies!$AA$5) -> n.b. | D12: =IF(ISNUMBER(CALC_Versies!$AA$6),CALC_Versies!$AA$6/P_Factor,CALC_Versies!$AA$6) -> n.b. | E12: =IF(ISNUMBER(CALC_Versies!$AA$7),CALC_Versies!$AA$7/P_Factor,CALC_Versies!$AA$7) -> n.b. | F12: =IF(ISNUMBER(CALC_Versies!$AA$8),CALC_Versies!$AA$8/P_Factor,CALC_Versies!$AA$8) -> n.b. | G12: =IF(ISNUMBER(CALC_Versies!$AA$9),CALC_Versies!$AA$9/P_Factor,CALC_Versies!$AA$9) -> n.b. | H12: =IF(ISNUMBER(CALC_Versies!$AA$10),CALC_Versies!$AA$10/P_Factor,CALC_Versies!$AA$10) -> n.b. | J12: =IF(ISNUMBER(CALC_Versies!$AA$11),CALC_Versies!$AA$11/P_Factor,CALC_Versies!$AA$11) -> n.b. | K12: =IF(ISNUMBER(CALC_Versies!$AH$11),CALC_Versies!$AH$11/P_Factor,CALC_Versies!$AH$11) -> n.b. | L12: ="" | M12: =IF(AND(ISNUMBER(J12),ISNUMBER(C12)),J12-C12,"n.b.") -> n.b. | N12: =IF(AND(ISNUMBER(J12),ISNUMBER(O12)),J12-O12,"n.b.") -> n.b. | O12: =IF(ISNUMBER(CALC_Versies!$AA$12),CALC_Versies!$AA$12/P_Factor,CALC_Versies!$AA$12) -> n.b. | P12: Invoer_Aanvullend. IFRS J/N wordt NIET automatisch geëlimineerd (zie memo)
B13: Omzet IFRS | C13: =IF(ISNUMBER(C11),SUM(C11,C12),C11) -> 118525.44 | D13: =IF(ISNUMBER(D11),SUM(D11,D12),D11) -> 116753.98 | E13: =IF(ISNUMBER(E11),SUM(E11,E12),E11) -> 112768.21 | F13: =IF(ISNUMBER(F11),SUM(F11,F12),F11) -> 114096.8 | G13: =IF(ISNUMBER(G11),SUM(G11,G12),G11) -> n.b. | H13: =IF(ISNUMBER(H11),SUM(H11,H12),H11) -> 114096.8 | J13: =IF(ISNUMBER(J11),SUM(J11,J12),J11) -> 114096.8 | K13: =IF(ISNUMBER(K11),SUM(K11,K12),K11) -> 74162.92 | L13: =IF(K13="n.v.t.",J13,IF(AND(ISNUMBER(J13),ISNUMBER(K13)),J13-K13,"n.b.")) -> 39933.88 | M13: =IF(AND(ISNUMBER(J13),ISNUMBER(C13)),J13-C13,"n.b.") -> -4428.64 | N13: =IF(AND(ISNUMBER(J13),ISNUMBER(O13)),J13-O13,"n.b.") -> 1328.592 | O13: =IF(ISNUMBER(O11),SUM(O11,O12),O11) -> 112768.21 | P13: Omzet old + IFRS-eliminaties
B15: Projectresultaat (BOR) opstal | C15: =IF(ISNUMBER(CALC_Versies!$I$5),CALC_Versies!$I$5/P_Factor,CALC_Versies!$I$5) -> 10424.156 | D15: =IF(ISNUMBER(CALC_Versies!$I$6),CALC_Versies!$I$6/P_Factor,CALC_Versies!$I$6) -> 10291.72 | E15: =IF(ISNUMBER(CALC_Versies!$I$7),CALC_Versies!$I$7/P_Factor,CALC_Versies!$I$7) -> 9993.7389 | F15: =IF(ISNUMBER(CALC_Versies!$I$8),CALC_Versies!$I$8/P_Factor,CALC_Versies!$I$8) -> 10093.066 | G15: =IF(ISNUMBER(CALC_Versies!$I$9),CALC_Versies!$I$9/P_Factor,CALC_Versies!$I$9) -> n.b. | H15: =IF(ISNUMBER(CALC_Versies!$I$10),CALC_Versies!$I$10/P_Factor,CALC_Versies!$I$10) -> 10093.066 | J15: =IF(ISNUMBER(CALC_Versies!$I$11),CALC_Versies!$I$11/P_Factor,CALC_Versies!$I$11) -> 10093.066 | K15: =IF(ISNUMBER(CALC_Versies!$M$11),CALC_Versies!$M$11/P_Factor,CALC_Versies!$M$11) -> 6560.4929 | L15: =IF(K15="n.v.t.",J15,IF(AND(ISNUMBER(J15),ISNUMBER(K15)),J15-K15,"n.b.")) -> 3532.5731 | M15: =IF(AND(ISNUMBER(J15),ISNUMBER(C15)),J15-C15,"n.b.") -> -331.0902 | N15: =IF(AND(ISNUMBER(J15),ISNUMBER(O15)),J15-O15,"n.b.") -> 99.32706 | O15: =IF(ISNUMBER(CALC_Versies!$I$12),CALC_Versies!$I$12/P_Factor,CALC_Versies!$I$12) -> 9993.7389 | P15: ZPMW03: FY RJ = −Bruto (omzet) result. LJ − OP.BOR RJ. Verlies blijft negatief (geen ABS)
B16: Projectresultaat (BOR) deelnemingen | C16: =IF(ISNUMBER(CALC_Versies!$J$5),CALC_Versies!$J$5/P_Factor,CALC_Versies!$J$5) -> 345.7188 | D16: =IF(ISNUMBER(CALC_Versies!$J$6),CALC_Versies!$J$6/P_Factor,CALC_Versies!$J$6) -> 361.08408 | E16: =IF(ISNUMBER(CALC_Versies!$J$7),CALC_Versies!$J$7/P_Factor,CALC_Versies!$J$7) -> 395.65596 | F16: =IF(ISNUMBER(CALC_Versies!$J$8),CALC_Versies!$J$8/P_Factor,CALC_Versies!$J$8) -> 384.132 | G16: =IF(ISNUMBER(CALC_Versies!$J$9),CALC_Versies!$J$9/P_Factor,CALC_Versies!$J$9) -> n.b. | H16: =IF(ISNUMBER(CALC_Versies!$J$10),CALC_Versies!$J$10/P_Factor,CALC_Versies!$J$10) -> 384.132 | J16: =IF(ISNUMBER(CALC_Versies!$J$11),CALC_Versies!$J$11/P_Factor,CALC_Versies!$J$11) -> 384.132 | K16: =IF(ISNUMBER(CALC_Versies!$N$11),CALC_Versies!$N$11/P_Factor,CALC_Versies!$N$11) -> 249.6858 | L16: =IF(K16="n.v.t.",J16,IF(AND(ISNUMBER(J16),ISNUMBER(K16)),J16-K16,"n.b.")) -> 134.4462 | M16: =IF(AND(ISNUMBER(J16),ISNUMBER(C16)),J16-C16,"n.b.") -> 38.4132 | N16: =IF(AND(ISNUMBER(J16),ISNUMBER(O16)),J16-O16,"n.b.") -> -11.52396 | O16: =IF(ISNUMBER(CALC_Versies!$J$12),CALC_Versies!$J$12/P_Factor,CALC_Versies!$J$12) -> 395.65596 | P16: Idem, Type=Deelneming
B17: Projectresultaten / BOR | C17: =IF(ISNUMBER(C15),SUM(C15,C16),C15) -> 10769.875 | D17: =IF(ISNUMBER(D15),SUM(D15,D16),D15) -> 10652.804 | E17: =IF(ISNUMBER(E15),SUM(E15,E16),E15) -> 10389.395 | F17: =IF(ISNUMBER(F15),SUM(F15,F16),F15) -> 10477.198 | G17: =IF(ISNUMBER(G15),SUM(G15,G16),G15) -> n.b. | H17: =IF(ISNUMBER(H15),SUM(H15,H16),H15) -> 10477.198 | J17: =IF(ISNUMBER(J15),SUM(J15,J16),J15) -> 10477.198 | K17: =IF(ISNUMBER(K15),SUM(K15,K16),K15) -> 6810.1787 | L17: =IF(K17="n.v.t.",J17,IF(AND(ISNUMBER(J17),ISNUMBER(K17)),J17-K17,"n.b.")) -> 3667.0193 | M17: =IF(AND(ISNUMBER(J17),ISNUMBER(C17)),J17-C17,"n.b.") -> -292.677 | N17: =IF(AND(ISNUMBER(J17),ISNUMBER(O17)),J17-O17,"n.b.") -> 87.8031 | O17: =IF(ISNUMBER(O15),SUM(O15,O16),O15) -> 10389.395 | P17: Subtotaal BOR
B18: AK-dekking | C18: =IF(ISNUMBER(CALC_Versies!$AB$5),CALC_Versies!$AB$5/P_Factor,CALC_Versies!$AB$5) -> n.b. | D18: =IF(ISNUMBER(CALC_Versies!$AB$6),CALC_Versies!$AB$6/P_Factor,CALC_Versies!$AB$6) -> n.b. | E18: =IF(ISNUMBER(CALC_Versies!$AB$7),CALC_Versies!$AB$7/P_Factor,CALC_Versies!$AB$7) -> n.b. | F18: =IF(ISNUMBER(CALC_Versies!$AB$8),CALC_Versies!$AB$8/P_Factor,CALC_Versies!$AB$8) -> n.b. | G18: =IF(ISNUMBER(CALC_Versies!$AB$9),CALC_Versies!$AB$9/P_Factor,CALC_Versies!$AB$9) -> n.b. | H18: =IF(ISNUMBER(CALC_Versies!$AB$10),CALC_Versies!$AB$10/P_Factor,CALC_Versies!$AB$10) -> n.b. | J18: =IF(ISNUMBER(CALC_Versies!$AB$11),CALC_Versies!$AB$11/P_Factor,CALC_Versies!$AB$11) -> n.b. | K18: =IF(ISNUMBER(CALC_Versies!$AI$11),CALC_Versies!$AI$11/P_Factor,CALC_Versies!$AI$11) -> n.b. | L18: ="" | M18: =IF(AND(ISNUMBER(J18),ISNUMBER(C18)),J18-C18,"n.b.") -> n.b. | N18: =IF(AND(ISNUMBER(J18),ISNUMBER(O18)),J18-O18,"n.b.") -> n.b. | O18: =IF(ISNUMBER(CALC_Versies!$AB$12),CALC_Versies!$AB$12/P_Factor,CALC_Versies!$AB$12) -> n.b. | P18: Invoer_Aanvullend. Geen generiek AK-percentage toegepast
B19: Fees | C19: =IF(ISNUMBER(CALC_Versies!$AC$5),CALC_Versies!$AC$5/P_Factor,CALC_Versies!$AC$5) -> n.b. | D19: =IF(ISNUMBER(CALC_Versies!$AC$6),CALC_Versies!$AC$6/P_Factor,CALC_Versies!$AC$6) -> n.b. | E19: =IF(ISNUMBER(CALC_Versies!$AC$7),CALC_Versies!$AC$7/P_Factor,CALC_Versies!$AC$7) -> n.b. | F19: =IF(ISNUMBER(CALC_Versies!$AC$8),CALC_Versies!$AC$8/P_Factor,CALC_Versies!$AC$8) -> n.b. | G19: =IF(ISNUMBER(CALC_Versies!$AC$9),CALC_Versies!$AC$9/P_Factor,CALC_Versies!$AC$9) -> n.b. | H19: =IF(ISNUMBER(CALC_Versies!$AC$10),CALC_Versies!$AC$10/P_Factor,CALC_Versies!$AC$10) -> n.b. | J19: =IF(ISNUMBER(CALC_Versies!$AC$11),CALC_Versies!$AC$11/P_Factor,CALC_Versies!$AC$11) -> n.b. | K19: =IF(ISNUMBER(CALC_Versies!$AJ$11),CALC_Versies!$AJ$11/P_Factor,CALC_Versies!$AJ$11) -> n.b. | L19: ="" | M19: =IF(AND(ISNUMBER(J19),ISNUMBER(C19)),J19-C19,"n.b.") -> n.b. | N19: =IF(AND(ISNUMBER(J19),ISNUMBER(O19)),J19-O19,"n.b.") -> n.b. | O19: =IF(ISNUMBER(CALC_Versies!$AC$12),CALC_Versies!$AC$12/P_Factor,CALC_Versies!$AC$12) -> n.b. | P19: Invoer_Aanvullend
B20: Overige resultaten | C20: =IF(ISNUMBER(CALC_Versies!$AD$5),CALC_Versies!$AD$5/P_Factor,CALC_Versies!$AD$5) -> n.b. | D20: =IF(ISNUMBER(CALC_Versies!$AD$6),CALC_Versies!$AD$6/P_Factor,CALC_Versies!$AD$6) -> n.b. | E20: =IF(ISNUMBER(CALC_Versies!$AD$7),CALC_Versies!$AD$7/P_Factor,CALC_Versies!$AD$7) -> n.b. | F20: =IF(ISNUMBER(CALC_Versies!$AD$8),CALC_Versies!$AD$8/P_Factor,CALC_Versies!$AD$8) -> n.b. | G20: =IF(ISNUMBER(CALC_Versies!$AD$9),CALC_Versies!$AD$9/P_Factor,CALC_Versies!$AD$9) -> n.b. | H20: =IF(ISNUMBER(CALC_Versies!$AD$10),CALC_Versies!$AD$10/P_Factor,CALC_Versies!$AD$10) -> n.b. | J20: =IF(ISNUMBER(CALC_Versies!$AD$11),CALC_Versies!$AD$11/P_Factor,CALC_Versies!$AD$11) -> n.b. | K20: =IF(ISNUMBER(CALC_Versies!$AK$11),CALC_Versies!$AK$11/P_Factor,CALC_Versies!$AK$11) -> n.b. | L20: ="" | M20: =IF(AND(ISNUMBER(J20),ISNUMBER(C20)),J20-C20,"n.b.") -> n.b. | N20: =IF(AND(ISNUMBER(J20),ISNUMBER(O20)),J20-O20,"n.b.") -> n.b. | O20: =IF(ISNUMBER(CALC_Versies!$AD$12),CALC_Versies!$AD$12/P_Factor,CALC_Versies!$AD$12) -> n.b. | P20: Invoer_Aanvullend
B21: Taakstelling EBIT | C21: =IF(ISNUMBER(CALC_Versies!$AE$5),CALC_Versies!$AE$5/P_Factor,CALC_Versies!$AE$5) -> n.b. | D21: =IF(ISNUMBER(CALC_Versies!$AE$6),CALC_Versies!$AE$6/P_Factor,CALC_Versies!$AE$6) -> n.b. | E21: =IF(ISNUMBER(CALC_Versies!$AE$7),CALC_Versies!$AE$7/P_Factor,CALC_Versies!$AE$7) -> n.b. | F21: =IF(ISNUMBER(CALC_Versies!$AE$8),CALC_Versies!$AE$8/P_Factor,CALC_Versies!$AE$8) -> n.b. | G21: =IF(ISNUMBER(CALC_Versies!$AE$9),CALC_Versies!$AE$9/P_Factor,CALC_Versies!$AE$9) -> n.b. | H21: =IF(ISNUMBER(CALC_Versies!$AE$10),CALC_Versies!$AE$10/P_Factor,CALC_Versies!$AE$10) -> n.b. | J21: =IF(ISNUMBER(CALC_Versies!$AE$11),CALC_Versies!$AE$11/P_Factor,CALC_Versies!$AE$11) -> n.b. | K21: =IF(ISNUMBER(CALC_Versies!$AL$11),CALC_Versies!$AL$11/P_Factor,CALC_Versies!$AL$11) -> n.b. | L21: ="" | M21: =IF(AND(ISNUMBER(J21),ISNUMBER(C21)),J21-C21,"n.b.") -> n.b. | N21: =IF(AND(ISNUMBER(J21),ISNUMBER(O21)),J21-O21,"n.b.") -> n.b. | O21: =IF(ISNUMBER(CALC_Versies!$AE$12),CALC_Versies!$AE$12/P_Factor,CALC_Versies!$AE$12) -> n.b. | P21: Invoer_Aanvullend
B22: EBIT-bijdrage | C22: =IF(ISNUMBER(C17),SUM(C17,C18,C19,C20,C21),C17) -> 10769.875 | D22: =IF(ISNUMBER(D17),SUM(D17,D18,D19,D20,D21),D17) -> 10652.804 | E22: =IF(ISNUMBER(E17),SUM(E17,E18,E19,E20,E21),E17) -> 10389.395 | F22: =IF(ISNUMBER(F17),SUM(F17,F18,F19,F20,F21),F17) -> 10477.198 | G22: =IF(ISNUMBER(G17),SUM(G17,G18,G19,G20,G21),G17) -> n.b. | H22: =IF(ISNUMBER(H17),SUM(H17,H18,H19,H20,H21),H17) -> 10477.198 | J22: =IF(ISNUMBER(J17),SUM(J17,J18,J19,J20,J21),J17) -> 10477.198 | K22: =IF(ISNUMBER(K17),SUM(K17,K18,K19,K20,K21),K17) -> 6810.1787 | L22: =IF(K22="n.v.t.",J22,IF(AND(ISNUMBER(J22),ISNUMBER(K22)),J22-K22,"n.b.")) -> 3667.0193 | M22: =IF(AND(ISNUMBER(J22),ISNUMBER(C22)),J22-C22,"n.b.") -> -292.677 | N22: =IF(AND(ISNUMBER(J22),ISNUMBER(O22)),J22-O22,"n.b.") -> 87.8031 | O22: =IF(ISNUMBER(O17),SUM(O17,O18,O19,O20,O21),O17) -> 10389.395 | P22: BOR + AK-dekking + fees + overige resultaten + taakstelling EBIT
B24: BOR % | C24: =IF(AND(ISNUMBER(C17),ISNUMBER(C28)),IF(C28<>0,C17/C28,"n.b."),"n.b.") -> 0.090865514 | D24: =IF(AND(ISNUMBER(D17),ISNUMBER(D28)),IF(D28<>0,D17/D28,"n.b."),"n.b.") -> 0.091241462 | E24: =IF(AND(ISNUMBER(E17),ISNUMBER(E28)),IF(E28<>0,E17/E28,"n.b."),"n.b.") -> 0.092130531 | F24: =IF(AND(ISNUMBER(F17),ISNUMBER(F28)),IF(F28<>0,F17/F28,"n.b."),"n.b.") -> 0.091827273 | G24: =IF(AND(ISNUMBER(G17),ISNUMBER(G28)),IF(G28<>0,G17/G28,"n.b."),"n.b.") -> n.b. | H24: =IF(AND(ISNUMBER(H17),ISNUMBER(H28)),IF(H28<>0,H17/H28,"n.b."),"n.b.") -> 0.091827273 | J24: =IF(AND(ISNUMBER(J17),ISNUMBER(J28)),IF(J28<>0,J17/J28,"n.b."),"n.b.") -> 0.091827273 | K24: =IF(AND(ISNUMBER(K17),ISNUMBER(K28)),IF(K28<>0,K17/K28,"n.b."),"n.b.") -> 0.091827273 | L24: ="" | M24: =IF(AND(ISNUMBER(J24),ISNUMBER(C24)),J24-C24,"n.b.") -> 0.00096175922 | N24: =IF(AND(ISNUMBER(J24),ISNUMBER(O24)),J24-O24,"n.b.") -> -0.00030325817 | O24: =IF(AND(ISNUMBER(O17),ISNUMBER(O28)),IF(O28<>0,O17/O28,"n.b."),"n.b.") -> 0.092130531 | P24: Totale BOR / totale projectomzet (opstal + deelnemingen). Geen gemiddelde van projectpercentages
B25: EBIT % | C25: =IF(AND(ISNUMBER(C22),ISNUMBER(C11)),IF(C11<>0,C22/C11,"n.b."),"n.b.") -> 0.090865514 | D25: =IF(AND(ISNUMBER(D22),ISNUMBER(D11)),IF(D11<>0,D22/D11,"n.b."),"n.b.") -> 0.091241462 | E25: =IF(AND(ISNUMBER(E22),ISNUMBER(E11)),IF(E11<>0,E22/E11,"n.b."),"n.b.") -> 0.092130531 | F25: =IF(AND(ISNUMBER(F22),ISNUMBER(F11)),IF(F11<>0,F22/F11,"n.b."),"n.b.") -> 0.091827273 | G25: =IF(AND(ISNUMBER(G22),ISNUMBER(G11)),IF(G11<>0,G22/G11,"n.b."),"n.b.") -> n.b. | H25: =IF(AND(ISNUMBER(H22),ISNUMBER(H11)),IF(H11<>0,H22/H11,"n.b."),"n.b.") -> 0.091827273 | J25: =IF(AND(ISNUMBER(J22),ISNUMBER(J11)),IF(J11<>0,J22/J11,"n.b."),"n.b.") -> 0.091827273 | K25: =IF(AND(ISNUMBER(K22),ISNUMBER(K11)),IF(K11<>0,K22/K11,"n.b."),"n.b.") -> 0.091827273 | L25: ="" | M25: =IF(AND(ISNUMBER(J25),ISNUMBER(C25)),J25-C25,"n.b.") -> 0.00096175922 | N25: =IF(AND(ISNUMBER(J25),ISNUMBER(O25)),J25-O25,"n.b.") -> -0.00030325817 | O25: =IF(AND(ISNUMBER(O22),ISNUMBER(O11)),IF(O11<>0,O22/O11,"n.b."),"n.b.") -> 0.092130531 | P25: EBIT-bijdrage / Omzet old (definitie te bevestigen, zie Productievragen)
B27: Memo
B28: Omzet projecten (noemer BOR %) | C28: =IF(ISNUMBER(C7),SUM(C7,C8),C7) -> 118525.44 | D28: =IF(ISNUMBER(D7),SUM(D7,D8),D7) -> 116753.98 | E28: =IF(ISNUMBER(E7),SUM(E7,E8),E7) -> 112768.21 | F28: =IF(ISNUMBER(F7),SUM(F7,F8),F7) -> 114096.8 | G28: =IF(ISNUMBER(G7),SUM(G7,G8),G7) -> n.b. | H28: =IF(ISNUMBER(H7),SUM(H7,H8),H7) -> 114096.8 | J28: =IF(ISNUMBER(J7),SUM(J7,J8),J7) -> 114096.8 | K28: =IF(ISNUMBER(K7),SUM(K7,K8),K7) -> 74162.92 | L28: =IF(K28="n.v.t.",J28,IF(AND(ISNUMBER(J28),ISNUMBER(K28)),J28-K28,"n.b.")) -> 39933.88 | M28: =IF(AND(ISNUMBER(J28),ISNUMBER(C28)),J28-C28,"n.b.") -> -4428.64 | N28: =IF(AND(ISNUMBER(J28),ISNUMBER(O28)),J28-O28,"n.b.") -> 1328.592 | O28: =IF(ISNUMBER(O7),SUM(O7,O8),O7) -> 112768.21 | P28: Omzet opstal + deelnemingen
B29: waarvan projecten met IFRS = N | C29: =IF(ISNUMBER(CALC_Versies!$O$5),CALC_Versies!$O$5/P_Factor,CALC_Versies!$O$5) -> 5094.18 | D29: =IF(ISNUMBER(CALC_Versies!$O$6),CALC_Versies!$O$6/P_Factor,CALC_Versies!$O$6) -> 5320.588 | E29: =IF(ISNUMBER(CALC_Versies!$O$7),CALC_Versies!$O$7/P_Factor,CALC_Versies!$O$7) -> 5830.006 | F29: =IF(ISNUMBER(CALC_Versies!$O$8),CALC_Versies!$O$8/P_Factor,CALC_Versies!$O$8) -> 5660.2 | G29: =IF(ISNUMBER(CALC_Versies!$O$9),CALC_Versies!$O$9/P_Factor,CALC_Versies!$O$9) -> n.b. | H29: =IF(ISNUMBER(CALC_Versies!$O$10),CALC_Versies!$O$10/P_Factor,CALC_Versies!$O$10) -> 5660.2 | J29: =IF(ISNUMBER(CALC_Versies!$O$11),CALC_Versies!$O$11/P_Factor,CALC_Versies!$O$11) -> 5660.2 | K29: ="" | L29: ="" | M29: =IF(AND(ISNUMBER(J29),ISNUMBER(C29)),J29-C29,"n.b.") -> 566.02 | N29: =IF(AND(ISNUMBER(J29),ISNUMBER(O29)),J29-O29,"n.b.") -> -169.806 | O29: =IF(ISNUMBER(CALC_Versies!$O$12),CALC_Versies!$O$12/P_Factor,CALC_Versies!$O$12) -> 5830.006 | P29: Informatief: IFRS J/N is een dimensie, geen automatische eliminatie- of consolidatieregel
B30: BOR projecten met IFRS = N | C30: =IF(ISNUMBER(CALC_Versies!$P$5),CALC_Versies!$P$5/P_Factor,CALC_Versies!$P$5) -> 345.7188 | D30: =IF(ISNUMBER(CALC_Versies!$P$6),CALC_Versies!$P$6/P_Factor,CALC_Versies!$P$6) -> 361.08408 | E30: =IF(ISNUMBER(CALC_Versies!$P$7),CALC_Versies!$P$7/P_Factor,CALC_Versies!$P$7) -> 395.65596 | F30: =IF(ISNUMBER(CALC_Versies!$P$8),CALC_Versies!$P$8/P_Factor,CALC_Versies!$P$8) -> 384.132 | G30: =IF(ISNUMBER(CALC_Versies!$P$9),CALC_Versies!$P$9/P_Factor,CALC_Versies!$P$9) -> n.b. | H30: =IF(ISNUMBER(CALC_Versies!$P$10),CALC_Versies!$P$10/P_Factor,CALC_Versies!$P$10) -> 384.132 | J30: =IF(ISNUMBER(CALC_Versies!$P$11),CALC_Versies!$P$11/P_Factor,CALC_Versies!$P$11) -> 384.132 | K30: ="" | L30: ="" | M30: =IF(AND(ISNUMBER(J30),ISNUMBER(C30)),J30-C30,"n.b.") -> 38.4132 | N30: =IF(AND(ISNUMBER(J30),ISNUMBER(O30)),J30-O30,"n.b.") -> -11.52396 | O30: =IF(ISNUMBER(CALC_Versies!$P$12),CALC_Versies!$P$12/P_Factor,CALC_Versies!$P$12) -> 395.65596 | P30: Informatief
B31: Woningverkopen (aantal, aandeelbasis) | C31: =CALC_Versies!$Q$5 -> 372 | D31: =CALC_Versies!$Q$6 -> 366 | E31: =CALC_Versies!$Q$7 -> 355 | F31: =CALC_Versies!$Q$8 -> 360 | G31: =CALC_Versies!$Q$9 -> n.b. | H31: =CALC_Versies!$Q$10 -> 360 | J31: =CALC_Versies!$Q$11 -> 360 | K31: =CALC_Versies!$R$11 -> 193 | L31: ="" | M31: =IF(AND(ISNUMBER(J31),ISNUMBER(C31)),J31-C31,"n.b.") -> -12 | N31: =IF(AND(ISNUMBER(J31),ISNUMBER(O31)),J31-O31,"n.b.") -> 5 | O31: =CALC_Versies!$Q$12 -> 355 | P31: Woningetalage 'Huidig jaar' (RJ) / 'Volgend jaar' (RJ+1). Verkopen ≠ opleveringen/transporten
B33: Leeswijzer
B34: • Budget/Q1–Q4 = vastgelegde (onveranderlijke) FY-jaarprognoses uit Vastlegging. Een nieuwe upload wijzigt deze kolommen niet. ● = versie bevat een correctie (revisie > 0).
B35: • 'Upload … concept' = live berekend uit SRC_ZPMW03/SRC_Woningetalage; wordt pas een versie na handmatige vastlegging (tab Vastleggen).
B36: • 'Realisatie YTD' (groen, cursief) is géén prognose: actual t/m de peildatum van de geselecteerde versie. To go = geselecteerde FY − realisatie van dezelfde peildatum.
B37: • n.b. = niet beschikbaar (geen vastgelegde of aanvullende invoer) — nooit stil als nul. n.v.t. = doeljaar ligt na het versiejaar, dus nog geen realisatie.
B38: • Oranje subtotaal = onvolledig: minstens één onderliggende post is n.b. De som bevat alleen de beschikbare posten.
B39: • Tekens: omzet en resultaat positief, verlies negatief (rood). Aanvullende invoer in managementteken (+ verhoogt omzet/resultaat).

Sheet Projecten
B1: ="Projectoverzicht "&P_Regio&" — omzet doeljaar "&Sel_Doeljaar&" ("&P_Eenheid&")" -> Projectoverzicht Demo Regio — omzet doeljaar 2026 (EUR x 1.000)
B2: ="Geselecteerde versie: "&Sel_Label&" · realisatie en to go van dezelfde peildatum · filter met de pijltjes in rij 9" -> Geselecteerde versie: Q3 2026 (vastgesteld) · realisatie en to go van dezelfde peildatum · filter met de pijltjes in rij 9
B6: Totaal (zichtbare regels) | E6: =IF(SUBTOTAL(102,E10:E109)=0,"n.b.",SUBTOTAL(109,E10:E109)) -> 118525.44 | F6: =IF(SUBTOTAL(102,F10:F109)=0,"n.b.",SUBTOTAL(109,F10:F109)) -> 116753.98 | G6: =IF(SUBTOTAL(102,G10:G109)=0,"n.b.",SUBTOTAL(109,G10:G109)) -> 112768.21 | H6: =IF(SUBTOTAL(102,H10:H109)=0,"n.b.",SUBTOTAL(109,H10:H109)) -> 114096.8 | I6: =IF(SUBTOTAL(102,I10:I109)=0,"n.b.",SUBTOTAL(109,I10:I109)) -> n.b. | J6: =IF(SUBTOTAL(102,J10:J109)=0,"n.b.",SUBTOTAL(109,J10:J109)) -> 114096.8 | K6: =IF(SUBTOTAL(102,K10:K109)=0,"n.b.",SUBTOTAL(109,K10:K109)) -> 114096.8 | L6: =IF(SUBTOTAL(102,L10:L109)=0,"n.b.",SUBTOTAL(109,L10:L109)) -> 74162.92 | ... N6: =IF(SUBTOTAL(102,N10:N109)=0,"n.b.",SUBTOTAL(109,N10:N109)) -> 10477.198 | O6: =IF(AND(ISNUMBER(N6),ISNUMBER(K6)),IF(K6<>0,N6/K6,"n.b."),"n.b.") -> 0.091827273 | P6: =IF(SUBTOTAL(102,P10:P109)=0,"n.b.",SUBTOTAL(109,P10:P109)) -> -4428.64 | Q6: =IF(SUBTOTAL(102,Q10:Q109)=0,"n.b.",SUBTOTAL(109,Q10:Q109)) -> 1328.592 | R6: =COUNTIF(R10:R109,"Verlies")&" verliesproject(en)" -> 2 verliesproject(en)
B7: Marge % totaal = som BOR / som omzet (geen gemiddelde). Realisatie en to go horen bij de peildatum van de geselecteerde versie.
E8: Budget | F8: Q1 | G8: Q2 | H8: Q3 | I8: Q4
A9: WBS-element | B9: Projectnaam | C9: Type | D9: IFRS | E9: ="Budget"&CHAR(10)&"FY "&Sel_Doeljaar -> Budget FY 2026 | F9: ="Q1 "&P_VJ&CHAR(10)&"FY" -> Q1 2026 FY | G9: ="Q2 "&P_VJ&CHAR(10)&"FY" -> Q2 2026 FY | H9: ="Q3 "&P_VJ&CHAR(10)&"FY" -> Q3 2026 FY | I9: ="Q4 "&P_VJ&CHAR(10)&"FY" -> Q4 2026 FY | J9: ="Upload"&CHAR(10)&"concept" -> Upload concept | K9: ="Geselect."&CHAR(10)&Sel_Versie&" FY" -> Geselect. Q3 FY | L9: Realisatie YTD | M9: Omzet to go | N9: ="BOR FY"&CHAR(10)&Sel_Versie -> BOR FY Q3 | O9: Marge % | P9: Δ vs Budget | Q9: ="Δ vs "&IF(Sel_Prev="","vorige",Sel_Prev) -> Δ vs Q2 | R9: Verlies | S9: Toelichting (Invoer_Toelichting)
A10: =IF(VERW_Project!$A6="","",VERW_Project!$A6) -> G.900001.8.9090 | B10: =IF($A10="","",VERW_Project!$C6) -> Lindehaven, Parkzoom fase 1 | C10: =IF($A10="","",VERW_Project!$D6) -> Opstal | D10: =IF($A10="","",VERW_Project!$I6) -> J | E10: =IF($A10="","",IF(ISNUMBER(IF(COUNTIFS(L_Actief,1,L_WBS,$A10,L_Doeljaar,Sel_Doeljaar,L_Versiejaar,P_VJ,L_Versie,E$8,L_Kengetal,"Omzet FY")=0,"n.b.",SUMIFS(L_Waarde,L_Actief,1,L_WBS,$A10,L_Doeljaar,Sel_Doeljaar,L_Versiejaar,P_VJ,L_Versie,E$8,L_Kengetal,"Omzet FY"))),IF(COUNTIFS(L_Actief,1,L_WBS,$A10,L_Doeljaar,Sel_Doeljaar,L_Versiejaar,P_VJ,L_Versie,E$8,L_Kengetal,"Omzet FY")=0,"n.b.",SUMIFS(L_Waarde,L_Actief,1,L_WBS,$A10,L_Doeljaar,Sel_Doeljaar,L_Versiejaar,P_VJ,L_Versie,E$8,L_Kengetal,"Omzet FY"))/P_Factor,IF(COUNTIFS(L_Actief,1,L_WBS,$A10,L_Doeljaar,Sel_Doeljaar,L_Versiejaar,P_VJ,L_Versie,E$8,L_Kengetal,"Omzet FY")=0,"n.b.",SUMIFS(L_Waarde,L_Actief,1,L_WBS,$A10,L_Doeljaar,Sel_Doeljaar,L_Versiejaar,P_VJ,L_Versie,E$8,L_Kengetal,"Omzet FY")))) -> 6152.96 | F10: =IF($A10="","",IF(ISNUMBER(IF(COUNTIFS(L_Actief,1,L_WBS,$A10,L_Doeljaar,Sel_Doeljaar,L_Versiejaar,P_VJ,L_Versie,F$8,L_Kengetal,"Omzet FY")=0,"n.b.",SUMIFS(L_Waarde,L_Actief,1,L_WBS,$A10,L_Doeljaar,Sel_Doeljaar,L_Versiejaar,P_VJ,L_Versie,F$8,L_Kengetal,"Omzet FY"))),IF(COUNTIFS(L_Actief,1,L_WBS,$A10,L_Doeljaar,Sel_Doeljaar,L_Versiejaar,P_VJ,L_Versie,F$8,L_Kengetal,"Omzet FY")=0,"n.b.",SUMIFS(L_Waarde,L_Actief,1,L_WBS,$A10,L_Doeljaar,Sel_Doeljaar,L_Versiejaar,P_VJ,L_Versie,F$8,L_Kengetal,"Omzet FY"))/P_Factor,IF(COUNTIFS(L_Actief,1,L_WBS,$A10,L_Doeljaar,Sel_Doeljaar,L_Versiejaar,P_VJ,L_Versie,F$8,L_Kengetal,"Omzet FY")=0,"n.b.",SUMIFS(L_Waarde,L_Actief,1,L_WBS,$A10,L_Doeljaar,Sel_Doeljaar,L_Versiejaar,P_VJ,L_Versie,F$8,L_Kengetal,"Omzet FY")))) -> 5929.216 | G10: =IF($A10="","",IF(ISNUMBER(IF(COUNTIFS(L_Actief,1,L_WBS,$A10,L_Doeljaar,Sel_Doeljaar,L_Versiejaar,P_VJ,L_Versie,G$8,L_Kengetal,"Omzet FY")=0,"n.b.",SUMIFS(L_Waarde,L_Actief,1,L_WBS,$A10,L_Doeljaar,Sel_Doeljaar,L_Versiejaar,P_VJ,L_Versie,G$8,L_Kengetal,"Omzet FY"))),IF(COUNTIFS(L_Actief,1,L_WBS,$A10,L_Doeljaar,Sel_Doeljaar,L_Versiejaar,P_VJ,L_Versie,G$8,L_Kengetal,"Omzet FY")=0,"n.b.",SUMIFS(L_Waarde,L_Actief,1,L_WBS,$A10,L_Doeljaar,Sel_Doeljaar,L_Versiejaar,P_VJ,L_Versie,G$8,L_Kengetal,"Omzet FY"))/P_Factor,IF(COUNTIFS(L_Actief,1,L_WBS,$A10,L_Doeljaar,Sel_Doeljaar,L_Versiejaar,P_VJ,L_Versie,G$8,L_Kengetal,"Omzet FY")=0,"n.b.",SUMIFS(L_Waarde,L_Actief,1,L_WBS,$A10,L_Doeljaar,Sel_Doeljaar,L_Versiejaar,P_VJ,L_Versie,G$8,L_Kengetal,"Omzet FY")))) -> 5425.792 | H10: =IF($A10="","",IF(ISNUMBER(IF(COUNTIFS(L_Actief,1,L_WBS,$A10,L_Doeljaar,Sel_Doeljaar,L_Versiejaar,P_VJ,L_Versie,H$8,L_Kengetal,"Omzet FY")=0,"n.b.",SUMIFS(L_Waarde,L_Actief,1,L_WBS,$A10,L_Doeljaar,Sel_Doeljaar,L_Versiejaar,P_VJ,L_Versie,H$8,L_Kengetal,"Omzet FY"))),IF(COUNTIFS(L_Actief,1,L_WBS,$A10,L_Doeljaar,Sel_Doeljaar,L_Versiejaar,P_VJ,L_Versie,H$8,L_Kengetal,"Omzet FY")=0,"n.b.",SUMIFS(L_Waarde,L_Actief,1,L_WBS,$A10,L_Doeljaar,Sel_Doeljaar,L_Versiejaar,P_VJ,L_Versie,H$8,L_Kengetal,"Omzet FY"))/P_Factor,IF(COUNTIFS(L_Actief,1,L_WBS,$A10,L_Doeljaar,Sel_Doeljaar,L_Versiejaar,P_VJ,L_Versie,H$8,L_Kengetal,"Omzet FY")=0,"n.b.",SUMIFS(L_Waarde,L_Actief,1,L_WBS,$A10,L_Doeljaar,Sel_Doeljaar,L_Versiejaar,P_VJ,L_Versie,H$8,L_Kengetal,"Omzet FY")))) -> 5593.6 | I10: =IF($A10="","",IF(ISNUMBER(IF(COUNTIFS(L_Actief,1,L_WBS,$A10,L_Doeljaar,Sel_Doeljaar,L_Versiejaar,P_VJ,L_Versie,I$8,L_Kengetal,"Omzet FY")=0,"n.b.",SUMIFS(L_Waarde,L_Actief,1,L_WBS,$A10,L_Doeljaar,Sel_Doeljaar,L_Versiejaar,P_VJ,L_Versie,I$8,L_Kengetal,"Omzet FY"))),IF(COUNTIFS(L_Actief,1,L_WBS,$A10,L_Doeljaar,Sel_Doeljaar,L_Versiejaar,P_VJ,L_Versie,I$8,L_Kengetal,"Omzet FY")=0,"n.b.",SUMIFS(L_Waarde,L_Actief,1,L_WBS,$A10,L_Doeljaar,Sel_Doeljaar,L_Versiejaar,P_VJ,L_Versie,I$8,L_Kengetal,"Omzet FY"))/P_Factor,IF(COUNTIFS(L_Actief,1,L_WBS,$A10,L_Doeljaar,Sel_Doeljaar,L_Versiejaar,P_VJ,L_Versie,I$8,L_Kengetal,"Omzet FY")=0,"n.b.",SUMIFS(L_Waarde,L_Actief,1,L_WBS,$A10,L_Doeljaar,Sel_Doeljaar,L_Versiejaar,P_VJ,L_Versie,I$8,L_Kengetal,"Omzet FY")))) -> n.b. | J10: =IF($A10="","",IF(ISNUMBER(IF(Sel_Doeljaar=P_RJ,VERW_Project!$P6,IF(Sel_Doeljaar=P_RJ+1,VERW_Project!$R6,"n.b."))),IF(Sel_Doeljaar=P_RJ,VERW_Project!$P6,IF(Sel_Doeljaar=P_RJ+1,VERW_Project!$R6,"n.b."))/P_Factor,IF(Sel_Doeljaar=P_RJ,VERW_Project!$P6,IF(Sel_Doeljaar=P_RJ+1,VERW_Project!$R6,"n.b.")))) -> 5593.6 | K10: =IF($A10="","",IF(Sel_Bron="Vastgesteld",INDEX($E10:$I10,MATCH(Sel_Versie,$E$8:$I$8,0)),IF(Sel_Bron="Concept",J10,"n.b."))) -> 5593.6 | L10: =IF($A10="","",IF(Sel_Doeljaar>P_VJ,"n.v.t.",IF(Sel_Bron="Vastgesteld",IF(ISNUMBER(IF(COUNTIFS(L_Actief,1,L_WBS,$A10,L_Doeljaar,Sel_Doeljaar,L_Versiejaar,P_VJ,L_Versie,Sel_Versie,L_Kengetal,"Omzet actual YTD")=0,"n.b.",SUMIFS(L_Waarde,L_Actief,1,L_WBS,$A10,L_Doeljaar,Sel_Doeljaar,L_Versiejaar,P_VJ,L_Versie,Sel_Versie,L_Kengetal,"Omzet actual YTD"))),IF(COUNTIFS(L_Actief,1,L_WBS,$A10,L_Doeljaar,Sel_Doeljaar,L_Versiejaar,P_VJ,L_Versie,Sel_Versie,L_Kengetal,"Omzet actual YTD")=0,"n.b.",SUMIFS(L_Waarde,L_Actief,1,L_WBS,$A10,L_Doeljaar,Sel_Doeljaar,L_Versiejaar,P_VJ,L_Versie,Sel_Versie,L_Kengetal,"Omzet actual YTD"))/P_Factor,IF(COUNTIFS(L_Actief,1,L_WBS,$A10,L_Doeljaar,Sel_Doeljaar,L_Versiejaar,P_VJ,L_Versie,Sel_Versie,L_Kengetal,"Omzet actual YTD")=0,"n.b.",SUMIFS(L_Waarde,L_Actief,1,L_WBS,$A10,L_Doeljaar,Sel_Doeljaar,L_Versiejaar,P_VJ,L_Versie,Sel_Versie,L_Kengetal,"Omzet actual YTD"))),IF(Sel_Bron="Concept",IF(ISNUMBER(IF(Sel_Doeljaar=P_RJ,VERW_Project!$L6,"n.v.t.")),IF(Sel_Doeljaar=P_RJ,VERW_Project!$L6,"n.v.t.")/P_Factor,IF(Sel_Doeljaar=P_RJ,VERW_Project!$L6,"n.v.t.")),"n.b.")))) -> 3635.84 | M10: =IF($A10="","",IF(L10="n.v.t.",K10,IF(AND(ISNUMBER(K10),ISNUMBER(L10)),K10-L10,"n.b."))) -> 1957.76 | N10: =IF($A10="","",IF(Sel_Bron="Vastgesteld",IF(ISNUMBER(IF(COUNTIFS(L_Actief,1,L_WBS,$A10,L_Doeljaar,Sel_Doeljaar,L_Versiejaar,P_VJ,L_Versie,Sel_Versie,L_Kengetal,"BOR FY")=0,"n.b.",SUMIFS(L_Waarde,L_Actief,1,L_WBS,$A10,L_Doeljaar,Sel_Doeljaar,L_Versiejaar,P_VJ,L_Versie,Sel_Versie,L_Kengetal,"BOR FY"))),IF(COUNTIFS(L_Actief,1,L_WBS,$A10,L_Doeljaar,Sel_Doeljaar,L_Versiejaar,P_VJ,L_Versie,Sel_Versie,L_Kengetal,"BOR FY")=0,"n.b.",SUMIFS(L_Waarde,L_Actief,1,L_WBS,$A10,L_Doeljaar,Sel_Doeljaar,L_Versiejaar,P_VJ,L_Versie,Sel_Versie,L_Kengetal,"BOR FY"))/P_Factor,IF(COUNTIFS(L_Actief,1,L_WBS,$A10,L_Doeljaar,Sel_Doeljaar,L_Versiejaar,P_VJ,L_Versie,Sel_Versie,L_Kengetal,"BOR FY")=0,"n.b.",SUMIFS(L_Waarde,L_Actief,1,L_WBS,$A10,L_Doeljaar,Sel_Doeljaar,L_Versiejaar,P_VJ,L_Versie,Sel_Versie,L_Kengetal,"BOR FY"))),IF(Sel_Bron="Concept",IF(ISNUMBER(IF(Sel_Doeljaar=P_RJ,VERW_Project!$Q6,IF(Sel_Doeljaar=P_RJ+1,VERW_Project!$S6,"n.b."))),IF(Sel_Doeljaar=P_RJ,VERW_Project!$Q6,IF(Sel_Doeljaar=P_RJ+1,VERW_Project!$S6,"n.b."))/P_Factor,IF(Sel_Doeljaar=P_RJ,VERW_Project!$Q6,IF(Sel_Doeljaar=P_RJ+1,VERW_Project!$S6,"n.b."))),"n.b."))) -> 503.424 | O10: =IF($A10="","",IF(AND(ISNUMBER(N10),ISNUMBER(K10)),IF(K10<>0,N10/K10,"n.b."),"n.b.")) -> 0.09 | P10: =IF($A10="","",IF(AND(ISNUMBER(K10),ISNUMBER(E10)),K10-E10,"n.b.")) -> -559.36 | Q10: =IF($A10="","",IF(AND(ISNUMBER(K10),ISNUMBER(W10)),K10-W10,"n.b.")) -> 167.808 | R10: =IF($A10="","",IF(ISNUMBER(N10),IF(N10<0,"Verlies",""),"")) | S10: =IF($A10="","",IFERROR(INDEX(T_Txt,MATCH($A10&"|"&Sel_Doeljaar&"|"&P_VJ&"|"&Sel_Versie,T_Key,0)),"")) | U10: =IF(AND(AND($A10<>"",OR(Sel_Type="Alle",$C10=Sel_Type),OR(Sel_Project="Alle",$B10=Sel_Project)),ISNUMBER(K10)),K10+ROW()/1000000000,"") -> 5593.6 | V10: =IF(AND(AND($A10<>"",OR(Sel_Type="Alle",$C10=Sel_Type),OR(Sel_Project="Alle",$B10=Sel_Project)),ISNUMBER(Q10)),ABS(Q10)+ROW()/1000000000,"") -> 167.808 | W10: =IF(OR($A10="",Sel_Prev=""),"n.b.",IF(ISNUMBER(IF(COUNTIFS(L_Actief,1,L_WBS,$A10,L_Doeljaar,Sel_Doeljaar,L_Versiejaar,P_VJ,L_Versie,Sel_Prev,L_Kengetal,"Omzet FY")=0,"n.b.",SUMIFS(L_Waarde,L_Actief,1,L_WBS,$A10,L_Doeljaar,Sel_Doeljaar,L_Versiejaar,P_VJ,L_Versie,Sel_Prev,L_Kengetal,"Omzet FY"))),IF(COUNTIFS(L_Actief,1,L_WBS,$A10,L_Doeljaar,Sel_Doeljaar,L_Versiejaar,P_VJ,L_Versie,Sel_Prev,L_Kengetal,"Omzet FY")=0,"n.b.",SUMIFS(L_Waarde,L_Actief,1,L_WBS,$A10,L_Doeljaar,Sel_Doeljaar,L_Versiejaar,P_VJ,L_Versie,Sel_Prev,L_Kengetal,"Omzet FY"))/P_Factor,IF(COUNTIFS(L_Actief,1,L_WBS,$A10,L_Doeljaar,Sel_Doeljaar,L_Versiejaar,P_VJ,L_Versie,Sel_Prev,L_Kengetal,"Omzet FY")=0,"n.b.",SUMIFS(L_Waarde,L_Actief,1,L_WBS,$A10,L_Doeljaar,Sel_Doeljaar,L_Versiejaar,P_VJ,L_Versie,Sel_Prev,L_Kengetal,"Omzet FY")))) -> 5425.792
A11: =IF(VERW_Project!$A7="","",VERW_Project!$A7) -> G.900002.8.9090 | B11: =IF($A11="","",VERW_Project!$C7) -> Duinwaard, De Watergaarde | C11: =IF($A11="","",VERW_Project!$D7) -> Opstal | D11: =IF($A11="","",VERW_Project!$I7) -> J | E11: =IF($A11="","",IF(ISNUMBER(IF(COUNTIFS(L_Actief,1,L_WBS,$A11,L_Doeljaar,Sel_Doeljaar,L_Versiejaar,P_VJ,L_Versie,E$8,L_Kengetal,"Omzet FY")=0,"n.b.",SUMIFS(L_Waarde,L_Actief,1,L_WBS,$A11,L_Doeljaar,Sel_Doeljaar,L_Versiejaar,P_VJ,L_Versie,E$8,L_Kengetal,"Omzet FY"))),IF(COUNTIFS(L_Actief,1,L_WBS,$A11,L_Doeljaar,Sel_Doeljaar,L_Versiejaar,P_VJ,L_Versie,E$8,L_Kengetal,"Omzet FY")=0,"n.b.",SUMIFS(L_Waarde,L_Actief,1,L_WBS,$A11,L_Doeljaar,Sel_Doeljaar,L_Versiejaar,P_VJ,L_Versie,E$8,L_Kengetal,"Omzet FY"))/P_Factor,IF(COUNTIFS(L_Actief,1,L_WBS,$A11,L_Doeljaar,Sel_Doeljaar,L_Versiejaar,P_VJ,L_Versie,E$8,L_Kengetal,"Omzet FY")=0,"n.b.",SUMIFS(L_Waarde,L_Actief,1,L_WBS,$A11,L_Doeljaar,Sel_Doeljaar,L_Versiejaar,P_VJ,L_Versie,E$8,L_Kengetal,"Omzet FY")))) -> 3348 | F11: =IF($A11="","",IF(ISNUMBER(IF(COUNTIFS(L_Actief,1,L_WBS,$A11,L_Doeljaar,Sel_Doeljaar,L_Versiejaar,P_VJ,L_Versie,F$8,L_Kengetal,"Omzet FY")=0,"n.b.",SUMIFS(L_Waarde,L_Actief,1,L_WBS,$A11,L_Doeljaar,Sel_Doeljaar,L_Versiejaar,P_VJ,L_Versie,F$8,L_Kengetal,"Omzet FY"))),IF(COUNTIFS(L_Actief,1,L_WBS,$A11,L_Doeljaar,Sel_Doeljaar,L_Versiejaar,P_VJ,L_Versie,F$8,L_Kengetal,"Omzet FY")=0,"n.b.",SUMIFS(L_Waarde,L_Actief,1,L_WBS,$A11,L_Doeljaar,Sel_Doeljaar,L_Versiejaar,P_VJ,L_Versie,F$8,L_Kengetal,"Omzet FY"))/P_Factor,IF(COUNTIFS(L_Actief,1,L_WBS,$A11,L_Doeljaar,Sel_Doeljaar,L_Versiejaar,P_VJ,L_Versie,F$8,L_Kengetal,"Omzet FY")=0,"n.b.",SUMIFS(L_Waarde,L_Actief,1,L_WBS,$A11,L_Doeljaar,Sel_Doeljaar,L_Versiejaar,P_VJ,L_Versie,F$8,L_Kengetal,"Omzet FY")))) -> 3496.8 | G11: =IF($A11="","",IF(ISNUMBER(IF(COUNTIFS(L_Actief,1,L_WBS,$A11,L_Doeljaar,Sel_Doeljaar,L_Versiejaar,P_VJ,L_Versie,G$8,L_Kengetal,"Omzet FY")=0,"n.b.",SUMIFS(L_Waarde,L_Actief,1,L_WBS,$A11,L_Doeljaar,Sel_Doeljaar,L_Versiejaar,P_VJ,L_Versie,G$8,L_Kengetal,"Omzet FY"))),IF(COUNTIFS(L_Actief,1,L_WBS,$A11,L_Doeljaar,Sel_Doeljaar,L_Versiejaar,P_VJ,L_Versie,G$8,L_Kengetal,"Omzet FY")=0,"n.b.",SUMIFS(L_Waarde,L_Actief,1,L_WBS,$A11,L_Doeljaar,Sel_Doeljaar,L_Versiejaar,P_VJ,L_Versie,G$8,L_Kengetal,"Omzet FY"))/P_Factor,IF(COUNTIFS(L_Actief,1,L_WBS,$A11,L_Doeljaar,Sel_Doeljaar,L_Versiejaar,P_VJ,L_Versie,G$8,L_Kengetal,"Omzet FY")=0,"n.b.",SUMIFS(L_Waarde,L_Actief,1,L_WBS,$A11,L_Doeljaar,Sel_Doeljaar,L_Versiejaar,P_VJ,L_Versie,G$8,L_Kengetal,"Omzet FY")))) -> 3831.6 | H11: =IF($A11="","",IF(ISNUMBER(IF(COUNTIFS(L_Actief,1,L_WBS,$A11,L_Doeljaar,Sel_Doeljaar,L_Versiejaar,P_VJ,L_Versie,H$8,L_Kengetal,"Omzet FY")=0,"n.b.",SUMIFS(L_Waarde,L_Actief,1,L_WBS,$A11,L_Doeljaar,Sel_Doeljaar,L_Versiejaar,P_VJ,L_Versie,H$8,L_Kengetal,"Omzet FY"))),IF(COUNTIFS(L_Actief,1,L_WBS,$A11,L_Doeljaar,Sel_Doeljaar,L_Versiejaar,P_VJ,L_Versie,H$8,L_Kengetal,"Omzet FY")=0,"n.b.",SUMIFS(L_Waarde,L_Actief,1,L_WBS,$A11,L_Doeljaar,Sel_Doeljaar,L_Versiejaar,P_VJ,L_Versie,H$8,L_Kengetal,"Omzet FY"))/P_Factor,IF(COUNTIFS(L_Actief,1,L_WBS,$A11,L_Doeljaar,Sel_Doeljaar,L_Versiejaar,P_VJ,L_Versie,H$8,L_Kengetal,"Omzet FY")=0,"n.b.",SUMIFS(L_Waarde,L_Actief,1,L_WBS,$A11,L_Doeljaar,Sel_Doeljaar,L_Versiejaar,P_VJ,L_Versie,H$8,L_Kengetal,"Omzet FY")))) -> 3720 | I11: =IF($A11="","",IF(ISNUMBER(IF(COUNTIFS(L_Actief,1,L_WBS,$A11,L_Doeljaar,Sel_Doeljaar,L_Versiejaar,P_VJ,L_Versie,I$8,L_Kengetal,"Omzet FY")=0,"n.b.",SUMIFS(L_Waarde,L_Actief,1,L_WBS,$A11,L_Doeljaar,Sel_Doeljaar,L_Versiejaar,P_VJ,L_Versie,I$8,L_Kengetal,"Omzet FY"))),IF(COUNTIFS(L_Actief,1,L_WBS,$A11,L_Doeljaar,Sel_Doeljaar,L_Versiejaar,P_VJ,L_Versie,I$8,L_Kengetal,"Omzet FY")=0,"n.b.",SUMIFS(L_Waarde,L_Actief,1,L_WBS,$A11,L_Doeljaar,Sel_Doeljaar,L_Versiejaar,P_VJ,L_Versie,I$8,L_Kengetal,"Omzet FY"))/P_Factor,IF(COUNTIFS(L_Actief,1,L_WBS,$A11,L_Doeljaar,Sel_Doeljaar,L_Versiejaar,P_VJ,L_Versie,I$8,L_Kengetal,"Omzet FY")=0,"n.b.",SUMIFS(L_Waarde,L_Actief,1,L_WBS,$A11,L_Doeljaar,Sel_Doeljaar,L_Versiejaar,P_VJ,L_Versie,I$8,L_Kengetal,"Omzet FY")))) -> n.b. | J11: =IF($A11="","",IF(ISNUMBER(IF(Sel_Doeljaar=P_RJ,VERW_Project!$P7,IF(Sel_Doeljaar=P_RJ+1,VERW_Project!$R7,"n.b."))),IF(Sel_Doeljaar=P_RJ,VERW_Project!$P7,IF(Sel_Doeljaar=P_RJ+1,VERW_Project!$R7,"n.b."))/P_Factor,IF(Sel_Doeljaar=P_RJ,VERW_Project!$P7,IF(Sel_Doeljaar=P_RJ+1,VERW_Project!$R7,"n.b.")))) -> 3720 | K11: =IF($A11="","",IF(Sel_Bron="Vastgesteld",INDEX($E11:$I11,MATCH(Sel_Versie,$E$8:$I$8,0)),IF(Sel_Bron="Concept",J11,"n.b."))) -> 3720 | L11: =IF($A11="","",IF(Sel_Doeljaar>P_VJ,"n.v.t.",IF(Sel_Bron="Vastgesteld",IF(ISNUMBER(IF(COUNTIFS(L_Actief,1,L_WBS,$A11,L_Doeljaar,Sel_Doeljaar,L_Versiejaar,P_VJ,L_Versie,Sel_Versie,L_Kengetal,"Omzet actual YTD")=0,"n.b.",SUMIFS(L_Waarde,L_Actief,1,L_WBS,$A11,L_Doeljaar,Sel_Doeljaar,L_Versiejaar,P_VJ,L_Versie,Sel_Versie,L_Kengetal,"Omzet actual YTD"))),IF(COUNTIFS(L_Actief,1,L_WBS,$A11,L_Doeljaar,Sel_Doeljaar,L_Versiejaar,P_VJ,L_Versie,Sel_Versie,L_Kengetal,"Omzet actual YTD")=0,"n.b.",SUMIFS(L_Waarde,L_Actief,1,L_WBS,$A11,L_Doeljaar,Sel_Doeljaar,L_Versiejaar,P_VJ,L_Versie,Sel_Versie,L_Kengetal,"Omzet actual YTD"))/P_Factor,IF(COUNTIFS(L_Actief,1,L_WBS,$A11,L_Doeljaar,Sel_Doeljaar,L_Versiejaar,P_VJ,L_Versie,Sel_Versie,L_Kengetal,"Omzet actual YTD")=0,"n.b.",SUMIFS(L_Waarde,L_Actief,1,L_WBS,$A11,L_Doeljaar,Sel_Doeljaar,L_Versiejaar,P_VJ,L_Versie,Sel_Versie,L_Kengetal,"Omzet actual YTD"))),IF(Sel_Bron="Concept",IF(ISNUMBER(IF(Sel_Doeljaar=P_RJ,VERW_Project!$L7,"n.v.t.")),IF(Sel_Doeljaar=P_RJ,VERW_Project!$L7,"n.v.t.")/P_Factor,IF(Sel_Doeljaar=P_RJ,VERW_Project!$L7,"n.v.t.")),"n.b.")))) -> 2418 | M11: =IF($A11="","",IF(L11="n.v.t.",K11,IF(AND(ISNUMBER(K11),ISNUMBER(L11)),K11-L11,"n.b."))) -> 1302 | N11: =IF($A11="","",IF(Sel_Bron="Vastgesteld",IF(ISNUMBER(IF(COUNTIFS(L_Actief,1,L_WBS,$A11,L_Doeljaar,Sel_Doeljaar,L_Versiejaar,P_VJ,L_Versie,Sel_Versie,L_Kengetal,"BOR FY")=0,"n.b.",SUMIFS(L_Waarde,L_Actief,1,L_WBS,$A11,L_Doeljaar,Sel_Doeljaar,L_Versiejaar,P_VJ,L_Versie,Sel_Versie,L_Kengetal,"BOR FY"))),IF(COUNTIFS(L_Actief,1,L_WBS,$A11,L_Doeljaar,Sel_Doeljaar,L_Versiejaar,P_VJ,L_Versie,Sel_Versie,L_Kengetal,"BOR FY")=0,"n.b.",SUMIFS(L_Waarde,L_Actief,1,L_WBS,$A11,L_Doeljaar,Sel_Doeljaar,L_Versiejaar,P_VJ,L_Versie,Sel_Versie,L_Kengetal,"BOR FY"))/P_Factor,IF(COUNTIFS(L_Actief,1,L_WBS,$A11,L_Doeljaar,Sel_Doeljaar,L_Versiejaar,P_VJ,L_Versie,Sel_Versie,L_Kengetal,"BOR FY")=0,"n.b.",SUMIFS(L_Waarde,L_Actief,1,L_WBS,$A11,L_Doeljaar,Sel_Doeljaar,L_Versiejaar,P_VJ,L_Versie,Sel_Versie,L_Kengetal,"BOR FY"))),IF(Sel_Bron="Concept",IF(ISNUMBER(IF(Sel_Doeljaar=P_RJ,VERW_Project!$Q7,IF(Sel_Doeljaar=P_RJ+1,VERW_Project!$S7,"n.b."))),IF(Sel_Doeljaar=P_RJ,VERW_Project!$Q7,IF(Sel_Doeljaar=P_RJ+1,VERW_Project!$S7,"n.b."))/P_Factor,IF(Sel_Doeljaar=P_RJ,VERW_Project!$Q7,IF(Sel_Doeljaar=P_RJ+1,VERW_Project!$S7,"n.b."))),"n.b."))) -> 446.4 | O11: =IF($A11="","",IF(AND(ISNUMBER(N11),ISNUMBER(K11)),IF(K11<>0,N11/K11,"n.b."),"n.b.")) -> 0.12 | P11: =IF($A11="","",IF(AND(ISNUMBER(K11),ISNUMBER(E11)),K11-E11,"n.b.")) -> 372 | Q11: =IF($A11="","",IF(AND(ISNUMBER(K11),ISNUMBER(W11)),K11-W11,"n.b.")) -> -111.6 | R11: =IF($A11="","",IF(ISNUMBER(N11),IF(N11<0,"Verlies",""),"")) | S11: =IF($A11="","",IFERROR(INDEX(T_Txt,MATCH($A11&"|"&Sel_Doeljaar&"|"&P_VJ&"|"&Sel_Versie,T_Key,0)),"")) | U11: =IF(AND(AND($A11<>"",OR(Sel_Type="Alle",$C11=Sel_Type),OR(Sel_Project="Alle",$B11=Sel_Project)),ISNUMBER(K11)),K11+ROW()/1000000000,"") -> 3720 | V11: =IF(AND(AND($A11<>"",OR(Sel_Type="Alle",$C11=Sel_Type),OR(Sel_Project="Alle",$B11=Sel_Project)),ISNUMBER(Q11)),ABS(Q11)+ROW()/1000000000,"") -> 111.6 | W11: =IF(OR($A11="",Sel_Prev=""),"n.b.",IF(ISNUMBER(IF(COUNTIFS(L_Actief,1,L_WBS,$A11,L_Doeljaar,Sel_Doeljaar,L_Versiejaar,P_VJ,L_Versie,Sel_Prev,L_Kengetal,"Omzet FY")=0,"n.b.",SUMIFS(L_Waarde,L_Actief,1,L_WBS,$A11,L_Doeljaar,Sel_Doeljaar,L_Versiejaar,P_VJ,L_Versie,Sel_Prev,L_Kengetal,"Omzet FY"))),IF(COUNTIFS(L_Actief,1,L_WBS,$A11,L_Doeljaar,Sel_Doeljaar,L_Versiejaar,P_VJ,L_Versie,Sel_Prev,L_Kengetal,"Omzet FY")=0,"n.b.",SUMIFS(L_Waarde,L_Actief,1,L_WBS,$A11,L_Doeljaar,Sel_Doeljaar,L_Versiejaar,P_VJ,L_Versie,Sel_Prev,L_Kengetal,"Omzet FY"))/P_Factor,IF(COUNTIFS(L_Actief,1,L_WBS,$A11,L_Doeljaar,Sel_Doeljaar,L_Versiejaar,P_VJ,L_Versie,Sel_Prev,L_Kengetal,"Omzet FY")=0,"n.b.",SUMIFS(L_Waarde,L_Actief,1,L_WBS,$A11,L_Doeljaar,Sel_Doeljaar,L_Versiejaar,P_VJ,L_Versie,Sel_Prev,L_Kengetal,"Omzet FY")))) -> 3831.6
A12: =IF(VERW_Project!$A8="","",VERW_Project!$A8) -> G.900003.8.9090 | B12: =IF($A12="","",VERW_Project!$C8) -> Veldendam, Stationshof | C12: =IF($A12="","",VERW_Project!$D8) -> Opstal | D12: =IF($A12="","",VERW_Project!$I8) -> J | E12: =IF($A12="","",IF(ISNUMBER(IF(COUNTIFS(L_Actief,1,L_WBS,$A12,L_Doeljaar,Sel_Doeljaar,L_Versiejaar,P_VJ,L_Versie,E$8,L_Kengetal,"Omzet FY")=0,"n.b.",SUMIFS(L_Waarde,L_Actief,1,L_WBS,$A12,L_Doeljaar,Sel_Doeljaar,L_Versiejaar,P_VJ,L_Versie,E$8,L_Kengetal,"Omzet FY"))),IF(COUNTIFS(L_Actief,1,L_WBS,$A12,L_Doeljaar,Sel_Doeljaar,L_Versiejaar,P_VJ,L_Versie,E$8,L_Kengetal,"Omzet FY")=0,"n.b.",SUMIFS(L_Waarde,L_Actief,1,L_WBS,$A12,L_Doeljaar,Sel_Doeljaar,L_Versiejaar,P_VJ,L_Versie,E$8,L_Kengetal,"Omzet FY"))/P_Factor,IF(COUNTIFS(L_Actief,1,L_WBS,$A12,L_Doeljaar,Sel_Doeljaar,L_Versiejaar,P_VJ,L_Versie,E$8,L_Kengetal,"Omzet FY")=0,"n.b.",SUMIFS(L_Waarde,L_Actief,1,L_WBS,$A12,L_Doeljaar,Sel_Doeljaar,L_Versiejaar,P_VJ,L_Versie,E$8,L_Kengetal,"Omzet FY")))) -> 5016 | F12: =IF($A12="","",IF(ISNUMBER(IF(COUNTIFS(L_Actief,1,L_WBS,$A12,L_Doeljaar,Sel_Doeljaar,L_Versiejaar,P_VJ,L_Versie,F$8,L_Kengetal,"Omzet FY")=0,"n.b.",SUMIFS(L_Waarde,L_Actief,1,L_WBS,$A12,L_Doeljaar,Sel_Doeljaar,L_Versiejaar,P_VJ,L_Versie,F$8,L_Kengetal,"Omzet FY"))),IF(COUNTIFS(L_Actief,1,L_WBS,$A12,L_Doeljaar,Sel_Doeljaar,L_Versiejaar,P_VJ,L_Versie,F$8,L_Kengetal,"Omzet FY")=0,"n.b.",SUMIFS(L_Waarde,L_Actief,1,L_WBS,$A12,L_Doeljaar,Sel_Doeljaar,L_Versiejaar,P_VJ,L_Versie,F$8,L_Kengetal,"Omzet FY"))/P_Factor,IF(COUNTIFS(L_Actief,1,L_WBS,$A12,L_Doeljaar,Sel_Doeljaar,L_Versiejaar,P_VJ,L_Versie,F$8,L_Kengetal,"Omzet FY")=0,"n.b.",SUMIFS(L_Waarde,L_Actief,1,L_WBS,$A12,L_Doeljaar,Sel_Doeljaar,L_Versiejaar,P_VJ,L_Versie,F$8,L_Kengetal,"Omzet FY")))) -> 4833.6 | G12: =IF($A12="","",IF(ISNUMBER(IF(COUNTIFS(L_Actief,1,L_WBS,$A12,L_Doeljaar,Sel_Doeljaar,L_Versiejaar,P_VJ,L_Versie,G$8,L_Kengetal,"Omzet FY")=0,"n.b.",SUMIFS(L_Waarde,L_Actief,1,L_WBS,$A12,L_Doeljaar,Sel_Doeljaar,L_Versiejaar,P_VJ,L_Versie,G$8,L_Kengetal,"Omzet FY"))),IF(COUNTIFS(L_Actief,1,L_WBS,$A12,L_Doeljaar,Sel_Doeljaar,L_Versiejaar,P_VJ,L_Versie,G$8,L_Kengetal,"Omzet FY")=0,"n.b.",SUMIFS(L_Waarde,L_Actief,1,L_WBS,$A12,L_Doeljaar,Sel_Doeljaar,L_Versiejaar,P_VJ,L_Versie,G$8,L_Kengetal,"Omzet FY"))/P_Factor,IF(COUNTIFS(L_Actief,1,L_WBS,$A12,L_Doeljaar,Sel_Doeljaar,L_Versiejaar,P_VJ,L_Versie,G$8,L_Kengetal,"Omzet FY")=0,"n.b.",SUMIFS(L_Waarde,L_Actief,1,L_WBS,$A12,L_Doeljaar,Sel_Doeljaar,L_Versiejaar,P_VJ,L_Versie,G$8,L_Kengetal,"Omzet FY")))) -> 4423.2 | H12: =IF($A12="","",IF(ISNUMBER(IF(COUNTIFS(L_Actief,1,L_WBS,$A12,L_Doeljaar,Sel_Doeljaar,L_Versiejaar,P_VJ,L_Versie,H$8,L_Kengetal,"Omzet FY")=0,"n.b.",SUMIFS(L_Waarde,L_Actief,1,L_WBS,$A12,L_Doeljaar,Sel_Doeljaar,L_Versiejaar,P_VJ,L_Versie,H$8,L_Kengetal,"Omzet FY"))),IF(COUNTIFS(L_Actief,1,L_WBS,$A12,L_Doeljaar,Sel_Doeljaar,L_Versiejaar,P_VJ,L_Versie,H$8,L_Kengetal,"Omzet FY")=0,"n.b.",SUMIFS(L_Waarde,L_Actief,1,L_WBS,$A12,L_Doeljaar,Sel_Doeljaar,L_Versiejaar,P_VJ,L_Versie,H$8,L_Kengetal,"Omzet FY"))/P_Factor,IF(COUNTIFS(L_Actief,1,L_WBS,$A12,L_Doeljaar,Sel_Doeljaar,L_Versiejaar,P_VJ,L_Versie,H$8,L_Kengetal,"Omzet FY")=0,"n.b.",SUMIFS(L_Waarde,L_Actief,1,L_WBS,$A12,L_Doeljaar,Sel_Doeljaar,L_Versiejaar,P_VJ,L_Versie,H$8,L_Kengetal,"Omzet FY")))) -> 4560 | I12: =IF($A12="","",IF(ISNUMBER(IF(COUNTIFS(L_Actief,1,L_WBS,$A12,L_Doeljaar,Sel_Doeljaar,L_Versiejaar,P_VJ,L_Versie,I$8,L_Kengetal,"Omzet FY")=0,"n.b.",SUMIFS(L_Waarde,L_Actief,1,L_WBS,$A12,L_Doeljaar,Sel_Doeljaar,L_Versiejaar,P_VJ,L_Versie,I$8,L_Kengetal,"Omzet FY"))),IF(COUNTIFS(L_Actief,1,L_WBS,$A12,L_Doeljaar,Sel_Doeljaar,L_Versiejaar,P_VJ,L_Versie,I$8,L_Kengetal,"Omzet FY")=0,"n.b.",SUMIFS(L_Waarde,L_Actief,1,L_WBS,$A12,L_Doeljaar,Sel_Doeljaar,L_Versiejaar,P_VJ,L_Versie,I$8,L_Kengetal,"Omzet FY"))/P_Factor,IF(COUNTIFS(L_Actief,1,L_WBS,$A12,L_Doeljaar,Sel_Doeljaar,L_Versiejaar,P_VJ,L_Versie,I$8,L_Kengetal,"Omzet FY")=0,"n.b.",SUMIFS(L_Waarde,L_Actief,1,L_WBS,$A12,L_Doeljaar,Sel_Doeljaar,L_Versiejaar,P_VJ,L_Versie,I$8,L_Kengetal,"Omzet FY")))) -> n.b. | J12: =IF($A12="","",IF(ISNUMBER(IF(Sel_Doeljaar=P_RJ,VERW_Project!$P8,IF(Sel_Doeljaar=P_RJ+1,VERW_Project!$R8,"n.b."))),IF(Sel_Doeljaar=P_RJ,VERW_Project!$P8,IF(Sel_Doeljaar=P_RJ+1,VERW_Project!$R8,"n.b."))/P_Factor,IF(Sel_Doeljaar=P_RJ,VERW_Project!$P8,IF(Sel_Doeljaar=P_RJ+1,VERW_Project!$R8,"n.b.")))) -> 4560 | K12: =IF($A12="","",IF(Sel_Bron="Vastgesteld",INDEX($E12:$I12,MATCH(Sel_Versie,$E$8:$I$8,0)),IF(Sel_Bron="Concept",J12,"n.b."))) -> 4560 | L12: =IF($A12="","",IF(Sel_Doeljaar>P_VJ,"n.v.t.",IF(Sel_Bron="Vastgesteld",IF(ISNUMBER(IF(COUNTIFS(L_Actief,1,L_WBS,$A12,L_Doeljaar,Sel_Doeljaar,L_Versiejaar,P_VJ,L_Versie,Sel_Versie,L_Kengetal,"Omzet actual YTD")=0,"n.b.",SUMIFS(L_Waarde,L_Actief,1,L_WBS,$A12,L_Doeljaar,Sel_Doeljaar,L_Versiejaar,P_VJ,L_Versie,Sel_Versie,L_Kengetal,"Omzet actual YTD"))),IF(COUNTIFS(L_Actief,1,L_WBS,$A12,L_Doeljaar,Sel_Doeljaar,L_Versiejaar,P_VJ,L_Versie,Sel_Versie,L_Kengetal,"Omzet actual YTD")=0,"n.b.",SUMIFS(L_Waarde,L_Actief,1,L_WBS,$A12,L_Doeljaar,Sel_Doeljaar,L_Versiejaar,P_VJ,L_Versie,Sel_Versie,L_Kengetal,"Omzet actual YTD"))/P_Factor,IF(COUNTIFS(L_Actief,1,L_WBS,$A12,L_Doeljaar,Sel_Doeljaar,L_Versiejaar,P_VJ,L_Versie,Sel_Versie,L_Kengetal,"Omzet actual YTD")=0,"n.b.",SUMIFS(L_Waarde,L_Actief,1,L_WBS,$A12,L_Doeljaar,Sel_Doeljaar,L_Versiejaar,P_VJ,L_Versie,Sel_Versie,L_Kengetal,"Omzet actual YTD"))),IF(Sel_Bron="Concept",IF(ISNUMBER(IF(Sel_Doeljaar=P_RJ,VERW_Project!$L8,"n.v.t.")),IF(Sel_Doeljaar=P_RJ,VERW_Project!$L8,"n.v.t.")/P_Factor,IF(Sel_Doeljaar=P_RJ,VERW_Project!$L8,"n.v.t.")),"n.b.")))) -> 2964 | M12: =IF($A12="","",IF(L12="n.v.t.",K12,IF(AND(ISNUMBER(K12),ISNUMBER(L12)),K12-L12,"n.b."))) -> 1596 | N12: =IF($A12="","",IF(Sel_Bron="Vastgesteld",IF(ISNUMBER(IF(COUNTIFS(L_Actief,1,L_WBS,$A12,L_Doeljaar,Sel_Doeljaar,L_Versiejaar,P_VJ,L_Versie,Sel_Versie,L_Kengetal,"BOR FY")=0,"n.b.",SUMIFS(L_Waarde,L_Actief,1,L_WBS,$A12,L_Doeljaar,Sel_Doeljaar,L_Versiejaar,P_VJ,L_Versie,Sel_Versie,L_Kengetal,"BOR FY"))),IF(COUNTIFS(L_Actief,1,L_WBS,$A12,L_Doeljaar,Sel_Doeljaar,L_Versiejaar,P_VJ,L_Versie,Sel_Versie,L_Kengetal,"BOR FY")=0,"n.b.",SUMIFS(L_Waarde,L_Actief,1,L_WBS,$A12,L_Doeljaar,Sel_Doeljaar,L_Versiejaar,P_VJ,L_Versie,Sel_Versie,L_Kengetal,"BOR FY"))/P_Factor,IF(COUNTIFS(L_Actief,1,L_WBS,$A12,L_Doeljaar,Sel_Doeljaar,L_Versiejaar,P_VJ,L_Versie,Sel_Versie,L_Kengetal,"BOR FY")=0,"n.b.",SUMIFS(L_Waarde,L_Actief,1,L_WBS,$A12,L_Doeljaar,Sel_Doeljaar,L_Versiejaar,P_VJ,L_Versie,Sel_Versie,L_Kengetal,"BOR FY"))),IF(Sel_Bron="Concept",IF(ISNUMBER(IF(Sel_Doeljaar=P_RJ,VERW_Project!$Q8,IF(Sel_Doeljaar=P_RJ+1,VERW_Project!$S8,"n.b."))),IF(Sel_Doeljaar=P_RJ,VERW_Project!$Q8,IF(Sel_Doeljaar=P_RJ+1,VERW_Project!$S8,"n.b."))/P_Factor,IF(Sel_Doeljaar=P_RJ,VERW_Project!$Q8,IF(Sel_Doeljaar=P_RJ+1,VERW_Project!$S8,"n.b."))),"n.b."))) -> 342 | O12: =IF($A12="","",IF(AND(ISNUMBER(N12),ISNUMBER(K12)),IF(K12<>0,N12/K12,"n.b."),"n.b.")) -> 0.075 | P12: =IF($A12="","",IF(AND(ISNUMBER(K12),ISNUMBER(E12)),K12-E12,"n.b.")) -> -456 | Q12: =IF($A12="","",IF(AND(ISNUMBER(K12),ISNUMBER(W12)),K12-W12,"n.b.")) -> 136.8 | R12: =IF($A12="","",IF(ISNUMBER(N12),IF(N12<0,"Verlies",""),"")) | S12: =IF($A12="","",IFERROR(INDEX(T_Txt,MATCH($A12&"|"&Sel_Doeljaar&"|"&P_VJ&"|"&Sel_Versie,T_Key,0)),"")) | U12: =IF(AND(AND($A12<>"",OR(Sel_Type="Alle",$C12=Sel_Type),OR(Sel_Project="Alle",$B12=Sel_Project)),ISNUMBER(K12)),K12+ROW()/1000000000,"") -> 4560 | V12: =IF(AND(AND($A12<>"",OR(Sel_Type="Alle",$C12=Sel_Type),OR(Sel_Project="Alle",$B12=Sel_Project)),ISNUMBER(Q12)),ABS(Q12)+ROW()/1000000000,"") -> 136.8 | W12: =IF(OR($A12="",Sel_Prev=""),"n.b.",IF(ISNUMBER(IF(COUNTIFS(L_Actief,1,L_WBS,$A12,L_Doeljaar,Sel_Doeljaar,L_Versiejaar,P_VJ,L_Versie,Sel_Prev,L_Kengetal,"Omzet FY")=0,"n.b.",SUMIFS(L_Waarde,L_Actief,1,L_WBS,$A12,L_Doeljaar,Sel_Doeljaar,L_Versiejaar,P_VJ,L_Versie,Sel_Prev,L_Kengetal,"Omzet FY"))),IF(COUNTIFS(L_Actief,1,L_WBS,$A12,L_Doeljaar,Sel_Doeljaar,L_Versiejaar,P_VJ,L_Versie,Sel_Prev,L_Kengetal,"Omzet FY")=0,"n.b.",SUMIFS(L_Waarde,L_Actief,1,L_WBS,$A12,L_Doeljaar,Sel_Doeljaar,L_Versiejaar,P_VJ,L_Versie,Sel_Prev,L_Kengetal,"Omzet FY"))/P_Factor,IF(COUNTIFS(L_Actief,1,L_WBS,$A12,L_Doeljaar,Sel_Doeljaar,L_Versiejaar,P_VJ,L_Versie,Sel_Prev,L_Kengetal,"Omzet FY")=0,"n.b.",SUMIFS(L_Waarde,L_Actief,1,L_WBS,$A12,L_Doeljaar,Sel_Doeljaar,L_Versiejaar,P_VJ,L_Versie,Sel_Prev,L_Kengetal,"Omzet FY")))) -> 4423.2
A13: =IF(VERW_Project!$A9="","",VERW_Project!$A9) -> G.900004.8.9090 | B13: =IF($A13="","",VERW_Project!$C9) -> Meerhovenstad, Het Kompas | C13: =IF($A13="","",VERW_Project!$D9) -> Deelneming | D13: =IF($A13="","",VERW_Project!$I9) -> N | E13: =IF($A13="","",IF(ISNUMBER(IF(COUNTIFS(L_Actief,1,L_WBS,$A13,L_Doeljaar,Sel_Doeljaar,L_Versiejaar,P_VJ,L_Versie,E$8,L_Kengetal,"Omzet FY")=0,"n.b.",SUMIFS(L_Waarde,L_Actief,1,L_WBS,$A13,L_Doeljaar,Sel_Doeljaar,L_Versiejaar,P_VJ,L_Versie,E$8,L_Kengetal,"Omzet FY"))),IF(COUNTIFS(L_Actief,1,L_WBS,$A13,L_Doeljaar,Sel_Doeljaar,L_Versiejaar,P_VJ,L_Versie,E$8,L_Kengetal,"Omzet FY")=0,"n.b.",SUMIFS(L_Waarde,L_Actief,1,L_WBS,$A13,L_Doeljaar,Sel_Doeljaar,L_Versiejaar,P_VJ,L_Versie,E$8,L_Kengetal,"Omzet FY"))/P_Factor,IF(COUNTIFS(L_Actief,1,L_WBS,$A13,L_Doeljaar,Sel_Doeljaar,L_Versiejaar,P_VJ,L_Versie,E$8,L_Kengetal,"Omzet FY")=0,"n.b.",SUMIFS(L_Waarde,L_Actief,1,L_WBS,$A13,L_Doeljaar,Sel_Doeljaar,L_Versiejaar,P_VJ,L_Versie,E$8,L_Kengetal,"Omzet FY")))) -> 2177.28 | F13: =IF($A13="","",IF(ISNUMBER(IF(COUNTIFS(L_Actief,1,L_WBS,$A13,L_Doeljaar,Sel_Doeljaar,L_Versiejaar,P_VJ,L_Versie,F$8,L_Kengetal,"Omzet FY")=0,"n.b.",SUMIFS(L_Waarde,L_Actief,1,L_WBS,$A13,L_Doeljaar,Sel_Doeljaar,L_Versiejaar,P_VJ,L_Versie,F$8,L_Kengetal,"Omzet FY"))),IF(COUNTIFS(L_Actief,1,L_WBS,$A13,L_Doeljaar,Sel_Doeljaar,L_Versiejaar,P_VJ,L_Versie,F$8,L_Kengetal,"Omzet FY")=0,"n.b.",SUMIFS(L_Waarde,L_Actief,1,L_WBS,$A13,L_Doeljaar,Sel_Doeljaar,L_Versiejaar,P_VJ,L_Versie,F$8,L_Kengetal,"Omzet FY"))/P_Factor,IF(COUNTIFS(L_Actief,1,L_WBS,$A13,L_Doeljaar,Sel_Doeljaar,L_Versiejaar,P_VJ,L_Versie,F$8,L_Kengetal,"Omzet FY")=0,"n.b.",SUMIFS(L_Waarde,L_Actief,1,L_WBS,$A13,L_Doeljaar,Sel_Doeljaar,L_Versiejaar,P_VJ,L_Versie,F$8,L_Kengetal,"Omzet FY")))) -> 2274.048 | G13: =IF($A13="","",IF(ISNUMBER(IF(COUNTIFS(L_Actief,1,L_WBS,$A13,L_Doeljaar,Sel_Doeljaar,L_Versiejaar,P_VJ,L_Versie,G$8,L_Kengetal,"Omzet FY")=0,"n.b.",SUMIFS(L_Waarde,L_Actief,1,L_WBS,$A13,L_Doeljaar,Sel_Doeljaar,L_Versiejaar,P_VJ,L_Versie,G$8,L_Kengetal,"Omzet FY"))),IF(COUNTIFS(L_Actief,1,L_WBS,$A13,L_Doeljaar,Sel_Doeljaar,L_Versiejaar,P_VJ,L_Versie,G$8,L_Kengetal,"Omzet FY")=0,"n.b.",SUMIFS(L_Waarde,L_Actief,1,L_WBS,$A13,L_Doeljaar,Sel_Doeljaar,L_Versiejaar,P_VJ,L_Versie,G$8,L_Kengetal,"Omzet FY"))/P_Factor,IF(COUNTIFS(L_Actief,1,L_WBS,$A13,L_Doeljaar,Sel_Doeljaar,L_Versiejaar,P_VJ,L_Versie,G$8,L_Kengetal,"Omzet FY")=0,"n.b.",SUMIFS(L_Waarde,L_Actief,1,L_WBS,$A13,L_Doeljaar,Sel_Doeljaar,L_Versiejaar,P_VJ,L_Versie,G$8,L_Kengetal,"Omzet FY")))) -> 2491.776 | H13: =IF($A13="","",IF(ISNUMBER(IF(COUNTIFS(L_Actief,1,L_WBS,$A13,L_Doeljaar,Sel_Doeljaar,L_Versiejaar,P_VJ,L_Versie,H$8,L_Kengetal,"Omzet FY")=0,"n.b.",SUMIFS(L_Waarde,L_Actief,1,L_WBS,$A13,L_Doeljaar,Sel_Doeljaar,L_Versiejaar,P_VJ,L_Versie,H$8,L_Kengetal,"Omzet FY"))),IF(COUNTIFS(L_Actief,1,L_WBS,$A13,L_Doeljaar,Sel_Doeljaar,L_Versiejaar,P_VJ,L_Versie,H$8,L_Kengetal,"Omzet FY")=0,"n.b.",SUMIFS(L_Waarde,L_Actief,1,L_WBS,$A13,L_Doeljaar,Sel_Doeljaar,L_Versiejaar,P_VJ,L_Versie,H$8,L_Kengetal,"Omzet FY"))/P_Factor,IF(COUNTIFS(L_Actief,1,L_WBS,$A13,L_Doeljaar,Sel_Doeljaar,L_Versiejaar,P_VJ,L_Versie,H$8,L_Kengetal,"Omzet FY")=0,"n.b.",SUMIFS(L_Waarde,L_Actief,1,L_WBS,$A13,L_Doeljaar,Sel_Doeljaar,L_Versiejaar,P_VJ,L_Versie,H$8,L_Kengetal,"Omzet FY")))) -> 2419.2 | I13: =IF($A13="","",IF(ISNUMBER(IF(COUNTIFS(L_Actief,1,L_WBS,$A13,L_Doeljaar,Sel_Doeljaar,L_Versiejaar,P_VJ,L_Versie,I$8,L_Kengetal,"Omzet FY")=0,"n.b.",SUMIFS(L_Waarde,L_Actief,1,L_WBS,$A13,L_Doeljaar,Sel_Doeljaar,L_Versiejaar,P_VJ,L_Versie,I$8,L_Kengetal,"Omzet FY"))),IF(COUNTIFS(L_Actief,1,L_WBS,$A13,L_Doeljaar,Sel_Doeljaar,L_Versiejaar,P_VJ,L_Versie,I$8,L_Kengetal,"Omzet FY")=0,"n.b.",SUMIFS(L_Waarde,L_Actief,1,L_WBS,$A13,L_Doeljaar,Sel_Doeljaar,L_Versiejaar,P_VJ,L_Versie,I$8,L_Kengetal,"Omzet FY"))/P_Factor,IF(COUNTIFS(L_Actief,1,L_WBS,$A13,L_Doeljaar,Sel_Doeljaar,L_Versiejaar,P_VJ,L_Versie,I$8,L_Kengetal,"Omzet FY")=0,"n.b.",SUMIFS(L_Waarde,L_Actief,1,L_WBS,$A13,L_Doeljaar,Sel_Doeljaar,L_Versiejaar,P_VJ,L_Versie,I$8,L_Kengetal,"Omzet FY")))) -> n.b. | J13: =IF($A13="","",IF(ISNUMBER(IF(Sel_Doeljaar=P_RJ,VERW_Project!$P9,IF(Sel_Doeljaar=P_RJ+1,VERW_Project!$R9,"n.b."))),IF(Sel_Doeljaar=P_RJ,VERW_Project!$P9,IF(Sel_Doeljaar=P_RJ+1,VERW_Project!$R9,"n.b."))/P_Factor,IF(Sel_Doeljaar=P_RJ,VERW_Project!$P9,IF(Sel_Doeljaar=P_RJ+1,VERW_Project!$R9,"n.b.")))) -> 2419.2 | K13: =IF($A13="","",IF(Sel_Bron="Vastgesteld",INDEX($E13:$I13,MATCH(Sel_Versie,$E$8:$I$8,0)),IF(Sel_Bron="Concept",J13,"n.b."))) -> 2419.2 | L13: =IF($A13="","",IF(Sel_Doeljaar>P_VJ,"n.v.t.",IF(Sel_Bron="Vastgesteld",IF(ISNUMBER(IF(COUNTIFS(L_Actief,1,L_WBS,$A13,L_Doeljaar,Sel_Doeljaar,L_Versiejaar,P_VJ,L_Versie,Sel_Versie,L_Kengetal,"Omzet actual YTD")=0,"n.b.",SUMIFS(L_Waarde,L_Actief,1,L_WBS,$A13,L_Doeljaar,Sel_Doeljaar,L_Versiejaar,P_VJ,L_Versie,Sel_Versie,L_Kengetal,"Omzet actual YTD"))),IF(COUNTIFS(L_Actief,1,L_WBS,$A13,L_Doeljaar,Sel_Doeljaar,L_Versiejaar,P_VJ,L_Versie,Sel_Versie,L_Kengetal,"Omzet actual YTD")=0,"n.b.",SUMIFS(L_Waarde,L_Actief,1,L_WBS,$A13,L_Doeljaar,Sel_Doeljaar,L_Versiejaar,P_VJ,L_Versie,Sel_Versie,L_Kengetal,"Omzet actual YTD"))/P_Factor,IF(COUNTIFS(L_Actief,1,L_WBS,$A13,L_Doeljaar,Sel_Doeljaar,L_Versiejaar,P_VJ,L_Versie,Sel_Versie,L_Kengetal,"Omzet actual YTD")=0,"n.b.",SUMIFS(L_Waarde,L_Actief,1,L_WBS,$A13,L_Doeljaar,Sel_Doeljaar,L_Versiejaar,P_VJ,L_Versie,Sel_Versie,L_Kengetal,"Omzet actual YTD"))),IF(Sel_Bron="Concept",IF(ISNUMBER(IF(Sel_Doeljaar=P_RJ,VERW_Project!$L9,"n.v.t.")),IF(Sel_Doeljaar=P_RJ,VERW_Project!$L9,"n.v.t.")/P_Factor,IF(Sel_Doeljaar=P_RJ,VERW_Project!$L9,"n.v.t.")),"n.b.")))) -> 1572.48 | M13: =IF($A13="","",IF(L13="n.v.t.",K13,IF(AND(ISNUMBER(K13),ISNUMBER(L13)),K13-L13,"n.b."))) -> 846.72 | N13: =IF($A13="","",IF(Sel_Bron="Vastgesteld",IF(ISNUMBER(IF(COUNTIFS(L_Actief,1,L_WBS,$A13,L_Doeljaar,Sel_Doeljaar,L_Versiejaar,P_VJ,L_Versie,Sel_Versie,L_Kengetal,"BOR FY")=0,"n.b.",SUMIFS(L_Waarde,L_Actief,1,L_WBS,$A13,L_Doeljaar,Sel_Doeljaar,L_Versiejaar,P_VJ,L_Versie,Sel_Versie,L_Kengetal,"BOR FY"))),IF(COUNTIFS(L_Actief,1,L_WBS,$A13,L_Doeljaar,Sel_Doeljaar,L_Versiejaar,P_VJ,L_Versie,Sel_Versie,L_Kengetal,"BOR FY")=0,"n.b.",SUMIFS(L_Waarde,L_Actief,1,L_WBS,$A13,L_Doeljaar,Sel_Doeljaar,L_Versiejaar,P_VJ,L_Versie,Sel_Versie,L_Kengetal,"BOR FY"))/P_Factor,IF(COUNTIFS(L_Actief,1,L_WBS,$A13,L_Doeljaar,Sel_Doeljaar,L_Versiejaar,P_VJ,L_Versie,Sel_Versie,L_Kengetal,"BOR FY")=0,"n.b.",SUMIFS(L_Waarde,L_Actief,1,L_WBS,$A13,L_Doeljaar,Sel_Doeljaar,L_Versiejaar,P_VJ,L_Versie,Sel_Versie,L_Kengetal,"BOR FY"))),IF(Sel_Bron="Concept",IF(ISNUMBER(IF(Sel_Doeljaar=P_RJ,VERW_Project!$Q9,IF(Sel_Doeljaar=P_RJ+1,VERW_Project!$S9,"n.b."))),IF(Sel_Doeljaar=P_RJ,VERW_Project!$Q9,IF(Sel_Doeljaar=P_RJ+1,VERW_Project!$S9,"n.b."))/P_Factor,IF(Sel_Doeljaar=P_RJ,VERW_Project!$Q9,IF(Sel_Doeljaar=P_RJ+1,VERW_Project!$S9,"n.b."))),"n.b."))) -> 266.112 | O13: =IF($A13="","",IF(AND(ISNUMBER(N13),ISNUMBER(K13)),IF(K13<>0,N13/K13,"n.b."),"n.b.")) -> 0.11 | P13: =IF($A13="","",IF(AND(ISNUMBER(K13),ISNUMBER(E13)),K13-E13,"n.b.")) -> 241.92 | Q13: =IF($A13="","",IF(AND(ISNUMBER(K13),ISNUMBER(W13)),K13-W13,"n.b.")) -> -72.576 | R13: =IF($A13="","",IF(ISNUMBER(N13),IF(N13<0,"Verlies",""),"")) | S13: =IF($A13="","",IFERROR(INDEX(T_Txt,MATCH($A13&"|"&Sel_Doeljaar&"|"&P_VJ&"|"&Sel_Versie,T_Key,0)),"")) | U13: =IF(AND(AND($A13<>"",OR(Sel_Type="Alle",$C13=Sel_Type),OR(Sel_Project="Alle",$B13=Sel_Project)),ISNUMBER(K13)),K13+ROW()/1000000000,"") -> 2419.2 | V13: =IF(AND(AND($A13<>"",OR(Sel_Type="Alle",$C13=Sel_Type),OR(Sel_Project="Alle",$B13=Sel_Project)),ISNUMBER(Q13)),ABS(Q13)+ROW()/1000000000,"") -> 72.576 | W13: =IF(OR($A13="",Sel_Prev=""),"n.b.",IF(ISNUMBER(IF(COUNTIFS(L_Actief,1,L_WBS,$A13,L_Doeljaar,Sel_Doeljaar,L_Versiejaar,P_VJ,L_Versie,Sel_Prev,L_Kengetal,"Omzet FY")=0,"n.b.",SUMIFS(L_Waarde,L_Actief,1,L_WBS,$A13,L_Doeljaar,Sel_Doeljaar,L_Versiejaar,P_VJ,L_Versie,Sel_Prev,L_Kengetal,"Omzet FY"))),IF(COUNTIFS(L_Actief,1,L_WBS,$A13,L_Doeljaar,Sel_Doeljaar,L_Versiejaar,P_VJ,L_Versie,Sel_Prev,L_Kengetal,"Omzet FY")=0,"n.b.",SUMIFS(L_Waarde,L_Actief,1,L_WBS,$A13,L_Doeljaar,Sel_Doeljaar,L_Versiejaar,P_VJ,L_Versie,Sel_Prev,L_Kengetal,"Omzet FY"))/P_Factor,IF(COUNTIFS(L_Actief,1,L_WBS,$A13,L_Doeljaar,Sel_Doeljaar,L_Versiejaar,P_VJ,L_Versie,Sel_Prev,L_Kengetal,"Omzet FY")=0,"n.b.",SUMIFS(L_Waarde,L_Actief,1,L_WBS,$A13,L_Doeljaar,Sel_Doeljaar,L_Versiejaar,P_VJ,L_Versie,Sel_Prev,L_Kengetal,"Omzet FY")))) -> 2491.776
A14: =IF(VERW_Project!$A10="","",VERW_Project!$A10) -> G.900005.8.9090 | B14: =IF($A14="","",VERW_Project!$C10) -> Zilverdam, Kadezicht | C14: =IF($A14="","",VERW_Project!$D10) -> Opstal | D14: =IF($A14="","",VERW_Project!$I10) -> J | E14: =IF($A14="","",IF(ISNUMBER(IF(COUNTIFS(L_Actief,1,L_WBS,$A14,L_Doeljaar,Sel_Doeljaar,L_Versiejaar,P_VJ,L_Versie,E$8,L_Kengetal,"Omzet FY")=0,"n.b.",SUMIFS(L_Waarde,L_Actief,1,L_WBS,$A14,L_Doeljaar,Sel_Doeljaar,L_Versiejaar,P_VJ,L_Versie,E$8,L_Kengetal,"Omzet FY"))),IF(COUNTIFS(L_Actief,1,L_WBS,$A14,L_Doeljaar,Sel_Doeljaar,L_Versiejaar,P_VJ,L_Versie,E$8,L_Kengetal,"Omzet FY")=0,"n.b.",SUMIFS(L_Waarde,L_Actief,1,L_WBS,$A14,L_Doeljaar,Sel_Doeljaar,L_Versiejaar,P_VJ,L_Versie,E$8,L_Kengetal,"Omzet FY"))/P_Factor,IF(COUNTIFS(L_Actief,1,L_WBS,$A14,L_Doeljaar,Sel_Doeljaar,L_Versiejaar,P_VJ,L_Versie,E$8,L_Kengetal,"Omzet FY")=0,"n.b.",SUMIFS(L_Waarde,L_Actief,1,L_WBS,$A14,L_Doeljaar,Sel_Doeljaar,L_Versiejaar,P_VJ,L_Versie,E$8,L_Kengetal,"Omzet FY")))) -> 7392 | F14: =IF($A14="","",IF(ISNUMBER(IF(COUNTIFS(L_Actief,1,L_WBS,$A14,L_Doeljaar,Sel_Doeljaar,L_Versiejaar,P_VJ,L_Versie,F$8,L_Kengetal,"Omzet FY")=0,"n.b.",SUMIFS(L_Waarde,L_Actief,1,L_WBS,$A14,L_Doeljaar,Sel_Doeljaar,L_Versiejaar,P_VJ,L_Versie,F$8,L_Kengetal,"Omzet FY"))),IF(COUNTIFS(L_Actief,1,L_WBS,$A14,L_Doeljaar,Sel_Doeljaar,L_Versiejaar,P_VJ,L_Versie,F$8,L_Kengetal,"Omzet FY")=0,"n.b.",SUMIFS(L_Waarde,L_Actief,1,L_WBS,$A14,L_Doeljaar,Sel_Doeljaar,L_Versiejaar,P_VJ,L_Versie,F$8,L_Kengetal,"Omzet FY"))/P_Factor,IF(COUNTIFS(L_Actief,1,L_WBS,$A14,L_Doeljaar,Sel_Doeljaar,L_Versiejaar,P_VJ,L_Versie,F$8,L_Kengetal,"Omzet FY")=0,"n.b.",SUMIFS(L_Waarde,L_Actief,1,L_WBS,$A14,L_Doeljaar,Sel_Doeljaar,L_Versiejaar,P_VJ,L_Versie,F$8,L_Kengetal,"Omzet FY")))) -> 7123.2 | G14: =IF($A14="","",IF(ISNUMBER(IF(COUNTIFS(L_Actief,1,L_WBS,$A14,L_Doeljaar,Sel_Doeljaar,L_Versiejaar,P_VJ,L_Versie,G$8,L_Kengetal,"Omzet FY")=0,"n.b.",SUMIFS(L_Waarde,L_Actief,1,L_WBS,$A14,L_Doeljaar,Sel_Doeljaar,L_Versiejaar,P_VJ,L_Versie,G$8,L_Kengetal,"Omzet FY"))),IF(COUNTIFS(L_Actief,1,L_WBS,$A14,L_Doeljaar,Sel_Doeljaar,L_Versiejaar,P_VJ,L_Versie,G$8,L_Kengetal,"Omzet FY")=0,"n.b.",SUMIFS(L_Waarde,L_Actief,1,L_WBS,$A14,L_Doeljaar,Sel_Doeljaar,L_Versiejaar,P_VJ,L_Versie,G$8,L_Kengetal,"Omzet FY"))/P_Factor,IF(COUNTIFS(L_Actief,1,L_WBS,$A14,L_Doeljaar,Sel_Doeljaar,L_Versiejaar,P_VJ,L_Versie,G$8,L_Kengetal,"Omzet FY")=0,"n.b.",SUMIFS(L_Waarde,L_Actief,1,L_WBS,$A14,L_Doeljaar,Sel_Doeljaar,L_Versiejaar,P_VJ,L_Versie,G$8,L_Kengetal,"Omzet FY")))) -> 6518.4 | H14: =IF($A14="","",IF(ISNUMBER(IF(COUNTIFS(L_Actief,1,L_WBS,$A14,L_Doeljaar,Sel_Doeljaar,L_Versiejaar,P_VJ,L_Versie,H$8,L_Kengetal,"Omzet FY")=0,"n.b.",SUMIFS(L_Waarde,L_Actief,1,L_WBS,$A14,L_Doeljaar,Sel_Doeljaar,L_Versiejaar,P_VJ,L_Versie,H$8,L_Kengetal,"Omzet FY"))),IF(COUNTIFS(L_Actief,1,L_WBS,$A14,L_Doeljaar,Sel_Doeljaar,L_Versiejaar,P_VJ,L_Versie,H$8,L_Kengetal,"Omzet FY")=0,"n.b.",SUMIFS(L_Waarde,L_Actief,1,L_WBS,$A14,L_Doeljaar,Sel_Doeljaar,L_Versiejaar,P_VJ,L_Versie,H$8,L_Kengetal,"Omzet FY"))/P_Factor,IF(COUNTIFS(L_Actief,1,L_WBS,$A14,L_Doeljaar,Sel_Doeljaar,L_Versiejaar,P_VJ,L_Versie,H$8,L_Kengetal,"Omzet FY")=0,"n.b.",SUMIFS(L_Waarde,L_Actief,1,L_WBS,$A14,L_Doeljaar,Sel_Doeljaar,L_Versiejaar,P_VJ,L_Versie,H$8,L_Kengetal,"Omzet FY")))) -> 6720 | I14: =IF($A14="","",IF(ISNUMBER(IF(COUNTIFS(L_Actief,1,L_WBS,$A14,L_Doeljaar,Sel_Doeljaar,L_Versiejaar,P_VJ,L_Versie,I$8,L_Kengetal,"Omzet FY")=0,"n.b.",SUMIFS(L_Waarde,L_Actief,1,L_WBS,$A14,L_Doeljaar,Sel_Doeljaar,L_Versiejaar,P_VJ,L_Versie,I$8,L_Kengetal,"Omzet FY"))),IF(COUNTIFS(L_Actief,1,L_WBS,$A14,L_Doeljaar,Sel_Doeljaar,L_Versiejaar,P_VJ,L_Versie,I$8,L_Kengetal,"Omzet FY")=0,"n.b.",SUMIFS(L_Waarde,L_Actief,1,L_WBS,$A14,L_Doeljaar,Sel_Doeljaar,L_Versiejaar,P_VJ,L_Versie,I$8,L_Kengetal,"Omzet FY"))/P_Factor,IF(COUNTIFS(L_Actief,1,L_WBS,$A14,L_Doeljaar,Sel_Doeljaar,L_Versiejaar,P_VJ,L_Versie,I$8,L_Kengetal,"Omzet FY")=0,"n.b.",SUMIFS(L_Waarde,L_Actief,1,L_WBS,$A14,L_Doeljaar,Sel_Doeljaar,L_Versiejaar,P_VJ,L_Versie,I$8,L_Kengetal,"Omzet FY")))) -> n.b. | J14: =IF($A14="","",IF(ISNUMBER(IF(Sel_Doeljaar=P_RJ,VERW_Project!$P10,IF(Sel_Doeljaar=P_RJ+1,VERW_Project!$R10,"n.b."))),IF(Sel_Doeljaar=P_RJ,VERW_Project!$P10,IF(Sel_Doeljaar=P_RJ+1,VERW_Project!$R10,"n.b."))/P_Factor,IF(Sel_Doeljaar=P_RJ,VERW_Project!$P10,IF(Sel_Doeljaar=P_RJ+1,VERW_Project!$R10,"n.b.")))) -> 6720 | K14: =IF($A14="","",IF(Sel_Bron="Vastgesteld",INDEX($E14:$I14,MATCH(Sel_Versie,$E$8:$I$8,0)),IF(Sel_Bron="Concept",J14,"n.b."))) -> 6720 | L14: =IF($A14="","",IF(Sel_Doeljaar>P_VJ,"n.v.t.",IF(Sel_Bron="Vastgesteld",IF(ISNUMBER(IF(COUNTIFS(L_Actief,1,L_WBS,$A14,L_Doeljaar,Sel_Doeljaar,L_Versiejaar,P_VJ,L_Versie,Sel_Versie,L_Kengetal,"Omzet actual YTD")=0,"n.b.",SUMIFS(L_Waarde,L_Actief,1,L_WBS,$A14,L_Doeljaar,Sel_Doeljaar,L_Versiejaar,P_VJ,L_Versie,Sel_Versie,L_Kengetal,"Omzet actual YTD"))),IF(COUNTIFS(L_Actief,1,L_WBS,$A14,L_Doeljaar,Sel_Doeljaar,L_Versiejaar,P_VJ,L_Versie,Sel_Versie,L_Kengetal,"Omzet actual YTD")=0,"n.b.",SUMIFS(L_Waarde,L_Actief,1,L_WBS,$A14,L_Doeljaar,Sel_Doeljaar,L_Versiejaar,P_VJ,L_Versie,Sel_Versie,L_Kengetal,"Omzet actual YTD"))/P_Factor,IF(COUNTIFS(L_Actief,1,L_WBS,$A14,L_Doeljaar,Sel_Doeljaar,L_Versiejaar,P_VJ,L_Versie,Sel_Versie,L_Kengetal,"Omzet actual YTD")=0,"n.b.",SUMIFS(L_Waarde,L_Actief,1,L_WBS,$A14,L_Doeljaar,Sel_Doeljaar,L_Versiejaar,P_VJ,L_Versie,Sel_Versie,L_Kengetal,"Omzet actual YTD"))),IF(Sel_Bron="Concept",IF(ISNUMBER(IF(Sel_Doeljaar=P_RJ,VERW_Project!$L10,"n.v.t.")),IF(Sel_Doeljaar=P_RJ,VERW_Project!$L10,"n.v.t.")/P_Factor,IF(Sel_Doeljaar=P_RJ,VERW_Project!$L10,"n.v.t.")),"n.b.")))) -> 4368 | M14: =IF($A14="","",IF(L14="n.v.t.",K14,IF(AND(ISNUMBER(K14),ISNUMBER(L14)),K14-L14,"n.b."))) -> 2352 | N14: =IF($A14="","",IF(Sel_Bron="Vastgesteld",IF(ISNUMBER(IF(COUNTIFS(L_Actief,1,L_WBS,$A14,L_Doeljaar,Sel_Doeljaar,L_Versiejaar,P_VJ,L_Versie,Sel_Versie,L_Kengetal,"BOR FY")=0,"n.b.",SUMIFS(L_Waarde,L_Actief,1,L_WBS,$A14,L_Doeljaar,Sel_Doeljaar,L_Versiejaar,P_VJ,L_Versie,Sel_Versie,L_Kengetal,"BOR FY"))),IF(COUNTIFS(L_Actief,1,L_WBS,$A14,L_Doeljaar,Sel_Doeljaar,L_Versiejaar,P_VJ,L_Versie,Sel_Versie,L_Kengetal,"BOR FY")=0,"n.b.",SUMIFS(L_Waarde,L_Actief,1,L_WBS,$A14,L_Doeljaar,Sel_Doeljaar,L_Versiejaar,P_VJ,L_Versie,Sel_Versie,L_Kengetal,"BOR FY"))/P_Factor,IF(COUNTIFS(L_Actief,1,L_WBS,$A14,L_Doeljaar,Sel_Doeljaar,L_Versiejaar,P_VJ,L_Versie,Sel_Versie,L_Kengetal,"BOR FY")=0,"n.b.",SUMIFS(L_Waarde,L_Actief,1,L_WBS,$A14,L_Doeljaar,Sel_Doeljaar,L_Versiejaar,P_VJ,L_Versie,Sel_Versie,L_Kengetal,"BOR FY"))),IF(Sel_Bron="Concept",IF(ISNUMBER(IF(Sel_Doeljaar=P_RJ,VERW_Project!$Q10,IF(Sel_Doeljaar=P_RJ+1,VERW_Project!$S10,"n.b."))),IF(Sel_Doeljaar=P_RJ,VERW_Project!$Q10,IF(Sel_Doeljaar=P_RJ+1,VERW_Project!$S10,"n.b."))/P_Factor,IF(Sel_Doeljaar=P_RJ,VERW_Project!$Q10,IF(Sel_Doeljaar=P_RJ+1,VERW_Project!$S10,"n.b."))),"n.b."))) -> 436.8 | O14: =IF($A14="","",IF(AND(ISNUMBER(N14),ISNUMBER(K14)),IF(K14<>0,N14/K14,"n.b."),"n.b.")) -> 0.065 | P14: =IF($A14="","",IF(AND(ISNUMBER(K14),ISNUMBER(E14)),K14-E14,"n.b.")) -> -672 | Q14: =IF($A14="","",IF(AND(ISNUMBER(K14),ISNUMBER(W14)),K14-W14,"n.b.")) -> 201.6 | R14: =IF($A14="","",IF(ISNUMBER(N14),IF(N14<0,"Verlies",""),"")) | S14: =IF($A14="","",IFERROR(INDEX(T_Txt,MATCH($A14&"|"&Sel_Doeljaar&"|"&P_VJ&"|"&Sel_Versie,T_Key,0)),"")) | U14: =IF(AND(AND($A14<>"",OR(Sel_Type="Alle",$C14=Sel_Type),OR(Sel_Project="Alle",$B14=Sel_Project)),ISNUMBER(K14)),K14+ROW()/1000000000,"") -> 6720 | V14: =IF(AND(AND($A14<>"",OR(Sel_Type="Alle",$C14=Sel_Type),OR(Sel_Project="Alle",$B14=Sel_Project)),ISNUMBER(Q14)),ABS(Q14)+ROW()/1000000000,"") -> 201.6 | W14: =IF(OR($A14="",Sel_Prev=""),"n.b.",IF(ISNUMBER(IF(COUNTIFS(L_Actief,1,L_WBS,$A14,L_Doeljaar,Sel_Doeljaar,L_Versiejaar,P_VJ,L_Versie,Sel_Prev,L_Kengetal,"Omzet FY")=0,"n.b.",SUMIFS(L_Waarde,L_Actief,1,L_WBS,$A14,L_Doeljaar,Sel_Doeljaar,L_Versiejaar,P_VJ,L_Versie,Sel_Prev,L_Kengetal,"Omzet FY"))),IF(COUNTIFS(L_Actief,1,L_WBS,$A14,L_Doeljaar,Sel_Doeljaar,L_Versiejaar,P_VJ,L_Versie,Sel_Prev,L_Kengetal,"Omzet FY")=0,"n.b.",SUMIFS(L_Waarde,L_Actief,1,L_WBS,$A14,L_Doeljaar,Sel_Doeljaar,L_Versiejaar,P_VJ,L_Versie,Sel_Prev,L_Kengetal,"Omzet FY"))/P_Factor,IF(COUNTIFS(L_Actief,1,L_WBS,$A14,L_Doeljaar,Sel_Doeljaar,L_Versiejaar,P_VJ,L_Versie,Sel_Prev,L_Kengetal,"Omzet FY")=0,"n.b.",SUMIFS(L_Waarde,L_Actief,1,L_WBS,$A14,L_Doeljaar,Sel_Doeljaar,L_Versiejaar,P_VJ,L_Versie,Sel_Prev,L_Kengetal,"Omzet FY")))) -> 6518.4
A15: =IF(VERW_Project!$A11="","",VERW_Project!$A11) -> G.900006.8.9090 | B15: =IF($A15="","",VERW_Project!$C11) -> Boswaard, De Eiken | C15: =IF($A15="","",VERW_Project!$D11) -> Opstal | D15: =IF($A15="","",VERW_Project!$I11) -> J | E15: =IF($A15="","",IF(ISNUMBER(IF(COUNTIFS(L_Actief,1,L_WBS,$A15,L_Doeljaar,Sel_Doeljaar,L_Versiejaar,P_VJ,L_Versie,E$8,L_Kengetal,"Omzet FY")=0,"n.b.",SUMIFS(L_Waarde,L_Actief,1,L_WBS,$A15,L_Doeljaar,Sel_Doeljaar,L_Versiejaar,P_VJ,L_Versie,E$8,L_Kengetal,"Omzet FY"))),IF(COUNTIFS(L_Actief,1,L_WBS,$A15,L_Doeljaar,Sel_Doeljaar,L_Versiejaar,P_VJ,L_Versie,E$8,L_Kengetal,"Omzet FY")=0,"n.b.",SUMIFS(L_Waarde,L_Actief,1,L_WBS,$A15,L_Doeljaar,Sel_Doeljaar,L_Versiejaar,P_VJ,L_Versie,E$8,L_Kengetal,"Omzet FY"))/P_Factor,IF(COUNTIFS(L_Actief,1,L_WBS,$A15,L_Doeljaar,Sel_Doeljaar,L_Versiejaar,P_VJ,L_Versie,E$8,L_Kengetal,"Omzet FY")=0,"n.b.",SUMIFS(L_Waarde,L_Actief,1,L_WBS,$A15,L_Doeljaar,Sel_Doeljaar,L_Versiejaar,P_VJ,L_Versie,E$8,L_Kengetal,"Omzet FY")))) -> 5909.76 | F15: =IF($A15="","",IF(ISNUMBER(IF(COUNTIFS(L_Actief,1,L_WBS,$A15,L_Doeljaar,Sel_Doeljaar,L_Versiejaar,P_VJ,L_Versie,F$8,L_Kengetal,"Omzet FY")=0,"n.b.",SUMIFS(L_Waarde,L_Actief,1,L_WBS,$A15,L_Doeljaar,Sel_Doeljaar,L_Versiejaar,P_VJ,L_Versie,F$8,L_Kengetal,"Omzet FY"))),IF(COUNTIFS(L_Actief,1,L_WBS,$A15,L_Doeljaar,Sel_Doeljaar,L_Versiejaar,P_VJ,L_Versie,F$8,L_Kengetal,"Omzet FY")=0,"n.b.",SUMIFS(L_Waarde,L_Actief,1,L_WBS,$A15,L_Doeljaar,Sel_Doeljaar,L_Versiejaar,P_VJ,L_Versie,F$8,L_Kengetal,"Omzet FY"))/P_Factor,IF(COUNTIFS(L_Actief,1,L_WBS,$A15,L_Doeljaar,Sel_Doeljaar,L_Versiejaar,P_VJ,L_Versie,F$8,L_Kengetal,"Omzet FY")=0,"n.b.",SUMIFS(L_Waarde,L_Actief,1,L_WBS,$A15,L_Doeljaar,Sel_Doeljaar,L_Versiejaar,P_VJ,L_Versie,F$8,L_Kengetal,"Omzet FY")))) -> 6172.416 | G15: =IF($A15="","",IF(ISNUMBER(IF(COUNTIFS(L_Actief,1,L_WBS,$A15,L_Doeljaar,Sel_Doeljaar,L_Versiejaar,P_VJ,L_Versie,G$8,L_Kengetal,"Omzet FY")=0,"n.b.",SUMIFS(L_Waarde,L_Actief,1,L_WBS,$A15,L_Doeljaar,Sel_Doeljaar,L_Versiejaar,P_VJ,L_Versie,G$8,L_Kengetal,"Omzet FY"))),IF(COUNTIFS(L_Actief,1,L_WBS,$A15,L_Doeljaar,Sel_Doeljaar,L_Versiejaar,P_VJ,L_Versie,G$8,L_Kengetal,"Omzet FY")=0,"n.b.",SUMIFS(L_Waarde,L_Actief,1,L_WBS,$A15,L_Doeljaar,Sel_Doeljaar,L_Versiejaar,P_VJ,L_Versie,G$8,L_Kengetal,"Omzet FY"))/P_Factor,IF(COUNTIFS(L_Actief,1,L_WBS,$A15,L_Doeljaar,Sel_Doeljaar,L_Versiejaar,P_VJ,L_Versie,G$8,L_Kengetal,"Omzet FY")=0,"n.b.",SUMIFS(L_Waarde,L_Actief,1,L_WBS,$A15,L_Doeljaar,Sel_Doeljaar,L_Versiejaar,P_VJ,L_Versie,G$8,L_Kengetal,"Omzet FY")))) -> 6763.392 | H15: =IF($A15="","",IF(ISNUMBER(IF(COUNTIFS(L_Actief,1,L_WBS,$A15,L_Doeljaar,Sel_Doeljaar,L_Versiejaar,P_VJ,L_Versie,H$8,L_Kengetal,"Omzet FY")=0,"n.b.",SUMIFS(L_Waarde,L_Actief,1,L_WBS,$A15,L_Doeljaar,Sel_Doeljaar,L_Versiejaar,P_VJ,L_Versie,H$8,L_Kengetal,"Omzet FY"))),IF(COUNTIFS(L_Actief,1,L_WBS,$A15,L_Doeljaar,Sel_Doeljaar,L_Versiejaar,P_VJ,L_Versie,H$8,L_Kengetal,"Omzet FY")=0,"n.b.",SUMIFS(L_Waarde,L_Actief,1,L_WBS,$A15,L_Doeljaar,Sel_Doeljaar,L_Versiejaar,P_VJ,L_Versie,H$8,L_Kengetal,"Omzet FY"))/P_Factor,IF(COUNTIFS(L_Actief,1,L_WBS,$A15,L_Doeljaar,Sel_Doeljaar,L_Versiejaar,P_VJ,L_Versie,H$8,L_Kengetal,"Omzet FY")=0,"n.b.",SUMIFS(L_Waarde,L_Actief,1,L_WBS,$A15,L_Doeljaar,Sel_Doeljaar,L_Versiejaar,P_VJ,L_Versie,H$8,L_Kengetal,"Omzet FY")))) -> 6566.4 | I15: =IF($A15="","",IF(ISNUMBER(IF(COUNTIFS(L_Actief,1,L_WBS,$A15,L_Doeljaar,Sel_Doeljaar,L_Versiejaar,P_VJ,L_Versie,I$8,L_Kengetal,"Omzet FY")=0,"n.b.",SUMIFS(L_Waarde,L_Actief,1,L_WBS,$A15,L_Doeljaar,Sel_Doeljaar,L_Versiejaar,P_VJ,L_Versie,I$8,L_Kengetal,"Omzet FY"))),IF(COUNTIFS(L_Actief,1,L_WBS,$A15,L_Doeljaar,Sel_Doeljaar,L_Versiejaar,P_VJ,L_Versie,I$8,L_Kengetal,"Omzet FY")=0,"n.b.",SUMIFS(L_Waarde,L_Actief,1,L_WBS,$A15,L_Doeljaar,Sel_Doeljaar,L_Versiejaar,P_VJ,L_Versie,I$8,L_Kengetal,"Omzet FY"))/P_Factor,IF(COUNTIFS(L_Actief,1,L_WBS,$A15,L_Doeljaar,Sel_Doeljaar,L_Versiejaar,P_VJ,L_Versie,I$8,L_Kengetal,"Omzet FY")=0,"n.b.",SUMIFS(L_Waarde,L_Actief,1,L_WBS,$A15,L_Doeljaar,Sel_Doeljaar,L_Versiejaar,P_VJ,L_Versie,I$8,L_Kengetal,"Omzet FY")))) -> n.b. | J15: =IF($A15="","",IF(ISNUMBER(IF(Sel_Doeljaar=P_RJ,VERW_Project!$P11,IF(Sel_Doeljaar=P_RJ+1,VERW_Project!$R11,"n.b."))),IF(Sel_Doeljaar=P_RJ,VERW_Project!$P11,IF(Sel_Doeljaar=P_RJ+1,VERW_Project!$R11,"n.b."))/P_Factor,IF(Sel_Doeljaar=P_RJ,VERW_Project!$P11,IF(Sel_Doeljaar=P_RJ+1,VERW_Project!$R11,"n.b.")))) -> 6566.4 | K15: =IF($A15="","",IF(Sel_Bron="Vastgesteld",INDEX($E15:$I15,MATCH(Sel_Versie,$E$8:$I$8,0)),IF(Sel_Bron="Concept",J15,"n.b."))) -> 6566.4 | L15: =IF($A15="","",IF(Sel_Doeljaar>P_VJ,"n.v.t.",IF(Sel_Bron="Vastgesteld",IF(ISNUMBER(IF(COUNTIFS(L_Actief,1,L_WBS,$A15,L_Doeljaar,Sel_Doeljaar,L_Versiejaar,P_VJ,L_Versie,Sel_Versie,L_Kengetal,"Omzet actual YTD")=0,"n.b.",SUMIFS(L_Waarde,L_Actief,1,L_WBS,$A15,L_Doeljaar,Sel_Doeljaar,L_Versiejaar,P_VJ,L_Versie,Sel_Versie,L_Kengetal,"Omzet actual YTD"))),IF(COUNTIFS(L_Actief,1,L_WBS,$A15,L_Doeljaar,Sel_Doeljaar,L_Versiejaar,P_VJ,L_Versie,Sel_Versie,L_Kengetal,"Omzet actual YTD")=0,"n.b.",SUMIFS(L_Waarde,L_Actief,1,L_WBS,$A15,L_Doeljaar,Sel_Doeljaar,L_Versiejaar,P_VJ,L_Versie,Sel_Versie,L_Kengetal,"Omzet actual YTD"))/P_Factor,IF(COUNTIFS(L_Actief,1,L_WBS,$A15,L_Doeljaar,Sel_Doeljaar,L_Versiejaar,P_VJ,L_Versie,Sel_Versie,L_Kengetal,"Omzet actual YTD")=0,"n.b.",SUMIFS(L_Waarde,L_Actief,1,L_WBS,$A15,L_Doeljaar,Sel_Doeljaar,L_Versiejaar,P_VJ,L_Versie,Sel_Versie,L_Kengetal,"Omzet actual YTD"))),IF(Sel_Bron="Concept",IF(ISNUMBER(IF(Sel_Doeljaar=P_RJ,VERW_Project!$L11,"n.v.t.")),IF(Sel_Doeljaar=P_RJ,VERW_Project!$L11,"n.v.t.")/P_Factor,IF(Sel_Doeljaar=P_RJ,VERW_Project!$L11,"n.v.t.")),"n.b.")))) -> 4268.16 | M15: =IF($A15="","",IF(L15="n.v.t.",K15,IF(AND(ISNUMBER(K15),ISNUMBER(L15)),K15-L15,"n.b."))) -> 2298.24 | N15: =IF($A15="","",IF(Sel_Bron="Vastgesteld",IF(ISNUMBER(IF(COUNTIFS(L_Actief,1,L_WBS,$A15,L_Doeljaar,Sel_Doeljaar,L_Versiejaar,P_VJ,L_Versie,Sel_Versie,L_Kengetal,"BOR FY")=0,"n.b.",SUMIFS(L_Waarde,L_Actief,1,L_WBS,$A15,L_Doeljaar,Sel_Doeljaar,L_Versiejaar,P_VJ,L_Versie,Sel_Versie,L_Kengetal,"BOR FY"))),IF(COUNTIFS(L_Actief,1,L_WBS,$A15,L_Doeljaar,Sel_Doeljaar,L_Versiejaar,P_VJ,L_Versie,Sel_Versie,L_Kengetal,"BOR FY")=0,"n.b.",SUMIFS(L_Waarde,L_Actief,1,L_WBS,$A15,L_Doeljaar,Sel_Doeljaar,L_Versiejaar,P_VJ,L_Versie,Sel_Versie,L_Kengetal,"BOR FY"))/P_Factor,IF(COUNTIFS(L_Actief,1,L_WBS,$A15,L_Doeljaar,Sel_Doeljaar,L_Versiejaar,P_VJ,L_Versie,Sel_Versie,L_Kengetal,"BOR FY")=0,"n.b.",SUMIFS(L_Waarde,L_Actief,1,L_WBS,$A15,L_Doeljaar,Sel_Doeljaar,L_Versiejaar,P_VJ,L_Versie,Sel_Versie,L_Kengetal,"BOR FY"))),IF(Sel_Bron="Concept",IF(ISNUMBER(IF(Sel_Doeljaar=P_RJ,VERW_Project!$Q11,IF(Sel_Doeljaar=P_RJ+1,VERW_Project!$S11,"n.b."))),IF(Sel_Doeljaar=P_RJ,VERW_Project!$Q11,IF(Sel_Doeljaar=P_RJ+1,VERW_Project!$S11,"n.b."))/P_Factor,IF(Sel_Doeljaar=P_RJ,VERW_Project!$Q11,IF(Sel_Doeljaar=P_RJ+1,VERW_Project!$S11,"n.b."))),"n.b."))) -> 919.296 | O15: =IF($A15="","",IF(AND(ISNUMBER(N15),ISNUMBER(K15)),IF(K15<>0,N15/K15,"n.b."),"n.b.")) -> 0.14 | P15: =IF($A15="","",IF(AND(ISNUMBER(K15),ISNUMBER(E15)),K15-E15,"n.b.")) -> 656.64 | Q15: =IF($A15="","",IF(AND(ISNUMBER(K15),ISNUMBER(W15)),K15-W15,"n.b.")) -> -196.992 | R15: =IF($A15="","",IF(ISNUMBER(N15),IF(N15<0,"Verlies",""),"")) | S15: =IF($A15="","",IFERROR(INDEX(T_Txt,MATCH($A15&"|"&Sel_Doeljaar&"|"&P_VJ&"|"&Sel_Versie,T_Key,0)),"")) | U15: =IF(AND(AND($A15<>"",OR(Sel_Type="Alle",$C15=Sel_Type),OR(Sel_Project="Alle",$B15=Sel_Project)),ISNUMBER(K15)),K15+ROW()/1000000000,"") -> 6566.4 | V15: =IF(AND(AND($A15<>"",OR(Sel_Type="Alle",$C15=Sel_Type),OR(Sel_Project="Alle",$B15=Sel_Project)),ISNUMBER(Q15)),ABS(Q15)+ROW()/1000000000,"") -> 196.992 | W15: =IF(OR($A15="",Sel_Prev=""),"n.b.",IF(ISNUMBER(IF(COUNTIFS(L_Actief,1,L_WBS,$A15,L_Doeljaar,Sel_Doeljaar,L_Versiejaar,P_VJ,L_Versie,Sel_Prev,L_Kengetal,"Omzet FY")=0,"n.b.",SUMIFS(L_Waarde,L_Actief,1,L_WBS,$A15,L_Doeljaar,Sel_Doeljaar,L_Versiejaar,P_VJ,L_Versie,Sel_Prev,L_Kengetal,"Omzet FY"))),IF(COUNTIFS(L_Actief,1,L_WBS,$A15,L_Doeljaar,Sel_Doeljaar,L_Versiejaar,P_VJ,L_Versie,Sel_Prev,L_Kengetal,"Omzet FY")=0,"n.b.",SUMIFS(L_Waarde,L_Actief,1,L_WBS,$A15,L_Doeljaar,Sel_Doeljaar,L_Versiejaar,P_VJ,L_Versie,Sel_Prev,L_Kengetal,"Omzet FY"))/P_Factor,IF(COUNTIFS(L_Actief,1,L_WBS,$A15,L_Doeljaar,Sel_Doeljaar,L_Versiejaar,P_VJ,L_Versie,Sel_Prev,L_Kengetal,"Omzet FY")=0,"n.b.",SUMIFS(L_Waarde,L_Actief,1,L_WBS,$A15,L_Doeljaar,Sel_Doeljaar,L_Versiejaar,P_VJ,L_Versie,Sel_Prev,L_Kengetal,"Omzet FY")))) -> 6763.392
A16: =IF(VERW_Project!$A12="","",VERW_Project!$A12) -> G.900007.8.9090 | B16: =IF($A16="","",VERW_Project!$C12) -> Rietdam, Havenkwartier | C16: =IF($A16="","",VERW_Project!$D12) -> Opstal | D16: =IF($A16="","",VERW_Project!$I12) -> J | E16: =IF($A16="","",IF(ISNUMBER(IF(COUNTIFS(L_Actief,1,L_WBS,$A16,L_Doeljaar,Sel_Doeljaar,L_Versiejaar,P_VJ,L_Versie,E$8,L_Kengetal,"Omzet FY")=0,"n.b.",SUMIFS(L_Waarde,L_Actief,1,L_WBS,$A16,L_Doeljaar,Sel_Doeljaar,L_Versiejaar,P_VJ,L_Versie,E$8,L_Kengetal,"Omzet FY"))),IF(COUNTIFS(L_Actief,1,L_WBS,$A16,L_Doeljaar,Sel_Doeljaar,L_Versiejaar,P_VJ,L_Versie,E$8,L_Kengetal,"Omzet FY")=0,"n.b.",SUMIFS(L_Waarde,L_Actief,1,L_WBS,$A16,L_Doeljaar,Sel_Doeljaar,L_Versiejaar,P_VJ,L_Versie,E$8,L_Kengetal,"Omzet FY"))/P_Factor,IF(COUNTIFS(L_Actief,1,L_WBS,$A16,L_Doeljaar,Sel_Doeljaar,L_Versiejaar,P_VJ,L_Versie,E$8,L_Kengetal,"Omzet FY")=0,"n.b.",SUMIFS(L_Waarde,L_Actief,1,L_WBS,$A16,L_Doeljaar,Sel_Doeljaar,L_Versiejaar,P_VJ,L_Versie,E$8,L_Kengetal,"Omzet FY")))) -> 6688 | F16: =IF($A16="","",IF(ISNUMBER(IF(COUNTIFS(L_Actief,1,L_WBS,$A16,L_Doeljaar,Sel_Doeljaar,L_Versiejaar,P_VJ,L_Versie,F$8,L_Kengetal,"Omzet FY")=0,"n.b.",SUMIFS(L_Waarde,L_Actief,1,L_WBS,$A16,L_Doeljaar,Sel_Doeljaar,L_Versiejaar,P_VJ,L_Versie,F$8,L_Kengetal,"Omzet FY"))),IF(COUNTIFS(L_Actief,1,L_WBS,$A16,L_Doeljaar,Sel_Doeljaar,L_Versiejaar,P_VJ,L_Versie,F$8,L_Kengetal,"Omzet FY")=0,"n.b.",SUMIFS(L_Waarde,L_Actief,1,L_WBS,$A16,L_Doeljaar,Sel_Doeljaar,L_Versiejaar,P_VJ,L_Versie,F$8,L_Kengetal,"Omzet FY"))/P_Factor,IF(COUNTIFS(L_Actief,1,L_WBS,$A16,L_Doeljaar,Sel_Doeljaar,L_Versiejaar,P_VJ,L_Versie,F$8,L_Kengetal,"Omzet FY")=0,"n.b.",SUMIFS(L_Waarde,L_Actief,1,L_WBS,$A16,L_Doeljaar,Sel_Doeljaar,L_Versiejaar,P_VJ,L_Versie,F$8,L_Kengetal,"Omzet FY")))) -> 6444.8 | G16: =IF($A16="","",IF(ISNUMBER(IF(COUNTIFS(L_Actief,1,L_WBS,$A16,L_Doeljaar,Sel_Doeljaar,L_Versiejaar,P_VJ,L_Versie,G$8,L_Kengetal,"Omzet FY")=0,"n.b.",SUMIFS(L_Waarde,L_Actief,1,L_WBS,$A16,L_Doeljaar,Sel_Doeljaar,L_Versiejaar,P_VJ,L_Versie,G$8,L_Kengetal,"Omzet FY"))),IF(COUNTIFS(L_Actief,1,L_WBS,$A16,L_Doeljaar,Sel_Doeljaar,L_Versiejaar,P_VJ,L_Versie,G$8,L_Kengetal,"Omzet FY")=0,"n.b.",SUMIFS(L_Waarde,L_Actief,1,L_WBS,$A16,L_Doeljaar,Sel_Doeljaar,L_Versiejaar,P_VJ,L_Versie,G$8,L_Kengetal,"Omzet FY"))/P_Factor,IF(COUNTIFS(L_Actief,1,L_WBS,$A16,L_Doeljaar,Sel_Doeljaar,L_Versiejaar,P_VJ,L_Versie,G$8,L_Kengetal,"Omzet FY")=0,"n.b.",SUMIFS(L_Waarde,L_Actief,1,L_WBS,$A16,L_Doeljaar,Sel_Doeljaar,L_Versiejaar,P_VJ,L_Versie,G$8,L_Kengetal,"Omzet FY")))) -> 5897.6 | H16: =IF($A16="","",IF(ISNUMBER(IF(COUNTIFS(L_Actief,1,L_WBS,$A16,L_Doeljaar,Sel_Doeljaar,L_Versiejaar,P_VJ,L_Versie,H$8,L_Kengetal,"Omzet FY")=0,"n.b.",SUMIFS(L_Waarde,L_Actief,1,L_WBS,$A16,L_Doeljaar,Sel_Doeljaar,L_Versiejaar,P_VJ,L_Versie,H$8,L_Kengetal,"Omzet FY"))),IF(COUNTIFS(L_Actief,1,L_WBS,$A16,L_Doeljaar,Sel_Doeljaar,L_Versiejaar,P_VJ,L_Versie,H$8,L_Kengetal,"Omzet FY")=0,"n.b.",SUMIFS(L_Waarde,L_Actief,1,L_WBS,$A16,L_Doeljaar,Sel_Doeljaar,L_Versiejaar,P_VJ,L_Versie,H$8,L_Kengetal,"Omzet FY"))/P_Factor,IF(COUNTIFS(L_Actief,1,L_WBS,$A16,L_Doeljaar,Sel_Doeljaar,L_Versiejaar,P_VJ,L_Versie,H$8,L_Kengetal,"Omzet FY")=0,"n.b.",SUMIFS(L_Waarde,L_Actief,1,L_WBS,$A16,L_Doeljaar,Sel_Doeljaar,L_Versiejaar,P_VJ,L_Versie,H$8,L_Kengetal,"Omzet FY")))) -> 6080 | I16: =IF($A16="","",IF(ISNUMBER(IF(COUNTIFS(L_Actief,1,L_WBS,$A16,L_Doeljaar,Sel_Doeljaar,L_Versiejaar,P_VJ,L_Versie,I$8,L_Kengetal,"Omzet FY")=0,"n.b.",SUMIFS(L_Waarde,L_Actief,1,L_WBS,$A16,L_Doeljaar,Sel_Doeljaar,L_Versiejaar,P_VJ,L_Versie,I$8,L_Kengetal,"Omzet FY"))),IF(COUNTIFS(L_Actief,1,L_WBS,$A16,L_Doeljaar,Sel_Doeljaar,L_Versiejaar,P_VJ,L_Versie,I$8,L_Kengetal,"Omzet FY")=0,"n.b.",SUMIFS(L_Waarde,L_Actief,1,L_WBS,$A16,L_Doeljaar,Sel_Doeljaar,L_Versiejaar,P_VJ,L_Versie,I$8,L_Kengetal,"Omzet FY"))/P_Factor,IF(COUNTIFS(L_Actief,1,L_WBS,$A16,L_Doeljaar,Sel_Doeljaar,L_Versiejaar,P_VJ,L_Versie,I$8,L_Kengetal,"Omzet FY")=0,"n.b.",SUMIFS(L_Waarde,L_Actief,1,L_WBS,$A16,L_Doeljaar,Sel_Doeljaar,L_Versiejaar,P_VJ,L_Versie,I$8,L_Kengetal,"Omzet FY")))) -> n.b. | J16: =IF($A16="","",IF(ISNUMBER(IF(Sel_Doeljaar=P_RJ,VERW_Project!$P12,IF(Sel_Doeljaar=P_RJ+1,VERW_Project!$R12,"n.b."))),IF(Sel_Doeljaar=P_RJ,VERW_Project!$P12,IF(Sel_Doeljaar=P_RJ+1,VERW_Project!$R12,"n.b."))/P_Factor,IF(Sel_Doeljaar=P_RJ,VERW_Project!$P12,IF(Sel_Doeljaar=P_RJ+1,VERW_Project!$R12,"n.b.")))) -> 6080 | K16: =IF($A16="","",IF(Sel_Bron="Vastgesteld",INDEX($E16:$I16,MATCH(Sel_Versie,$E$8:$I$8,0)),IF(Sel_Bron="Concept",J16,"n.b."))) -> 6080 | L16: =IF($A16="","",IF(Sel_Doeljaar>P_VJ,"n.v.t.",IF(Sel_Bron="Vastgesteld",IF(ISNUMBER(IF(COUNTIFS(L_Actief,1,L_WBS,$A16,L_Doeljaar,Sel_Doeljaar,L_Versiejaar,P_VJ,L_Versie,Sel_Versie,L_Kengetal,"Omzet actual YTD")=0,"n.b.",SUMIFS(L_Waarde,L_Actief,1,L_WBS,$A16,L_Doeljaar,Sel_Doeljaar,L_Versiejaar,P_VJ,L_Versie,Sel_Versie,L_Kengetal,"Omzet actual YTD"))),IF(COUNTIFS(L_Actief,1,L_WBS,$A16,L_Doeljaar,Sel_Doeljaar,L_Versiejaar,P_VJ,L_Versie,Sel_Versie,L_Kengetal,"Omzet actual YTD")=0,"n.b.",SUMIFS(L_Waarde,L_Actief,1,L_WBS,$A16,L_Doeljaar,Sel_Doeljaar,L_Versiejaar,P_VJ,L_Versie,Sel_Versie,L_Kengetal,"Omzet actual YTD"))/P_Factor,IF(COUNTIFS(L_Actief,1,L_WBS,$A16,L_Doeljaar,Sel_Doeljaar,L_Versiejaar,P_VJ,L_Versie,Sel_Versie,L_Kengetal,"Omzet actual YTD")=0,"n.b.",SUMIFS(L_Waarde,L_Actief,1,L_WBS,$A16,L_Doeljaar,Sel_Doeljaar,L_Versiejaar,P_VJ,L_Versie,Sel_Versie,L_Kengetal,"Omzet actual YTD"))),IF(Sel_Bron="Concept",IF(ISNUMBER(IF(Sel_Doeljaar=P_RJ,VERW_Project!$L12,"n.v.t.")),IF(Sel_Doeljaar=P_RJ,VERW_Project!$L12,"n.v.t.")/P_Factor,IF(Sel_Doeljaar=P_RJ,VERW_Project!$L12,"n.v.t.")),"n.b.")))) -> 3952 | M16: =IF($A16="","",IF(L16="n.v.t.",K16,IF(AND(ISNUMBER(K16),ISNUMBER(L16)),K16-L16,"n.b."))) -> 2128 | N16: =IF($A16="","",IF(Sel_Bron="Vastgesteld",IF(ISNUMBER(IF(COUNTIFS(L_Actief,1,L_WBS,$A16,L_Doeljaar,Sel_Doeljaar,L_Versiejaar,P_VJ,L_Versie,Sel_Versie,L_Kengetal,"BOR FY")=0,"n.b.",SUMIFS(L_Waarde,L_Actief,1,L_WBS,$A16,L_Doeljaar,Sel_Doeljaar,L_Versiejaar,P_VJ,L_Versie,Sel_Versie,L_Kengetal,"BOR FY"))),IF(COUNTIFS(L_Actief,1,L_WBS,$A16,L_Doeljaar,Sel_Doeljaar,L_Versiejaar,P_VJ,L_Versie,Sel_Versie,L_Kengetal,"BOR FY")=0,"n.b.",SUMIFS(L_Waarde,L_Actief,1,L_WBS,$A16,L_Doeljaar,Sel_Doeljaar,L_Versiejaar,P_VJ,L_Versie,Sel_Versie,L_Kengetal,"BOR FY"))/P_Factor,IF(COUNTIFS(L_Actief,1,L_WBS,$A16,L_Doeljaar,Sel_Doeljaar,L_Versiejaar,P_VJ,L_Versie,Sel_Versie,L_Kengetal,"BOR FY")=0,"n.b.",SUMIFS(L_Waarde,L_Actief,1,L_WBS,$A16,L_Doeljaar,Sel_Doeljaar,L_Versiejaar,P_VJ,L_Versie,Sel_Versie,L_Kengetal,"BOR FY"))),IF(Sel_Bron="Concept",IF(ISNUMBER(IF(Sel_Doeljaar=P_RJ,VERW_Project!$Q12,IF(Sel_Doeljaar=P_RJ+1,VERW_Project!$S12,"n.b."))),IF(Sel_Doeljaar=P_RJ,VERW_Project!$Q12,IF(Sel_Doeljaar=P_RJ+1,VERW_Project!$S12,"n.b."))/P_Factor,IF(Sel_Doeljaar=P_RJ,VERW_Project!$Q12,IF(Sel_Doeljaar=P_RJ+1,VERW_Project!$S12,"n.b."))),"n.b."))) -> 608 | O16: =IF($A16="","",IF(AND(ISNUMBER(N16),ISNUMBER(K16)),IF(K16<>0,N16/K16,"n.b."),"n.b.")) -> 0.1 | P16: =IF($A16="","",IF(AND(ISNUMBER(K16),ISNUMBER(E16)),K16-E16,"n.b.")) -> -608 | Q16: =IF($A16="","",IF(AND(ISNUMBER(K16),ISNUMBER(W16)),K16-W16,"n.b.")) -> 182.4 | R16: =IF($A16="","",IF(ISNUMBER(N16),IF(N16<0,"Verlies",""),"")) | S16: =IF($A16="","",IFERROR(INDEX(T_Txt,MATCH($A16&"|"&Sel_Doeljaar&"|"&P_VJ&"|"&Sel_Versie,T_Key,0)),"")) | U16: =IF(AND(AND($A16<>"",OR(Sel_Type="Alle",$C16=Sel_Type),OR(Sel_Project="Alle",$B16=Sel_Project)),ISNUMBER(K16)),K16+ROW()/1000000000,"") -> 6080 | V16: =IF(AND(AND($A16<>"",OR(Sel_Type="Alle",$C16=Sel_Type),OR(Sel_Project="Alle",$B16=Sel_Project)),ISNUMBER(Q16)),ABS(Q16)+ROW()/1000000000,"") -> 182.4 | W16: =IF(OR($A16="",Sel_Prev=""),"n.b.",IF(ISNUMBER(IF(COUNTIFS(L_Actief,1,L_WBS,$A16,L_Doeljaar,Sel_Doeljaar,L_Versiejaar,P_VJ,L_Versie,Sel_Prev,L_Kengetal,"Omzet FY")=0,"n.b.",SUMIFS(L_Waarde,L_Actief,1,L_WBS,$A16,L_Doeljaar,Sel_Doeljaar,L_Versiejaar,P_VJ,L_Versie,Sel_Prev,L_Kengetal,"Omzet FY"))),IF(COUNTIFS(L_Actief,1,L_WBS,$A16,L_Doeljaar,Sel_Doeljaar,L_Versiejaar,P_VJ,L_Versie,Sel_Prev,L_Kengetal,"Omzet FY")=0,"n.b.",SUMIFS(L_Waarde,L_Actief,1,L_WBS,$A16,L_Doeljaar,Sel_Doeljaar,L_Versiejaar,P_VJ,L_Versie,Sel_Prev,L_Kengetal,"Omzet FY"))/P_Factor,IF(COUNTIFS(L_Actief,1,L_WBS,$A16,L_Doeljaar,Sel_Doeljaar,L_Versiejaar,P_VJ,L_Versie,Sel_Prev,L_Kengetal,"Omzet FY")=0,"n.b.",SUMIFS(L_Waarde,L_Actief,1,L_WBS,$A16,L_Doeljaar,Sel_Doeljaar,L_Versiejaar,P_VJ,L_Versie,Sel_Prev,L_Kengetal,"Omzet FY")))) -> 5897.6
A17: =IF(VERW_Project!$A13="","",VERW_Project!$A13) -> G.900008.8.9090 | B17: =IF($A17="","",VERW_Project!$C13) -> Lindehaven, De Brink | C17: =IF($A17="","",VERW_Project!$D13) -> Opstal | D17: =IF($A17="","",VERW_Project!$I13) -> J | E17: =IF($A17="","",IF(ISNUMBER(IF(COUNTIFS(L_Actief,1,L_WBS,$A17,L_Doeljaar,Sel_Doeljaar,L_Versiejaar,P_VJ,L_Versie,E$8,L_Kengetal,"Omzet FY")=0,"n.b.",SUMIFS(L_Waarde,L_Actief,1,L_WBS,$A17,L_Doeljaar,Sel_Doeljaar,L_Versiejaar,P_VJ,L_Versie,E$8,L_Kengetal,"Omzet FY"))),IF(COUNTIFS(L_Actief,1,L_WBS,$A17,L_Doeljaar,Sel_Doeljaar,L_Versiejaar,P_VJ,L_Versie,E$8,L_Kengetal,"Omzet FY")=0,"n.b.",SUMIFS(L_Waarde,L_Actief,1,L_WBS,$A17,L_Doeljaar,Sel_Doeljaar,L_Versiejaar,P_VJ,L_Versie,E$8,L_Kengetal,"Omzet FY"))/P_Factor,IF(COUNTIFS(L_Actief,1,L_WBS,$A17,L_Doeljaar,Sel_Doeljaar,L_Versiejaar,P_VJ,L_Versie,E$8,L_Kengetal,"Omzet FY")=0,"n.b.",SUMIFS(L_Waarde,L_Actief,1,L_WBS,$A17,L_Doeljaar,Sel_Doeljaar,L_Versiejaar,P_VJ,L_Versie,E$8,L_Kengetal,"Omzet FY")))) -> 1757.7 | F17: =IF($A17="","",IF(ISNUMBER(IF(COUNTIFS(L_Actief,1,L_WBS,$A17,L_Doeljaar,Sel_Doeljaar,L_Versiejaar,P_VJ,L_Versie,F$8,L_Kengetal,"Omzet FY")=0,"n.b.",SUMIFS(L_Waarde,L_Actief,1,L_WBS,$A17,L_Doeljaar,Sel_Doeljaar,L_Versiejaar,P_VJ,L_Versie,F$8,L_Kengetal,"Omzet FY"))),IF(COUNTIFS(L_Actief,1,L_WBS,$A17,L_Doeljaar,Sel_Doeljaar,L_Versiejaar,P_VJ,L_Versie,F$8,L_Kengetal,"Omzet FY")=0,"n.b.",SUMIFS(L_Waarde,L_Actief,1,L_WBS,$A17,L_Doeljaar,Sel_Doeljaar,L_Versiejaar,P_VJ,L_Versie,F$8,L_Kengetal,"Omzet FY"))/P_Factor,IF(COUNTIFS(L_Actief,1,L_WBS,$A17,L_Doeljaar,Sel_Doeljaar,L_Versiejaar,P_VJ,L_Versie,F$8,L_Kengetal,"Omzet FY")=0,"n.b.",SUMIFS(L_Waarde,L_Actief,1,L_WBS,$A17,L_Doeljaar,Sel_Doeljaar,L_Versiejaar,P_VJ,L_Versie,F$8,L_Kengetal,"Omzet FY")))) -> 1835.82 | G17: =IF($A17="","",IF(ISNUMBER(IF(COUNTIFS(L_Actief,1,L_WBS,$A17,L_Doeljaar,Sel_Doeljaar,L_Versiejaar,P_VJ,L_Versie,G$8,L_Kengetal,"Omzet FY")=0,"n.b.",SUMIFS(L_Waarde,L_Actief,1,L_WBS,$A17,L_Doeljaar,Sel_Doeljaar,L_Versiejaar,P_VJ,L_Versie,G$8,L_Kengetal,"Omzet FY"))),IF(COUNTIFS(L_Actief,1,L_WBS,$A17,L_Doeljaar,Sel_Doeljaar,L_Versiejaar,P_VJ,L_Versie,G$8,L_Kengetal,"Omzet FY")=0,"n.b.",SUMIFS(L_Waarde,L_Actief,1,L_WBS,$A17,L_Doeljaar,Sel_Doeljaar,L_Versiejaar,P_VJ,L_Versie,G$8,L_Kengetal,"Omzet FY"))/P_Factor,IF(COUNTIFS(L_Actief,1,L_WBS,$A17,L_Doeljaar,Sel_Doeljaar,L_Versiejaar,P_VJ,L_Versie,G$8,L_Kengetal,"Omzet FY")=0,"n.b.",SUMIFS(L_Waarde,L_Actief,1,L_WBS,$A17,L_Doeljaar,Sel_Doeljaar,L_Versiejaar,P_VJ,L_Versie,G$8,L_Kengetal,"Omzet FY")))) -> 2011.59 | H17: =IF($A17="","",IF(ISNUMBER(IF(COUNTIFS(L_Actief,1,L_WBS,$A17,L_Doeljaar,Sel_Doeljaar,L_Versiejaar,P_VJ,L_Versie,H$8,L_Kengetal,"Omzet FY")=0,"n.b.",SUMIFS(L_Waarde,L_Actief,1,L_WBS,$A17,L_Doeljaar,Sel_Doeljaar,L_Versiejaar,P_VJ,L_Versie,H$8,L_Kengetal,"Omzet FY"))),IF(COUNTIFS(L_Actief,1,L_WBS,$A17,L_Doeljaar,Sel_Doeljaar,L_Versiejaar,P_VJ,L_Versie,H$8,L_Kengetal,"Omzet FY")=0,"n.b.",SUMIFS(L_Waarde,L_Actief,1,L_WBS,$A17,L_Doeljaar,Sel_Doeljaar,L_Versiejaar,P_VJ,L_Versie,H$8,L_Kengetal,"Omzet FY"))/P_Factor,IF(COUNTIFS(L_Actief,1,L_WBS,$A17,L_Doeljaar,Sel_Doeljaar,L_Versiejaar,P_VJ,L_Versie,H$8,L_Kengetal,"Omzet FY")=0,"n.b.",SUMIFS(L_Waarde,L_Actief,1,L_WBS,$A17,L_Doeljaar,Sel_Doeljaar,L_Versiejaar,P_VJ,L_Versie,H$8,L_Kengetal,"Omzet FY")))) -> 1953 | I17: =IF($A17="","",IF(ISNUMBER(IF(COUNTIFS(L_Actief,1,L_WBS,$A17,L_Doeljaar,Sel_Doeljaar,L_Versiejaar,P_VJ,L_Versie,I$8,L_Kengetal,"Omzet FY")=0,"n.b.",SUMIFS(L_Waarde,L_Actief,1,L_WBS,$A17,L_Doeljaar,Sel_Doeljaar,L_Versiejaar,P_VJ,L_Versie,I$8,L_Kengetal,"Omzet FY"))),IF(COUNTIFS(L_Actief,1,L_WBS,$A17,L_Doeljaar,Sel_Doeljaar,L_Versiejaar,P_VJ,L_Versie,I$8,L_Kengetal,"Omzet FY")=0,"n.b.",SUMIFS(L_Waarde,L_Actief,1,L_WBS,$A17,L_Doeljaar,Sel_Doeljaar,L_Versiejaar,P_VJ,L_Versie,I$8,L_Kengetal,"Omzet FY"))/P_Factor,IF(COUNTIFS(L_Actief,1,L_WBS,$A17,L_Doeljaar,Sel_Doeljaar,L_Versiejaar,P_VJ,L_Versie,I$8,L_Kengetal,"Omzet FY")=0,"n.b.",SUMIFS(L_Waarde,L_Actief,1,L_WBS,$A17,L_Doeljaar,Sel_Doeljaar,L_Versiejaar,P_VJ,L_Versie,I$8,L_Kengetal,"Omzet FY")))) -> n.b. | J17: =IF($A17="","",IF(ISNUMBER(IF(Sel_Doeljaar=P_RJ,VERW_Project!$P13,IF(Sel_Doeljaar=P_RJ+1,VERW_Project!$R13,"n.b."))),IF(Sel_Doeljaar=P_RJ,VERW_Project!$P13,IF(Sel_Doeljaar=P_RJ+1,VERW_Project!$R13,"n.b."))/P_Factor,IF(Sel_Doeljaar=P_RJ,VERW_Project!$P13,IF(Sel_Doeljaar=P_RJ+1,VERW_Project!$R13,"n.b.")))) -> 1953 | K17: =IF($A17="","",IF(Sel_Bron="Vastgesteld",INDEX($E17:$I17,MATCH(Sel_Versie,$E$8:$I$8,0)),IF(Sel_Bron="Concept",J17,"n.b."))) -> 1953 | L17: =IF($A17="","",IF(Sel_Doeljaar>P_VJ,"n.v.t.",IF(Sel_Bron="Vastgesteld",IF(ISNUMBER(IF(COUNTIFS(L_Actief,1,L_WBS,$A17,L_Doeljaar,Sel_Doeljaar,L_Versiejaar,P_VJ,L_Versie,Sel_Versie,L_Kengetal,"Omzet actual YTD")=0,"n.b.",SUMIFS(L_Waarde,L_Actief,1,L_WBS,$A17,L_Doeljaar,Sel_Doeljaar,L_Versiejaar,P_VJ,L_Versie,Sel_Versie,L_Kengetal,"Omzet actual YTD"))),IF(COUNTIFS(L_Actief,1,L_WBS,$A17,L_Doeljaar,Sel_Doeljaar,L_Versiejaar,P_VJ,L_Versie,Sel_Versie,L_Kengetal,"Omzet actual YTD")=0,"n.b.",SUMIFS(L_Waarde,L_Actief,1,L_WBS,$A17,L_Doeljaar,Sel_Doeljaar,L_Versiejaar,P_VJ,L_Versie,Sel_Versie,L_Kengetal,"Omzet actual YTD"))/P_Factor,IF(COUNTIFS(L_Actief,1,L_WBS,$A17,L_Doeljaar,Sel_Doeljaar,L_Versiejaar,P_VJ,L_Versie,Sel_Versie,L_Kengetal,"Omzet actual YTD")=0,"n.b.",SUMIFS(L_Waarde,L_Actief,1,L_WBS,$A17,L_Doeljaar,Sel_Doeljaar,L_Versiejaar,P_VJ,L_Versie,Sel_Versie,L_Kengetal,"Omzet actual YTD"))),IF(Sel_Bron="Concept",IF(ISNUMBER(IF(Sel_Doeljaar=P_RJ,VERW_Project!$L13,"n.v.t.")),IF(Sel_Doeljaar=P_RJ,VERW_Project!$L13,"n.v.t.")/P_Factor,IF(Sel_Doeljaar=P_RJ,VERW_Project!$L13,"n.v.t.")),"n.b.")))) -> 1269.45 | M17: =IF($A17="","",IF(L17="n.v.t.",K17,IF(AND(ISNUMBER(K17),ISNUMBER(L17)),K17-L17,"n.b."))) -> 683.55 | N17: =IF($A17="","",IF(Sel_Bron="Vastgesteld",IF(ISNUMBER(IF(COUNTIFS(L_Actief,1,L_WBS,$A17,L_Doeljaar,Sel_Doeljaar,L_Versiejaar,P_VJ,L_Versie,Sel_Versie,L_Kengetal,"BOR FY")=0,"n.b.",SUMIFS(L_Waarde,L_Actief,1,L_WBS,$A17,L_Doeljaar,Sel_Doeljaar,L_Versiejaar,P_VJ,L_Versie,Sel_Versie,L_Kengetal,"BOR FY"))),IF(COUNTIFS(L_Actief,1,L_WBS,$A17,L_Doeljaar,Sel_Doeljaar,L_Versiejaar,P_VJ,L_Versie,Sel_Versie,L_Kengetal,"BOR FY")=0,"n.b.",SUMIFS(L_Waarde,L_Actief,1,L_WBS,$A17,L_Doeljaar,Sel_Doeljaar,L_Versiejaar,P_VJ,L_Versie,Sel_Versie,L_Kengetal,"BOR FY"))/P_Factor,IF(COUNTIFS(L_Actief,1,L_WBS,$A17,L_Doeljaar,Sel_Doeljaar,L_Versiejaar,P_VJ,L_Versie,Sel_Versie,L_Kengetal,"BOR FY")=0,"n.b.",SUMIFS(L_Waarde,L_Actief,1,L_WBS,$A17,L_Doeljaar,Sel_Doeljaar,L_Versiejaar,P_VJ,L_Versie,Sel_Versie,L_Kengetal,"BOR FY"))),IF(Sel_Bron="Concept",IF(ISNUMBER(IF(Sel_Doeljaar=P_RJ,VERW_Project!$Q13,IF(Sel_Doeljaar=P_RJ+1,VERW_Project!$S13,"n.b."))),IF(Sel_Doeljaar=P_RJ,VERW_Project!$Q13,IF(Sel_Doeljaar=P_RJ+1,VERW_Project!$S13,"n.b."))/P_Factor,IF(Sel_Doeljaar=P_RJ,VERW_Project!$Q13,IF(Sel_Doeljaar=P_RJ+1,VERW_Project!$S13,"n.b."))),"n.b."))) -> -58.59 | O17: =IF($A17="","",IF(AND(ISNUMBER(N17),ISNUMBER(K17)),IF(K17<>0,N17/K17,"n.b."),"n.b.")) -> -0.03 | P17: =IF($A17="","",IF(AND(ISNUMBER(K17),ISNUMBER(E17)),K17-E17,"n.b.")) -> 195.3 | Q17: =IF($A17="","",IF(AND(ISNUMBER(K17),ISNUMBER(W17)),K17-W17,"n.b.")) -> -58.59 | R17: =IF($A17="","",IF(ISNUMBER(N17),IF(N17<0,"Verlies",""),"")) -> Verlies | S17: =IF($A17="","",IFERROR(INDEX(T_Txt,MATCH($A17&"|"&Sel_Doeljaar&"|"&P_VJ&"|"&Sel_Versie,T_Key,0)),"")) -> [VOORBEELD – fictief] Verliesproject: voorbeeldtekst om het formaat te tonen. | U17: =IF(AND(AND($A17<>"",OR(Sel_Type="Alle",$C17=Sel_Type),OR(Sel_Project="Alle",$B17=Sel_Project)),ISNUMBER(K17)),K17+ROW()/1000000000,"") -> 1953 | V17: =IF(AND(AND($A17<>"",OR(Sel_Type="Alle",$C17=Sel_Type),OR(Sel_Project="Alle",$B17=Sel_Project)),ISNUMBER(Q17)),ABS(Q17)+ROW()/1000000000,"") -> 58.59 | W17: =IF(OR($A17="",Sel_Prev=""),"n.b.",IF(ISNUMBER(IF(COUNTIFS(L_Actief,1,L_WBS,$A17,L_Doeljaar,Sel_Doeljaar,L_Versiejaar,P_VJ,L_Versie,Sel_Prev,L_Kengetal,"Omzet FY")=0,"n.b.",SUMIFS(L_Waarde,L_Actief,1,L_WBS,$A17,L_Doeljaar,Sel_Doeljaar,L_Versiejaar,P_VJ,L_Versie,Sel_Prev,L_Kengetal,"Omzet FY"))),IF(COUNTIFS(L_Actief,1,L_WBS,$A17,L_Doeljaar,Sel_Doeljaar,L_Versiejaar,P_VJ,L_Versie,Sel_Prev,L_Kengetal,"Omzet FY")=0,"n.b.",SUMIFS(L_Waarde,L_Actief,1,L_WBS,$A17,L_Doeljaar,Sel_Doeljaar,L_Versiejaar,P_VJ,L_Versie,Sel_Prev,L_Kengetal,"Omzet FY"))/P_Factor,IF(COUNTIFS(L_Actief,1,L_WBS,$A17,L_Doeljaar,Sel_Doeljaar,L_Versiejaar,P_VJ,L_Versie,Sel_Prev,L_Kengetal,"Omzet FY")=0,"n.b.",SUMIFS(L_Waarde,L_Actief,1,L_WBS,$A17,L_Doeljaar,Sel_Doeljaar,L_Versiejaar,P_VJ,L_Versie,Sel_Prev,L_Kengetal,"Omzet FY")))) -> 2011.59
A18: =IF(VERW_Project!$A14="","",VERW_Project!$A14) -> G.900009.8.9090 | B18: =IF($A18="","",VERW_Project!$C14) -> Duinwaard, Duinrand | C18: =IF($A18="","",VERW_Project!$D14) -> Opstal | D18: =IF($A18="","",VERW_Project!$I14) -> J | E18: =IF($A18="","",IF(ISNUMBER(IF(COUNTIFS(L_Actief,1,L_WBS,$A18,L_Doeljaar,Sel_Doeljaar,L_Versiejaar,P_VJ,L_Versie,E$8,L_Kengetal,"Omzet FY")=0,"n.b.",SUMIFS(L_Waarde,L_Actief,1,L_WBS,$A18,L_Doeljaar,Sel_Doeljaar,L_Versiejaar,P_VJ,L_Versie,E$8,L_Kengetal,"Omzet FY"))),IF(COUNTIFS(L_Actief,1,L_WBS,$A18,L_Doeljaar,Sel_Doeljaar,L_Versiejaar,P_VJ,L_Versie,E$8,L_Kengetal,"Omzet FY")=0,"n.b.",SUMIFS(L_Waarde,L_Actief,1,L_WBS,$A18,L_Doeljaar,Sel_Doeljaar,L_Versiejaar,P_VJ,L_Versie,E$8,L_Kengetal,"Omzet FY"))/P_Factor,IF(COUNTIFS(L_Actief,1,L_WBS,$A18,L_Doeljaar,Sel_Doeljaar,L_Versiejaar,P_VJ,L_Versie,E$8,L_Kengetal,"Omzet FY")=0,"n.b.",SUMIFS(L_Waarde,L_Actief,1,L_WBS,$A18,L_Doeljaar,Sel_Doeljaar,L_Versiejaar,P_VJ,L_Versie,E$8,L_Kengetal,"Omzet FY")))) -> 18295.2 | F18: =IF($A18="","",IF(ISNUMBER(IF(COUNTIFS(L_Actief,1,L_WBS,$A18,L_Doeljaar,Sel_Doeljaar,L_Versiejaar,P_VJ,L_Versie,F$8,L_Kengetal,"Omzet FY")=0,"n.b.",SUMIFS(L_Waarde,L_Actief,1,L_WBS,$A18,L_Doeljaar,Sel_Doeljaar,L_Versiejaar,P_VJ,L_Versie,F$8,L_Kengetal,"Omzet FY"))),IF(COUNTIFS(L_Actief,1,L_WBS,$A18,L_Doeljaar,Sel_Doeljaar,L_Versiejaar,P_VJ,L_Versie,F$8,L_Kengetal,"Omzet FY")=0,"n.b.",SUMIFS(L_Waarde,L_Actief,1,L_WBS,$A18,L_Doeljaar,Sel_Doeljaar,L_Versiejaar,P_VJ,L_Versie,F$8,L_Kengetal,"Omzet FY"))/P_Factor,IF(COUNTIFS(L_Actief,1,L_WBS,$A18,L_Doeljaar,Sel_Doeljaar,L_Versiejaar,P_VJ,L_Versie,F$8,L_Kengetal,"Omzet FY")=0,"n.b.",SUMIFS(L_Waarde,L_Actief,1,L_WBS,$A18,L_Doeljaar,Sel_Doeljaar,L_Versiejaar,P_VJ,L_Versie,F$8,L_Kengetal,"Omzet FY")))) -> 17629.92 | G18: =IF($A18="","",IF(ISNUMBER(IF(COUNTIFS(L_Actief,1,L_WBS,$A18,L_Doeljaar,Sel_Doeljaar,L_Versiejaar,P_VJ,L_Versie,G$8,L_Kengetal,"Omzet FY")=0,"n.b.",SUMIFS(L_Waarde,L_Actief,1,L_WBS,$A18,L_Doeljaar,Sel_Doeljaar,L_Versiejaar,P_VJ,L_Versie,G$8,L_Kengetal,"Omzet FY"))),IF(COUNTIFS(L_Actief,1,L_WBS,$A18,L_Doeljaar,Sel_Doeljaar,L_Versiejaar,P_VJ,L_Versie,G$8,L_Kengetal,"Omzet FY")=0,"n.b.",SUMIFS(L_Waarde,L_Actief,1,L_WBS,$A18,L_Doeljaar,Sel_Doeljaar,L_Versiejaar,P_VJ,L_Versie,G$8,L_Kengetal,"Omzet FY"))/P_Factor,IF(COUNTIFS(L_Actief,1,L_WBS,$A18,L_Doeljaar,Sel_Doeljaar,L_Versiejaar,P_VJ,L_Versie,G$8,L_Kengetal,"Omzet FY")=0,"n.b.",SUMIFS(L_Waarde,L_Actief,1,L_WBS,$A18,L_Doeljaar,Sel_Doeljaar,L_Versiejaar,P_VJ,L_Versie,G$8,L_Kengetal,"Omzet FY")))) -> 16133.04 | H18: =IF($A18="","",IF(ISNUMBER(IF(COUNTIFS(L_Actief,1,L_WBS,$A18,L_Doeljaar,Sel_Doeljaar,L_Versiejaar,P_VJ,L_Versie,H$8,L_Kengetal,"Omzet FY")=0,"n.b.",SUMIFS(L_Waarde,L_Actief,1,L_WBS,$A18,L_Doeljaar,Sel_Doeljaar,L_Versiejaar,P_VJ,L_Versie,H$8,L_Kengetal,"Omzet FY"))),IF(COUNTIFS(L_Actief,1,L_WBS,$A18,L_Doeljaar,Sel_Doeljaar,L_Versiejaar,P_VJ,L_Versie,H$8,L_Kengetal,"Omzet FY")=0,"n.b.",SUMIFS(L_Waarde,L_Actief,1,L_WBS,$A18,L_Doeljaar,Sel_Doeljaar,L_Versiejaar,P_VJ,L_Versie,H$8,L_Kengetal,"Omzet FY"))/P_Factor,IF(COUNTIFS(L_Actief,1,L_WBS,$A18,L_Doeljaar,Sel_Doeljaar,L_Versiejaar,P_VJ,L_Versie,H$8,L_Kengetal,"Omzet FY")=0,"n.b.",SUMIFS(L_Waarde,L_Actief,1,L_WBS,$A18,L_Doeljaar,Sel_Doeljaar,L_Versiejaar,P_VJ,L_Versie,H$8,L_Kengetal,"Omzet FY")))) -> 16632 | I18: =IF($A18="","",IF(ISNUMBER(IF(COUNTIFS(L_Actief,1,L_WBS,$A18,L_Doeljaar,Sel_Doeljaar,L_Versiejaar,P_VJ,L_Versie,I$8,L_Kengetal,"Omzet FY")=0,"n.b.",SUMIFS(L_Waarde,L_Actief,1,L_WBS,$A18,L_Doeljaar,Sel_Doeljaar,L_Versiejaar,P_VJ,L_Versie,I$8,L_Kengetal,"Omzet FY"))),IF(COUNTIFS(L_Actief,1,L_WBS,$A18,L_Doeljaar,Sel_Doeljaar,L_Versiejaar,P_VJ,L_Versie,I$8,L_Kengetal,"Omzet FY")=0,"n.b.",SUMIFS(L_Waarde,L_Actief,1,L_WBS,$A18,L_Doeljaar,Sel_Doeljaar,L_Versiejaar,P_VJ,L_Versie,I$8,L_Kengetal,"Omzet FY"))/P_Factor,IF(COUNTIFS(L_Actief,1,L_WBS,$A18,L_Doeljaar,Sel_Doeljaar,L_Versiejaar,P_VJ,L_Versie,I$8,L_Kengetal,"Omzet FY")=0,"n.b.",SUMIFS(L_Waarde,L_Actief,1,L_WBS,$A18,L_Doeljaar,Sel_Doeljaar,L_Versiejaar,P_VJ,L_Versie,I$8,L_Kengetal,"Omzet FY")))) -> n.b. | J18: =IF($A18="","",IF(ISNUMBER(IF(Sel_Doeljaar=P_RJ,VERW_Project!$P14,IF(Sel_Doeljaar=P_RJ+1,VERW_Project!$R14,"n.b."))),IF(Sel_Doeljaar=P_RJ,VERW_Project!$P14,IF(Sel_Doeljaar=P_RJ+1,VERW_Project!$R14,"n.b."))/P_Factor,IF(Sel_Doeljaar=P_RJ,VERW_Project!$P14,IF(Sel_Doeljaar=P_RJ+1,VERW_Project!$R14,"n.b.")))) -> 16632 | K18: =IF($A18="","",IF(Sel_Bron="Vastgesteld",INDEX($E18:$I18,MATCH(Sel_Versie,$E$8:$I$8,0)),IF(Sel_Bron="Concept",J18,"n.b."))) -> 16632 | L18: =IF($A18="","",IF(Sel_Doeljaar>P_VJ,"n.v.t.",IF(Sel_Bron="Vastgesteld",IF(ISNUMBER(IF(COUNTIFS(L_Actief,1,L_WBS,$A18,L_Doeljaar,Sel_Doeljaar,L_Versiejaar,P_VJ,L_Versie,Sel_Versie,L_Kengetal,"Omzet actual YTD")=0,"n.b.",SUMIFS(L_Waarde,L_Actief,1,L_WBS,$A18,L_Doeljaar,Sel_Doeljaar,L_Versiejaar,P_VJ,L_Versie,Sel_Versie,L_Kengetal,"Omzet actual YTD"))),IF(COUNTIFS(L_Actief,1,L_WBS,$A18,L_Doeljaar,Sel_Doeljaar,L_Versiejaar,P_VJ,L_Versie,Sel_Versie,L_Kengetal,"Omzet actual YTD")=0,"n.b.",SUMIFS(L_Waarde,L_Actief,1,L_WBS,$A18,L_Doeljaar,Sel_Doeljaar,L_Versiejaar,P_VJ,L_Versie,Sel_Versie,L_Kengetal,"Omzet actual YTD"))/P_Factor,IF(COUNTIFS(L_Actief,1,L_WBS,$A18,L_Doeljaar,Sel_Doeljaar,L_Versiejaar,P_VJ,L_Versie,Sel_Versie,L_Kengetal,"Omzet actual YTD")=0,"n.b.",SUMIFS(L_Waarde,L_Actief,1,L_WBS,$A18,L_Doeljaar,Sel_Doeljaar,L_Versiejaar,P_VJ,L_Versie,Sel_Versie,L_Kengetal,"Omzet actual YTD"))),IF(Sel_Bron="Concept",IF(ISNUMBER(IF(Sel_Doeljaar=P_RJ,VERW_Project!$L14,"n.v.t.")),IF(Sel_Doeljaar=P_RJ,VERW_Project!$L14,"n.v.t.")/P_Factor,IF(Sel_Doeljaar=P_RJ,VERW_Project!$L14,"n.v.t.")),"n.b.")))) -> 10810.8 | M18: =IF($A18="","",IF(L18="n.v.t.",K18,IF(AND(ISNUMBER(K18),ISNUMBER(L18)),K18-L18,"n.b."))) -> 5821.2 | N18: =IF($A18="","",IF(Sel_Bron="Vastgesteld",IF(ISNUMBER(IF(COUNTIFS(L_Actief,1,L_WBS,$A18,L_Doeljaar,Sel_Doeljaar,L_Versiejaar,P_VJ,L_Versie,Sel_Versie,L_Kengetal,"BOR FY")=0,"n.b.",SUMIFS(L_Waarde,L_Actief,1,L_WBS,$A18,L_Doeljaar,Sel_Doeljaar,L_Versiejaar,P_VJ,L_Versie,Sel_Versie,L_Kengetal,"BOR FY"))),IF(COUNTIFS(L_Actief,1,L_WBS,$A18,L_Doeljaar,Sel_Doeljaar,L_Versiejaar,P_VJ,L_Versie,Sel_Versie,L_Kengetal,"BOR FY")=0,"n.b.",SUMIFS(L_Waarde,L_Actief,1,L_WBS,$A18,L_Doeljaar,Sel_Doeljaar,L_Versiejaar,P_VJ,L_Versie,Sel_Versie,L_Kengetal,"BOR FY"))/P_Factor,IF(COUNTIFS(L_Actief,1,L_WBS,$A18,L_Doeljaar,Sel_Doeljaar,L_Versiejaar,P_VJ,L_Versie,Sel_Versie,L_Kengetal,"BOR FY")=0,"n.b.",SUMIFS(L_Waarde,L_Actief,1,L_WBS,$A18,L_Doeljaar,Sel_Doeljaar,L_Versiejaar,P_VJ,L_Versie,Sel_Versie,L_Kengetal,"BOR FY"))),IF(Sel_Bron="Concept",IF(ISNUMBER(IF(Sel_Doeljaar=P_RJ,VERW_Project!$Q14,IF(Sel_Doeljaar=P_RJ+1,VERW_Project!$S14,"n.b."))),IF(Sel_Doeljaar=P_RJ,VERW_Project!$Q14,IF(Sel_Doeljaar=P_RJ+1,VERW_Project!$S14,"n.b."))/P_Factor,IF(Sel_Doeljaar=P_RJ,VERW_Project!$Q14,IF(Sel_Doeljaar=P_RJ+1,VERW_Project!$S14,"n.b."))),"n.b."))) -> 1330.56 | O18: =IF($A18="","",IF(AND(ISNUMBER(N18),ISNUMBER(K18)),IF(K18<>0,N18/K18,"n.b."),"n.b.")) -> 0.08 | P18: =IF($A18="","",IF(AND(ISNUMBER(K18),ISNUMBER(E18)),K18-E18,"n.b.")) -> -1663.2 | Q18: =IF($A18="","",IF(AND(ISNUMBER(K18),ISNUMBER(W18)),K18-W18,"n.b.")) -> 498.96 | R18: =IF($A18="","",IF(ISNUMBER(N18),IF(N18<0,"Verlies",""),"")) | S18: =IF($A18="","",IFERROR(INDEX(T_Txt,MATCH($A18&"|"&Sel_Doeljaar&"|"&P_VJ&"|"&Sel_Versie,T_Key,0)),"")) | U18: =IF(AND(AND($A18<>"",OR(Sel_Type="Alle",$C18=Sel_Type),OR(Sel_Project="Alle",$B18=Sel_Project)),ISNUMBER(K18)),K18+ROW()/1000000000,"") -> 16632 | V18: =IF(AND(AND($A18<>"",OR(Sel_Type="Alle",$C18=Sel_Type),OR(Sel_Project="Alle",$B18=Sel_Project)),ISNUMBER(Q18)),ABS(Q18)+ROW()/1000000000,"") -> 498.96 | W18: =IF(OR($A18="",Sel_Prev=""),"n.b.",IF(ISNUMBER(IF(COUNTIFS(L_Actief,1,L_WBS,$A18,L_Doeljaar,Sel_Doeljaar,L_Versiejaar,P_VJ,L_Versie,Sel_Prev,L_Kengetal,"Omzet FY")=0,"n.b.",SUMIFS(L_Waarde,L_Actief,1,L_WBS,$A18,L_Doeljaar,Sel_Doeljaar,L_Versiejaar,P_VJ,L_Versie,Sel_Prev,L_Kengetal,"Omzet FY"))),IF(COUNTIFS(L_Actief,1,L_WBS,$A18,L_Doeljaar,Sel_Doeljaar,L_Versiejaar,P_VJ,L_Versie,Sel_Prev,L_Kengetal,"Omzet FY")=0,"n.b.",SUMIFS(L_Waarde,L_Actief,1,L_WBS,$A18,L_Doeljaar,Sel_Doeljaar,L_Versiejaar,P_VJ,L_Versie,Sel_Prev,L_Kengetal,"Omzet FY"))/P_Factor,IF(COUNTIFS(L_Actief,1,L_WBS,$A18,L_Doeljaar,Sel_Doeljaar,L_Versiejaar,P_VJ,L_Versie,Sel_Prev,L_Kengetal,"Omzet FY")=0,"n.b.",SUMIFS(L_Waarde,L_Actief,1,L_WBS,$A18,L_Doeljaar,Sel_Doeljaar,L_Versiejaar,P_VJ,L_Versie,Sel_Prev,L_Kengetal,"Omzet FY")))) -> 16133.04
A19: =IF(VERW_Project!$A15="","",VERW_Project!$A15) -> G.900010.8.9090 | B19: =IF($A19="","",VERW_Project!$C15) -> Veldendam, Groene Singel | C19: =IF($A19="","",VERW_Project!$D15) -> Opstal | D19: =IF($A19="","",VERW_Project!$I15) -> J | E19: =IF($A19="","",IF(ISNUMBER(IF(COUNTIFS(L_Actief,1,L_WBS,$A19,L_Doeljaar,Sel_Doeljaar,L_Versiejaar,P_VJ,L_Versie,E$8,L_Kengetal,"Omzet FY")=0,"n.b.",SUMIFS(L_Waarde,L_Actief,1,L_WBS,$A19,L_Doeljaar,Sel_Doeljaar,L_Versiejaar,P_VJ,L_Versie,E$8,L_Kengetal,"Omzet FY"))),IF(COUNTIFS(L_Actief,1,L_WBS,$A19,L_Doeljaar,Sel_Doeljaar,L_Versiejaar,P_VJ,L_Versie,E$8,L_Kengetal,"Omzet FY")=0,"n.b.",SUMIFS(L_Waarde,L_Actief,1,L_WBS,$A19,L_Doeljaar,Sel_Doeljaar,L_Versiejaar,P_VJ,L_Versie,E$8,L_Kengetal,"Omzet FY"))/P_Factor,IF(COUNTIFS(L_Actief,1,L_WBS,$A19,L_Doeljaar,Sel_Doeljaar,L_Versiejaar,P_VJ,L_Versie,E$8,L_Kengetal,"Omzet FY")=0,"n.b.",SUMIFS(L_Waarde,L_Actief,1,L_WBS,$A19,L_Doeljaar,Sel_Doeljaar,L_Versiejaar,P_VJ,L_Versie,E$8,L_Kengetal,"Omzet FY")))) -> 2818.8 | F19: =IF($A19="","",IF(ISNUMBER(IF(COUNTIFS(L_Actief,1,L_WBS,$A19,L_Doeljaar,Sel_Doeljaar,L_Versiejaar,P_VJ,L_Versie,F$8,L_Kengetal,"Omzet FY")=0,"n.b.",SUMIFS(L_Waarde,L_Actief,1,L_WBS,$A19,L_Doeljaar,Sel_Doeljaar,L_Versiejaar,P_VJ,L_Versie,F$8,L_Kengetal,"Omzet FY"))),IF(COUNTIFS(L_Actief,1,L_WBS,$A19,L_Doeljaar,Sel_Doeljaar,L_Versiejaar,P_VJ,L_Versie,F$8,L_Kengetal,"Omzet FY")=0,"n.b.",SUMIFS(L_Waarde,L_Actief,1,L_WBS,$A19,L_Doeljaar,Sel_Doeljaar,L_Versiejaar,P_VJ,L_Versie,F$8,L_Kengetal,"Omzet FY"))/P_Factor,IF(COUNTIFS(L_Actief,1,L_WBS,$A19,L_Doeljaar,Sel_Doeljaar,L_Versiejaar,P_VJ,L_Versie,F$8,L_Kengetal,"Omzet FY")=0,"n.b.",SUMIFS(L_Waarde,L_Actief,1,L_WBS,$A19,L_Doeljaar,Sel_Doeljaar,L_Versiejaar,P_VJ,L_Versie,F$8,L_Kengetal,"Omzet FY")))) -> 2944.08 | G19: =IF($A19="","",IF(ISNUMBER(IF(COUNTIFS(L_Actief,1,L_WBS,$A19,L_Doeljaar,Sel_Doeljaar,L_Versiejaar,P_VJ,L_Versie,G$8,L_Kengetal,"Omzet FY")=0,"n.b.",SUMIFS(L_Waarde,L_Actief,1,L_WBS,$A19,L_Doeljaar,Sel_Doeljaar,L_Versiejaar,P_VJ,L_Versie,G$8,L_Kengetal,"Omzet FY"))),IF(COUNTIFS(L_Actief,1,L_WBS,$A19,L_Doeljaar,Sel_Doeljaar,L_Versiejaar,P_VJ,L_Versie,G$8,L_Kengetal,"Omzet FY")=0,"n.b.",SUMIFS(L_Waarde,L_Actief,1,L_WBS,$A19,L_Doeljaar,Sel_Doeljaar,L_Versiejaar,P_VJ,L_Versie,G$8,L_Kengetal,"Omzet FY"))/P_Factor,IF(COUNTIFS(L_Actief,1,L_WBS,$A19,L_Doeljaar,Sel_Doeljaar,L_Versiejaar,P_VJ,L_Versie,G$8,L_Kengetal,"Omzet FY")=0,"n.b.",SUMIFS(L_Waarde,L_Actief,1,L_WBS,$A19,L_Doeljaar,Sel_Doeljaar,L_Versiejaar,P_VJ,L_Versie,G$8,L_Kengetal,"Omzet FY")))) -> 3225.96 | H19: =IF($A19="","",IF(ISNUMBER(IF(COUNTIFS(L_Actief,1,L_WBS,$A19,L_Doeljaar,Sel_Doeljaar,L_Versiejaar,P_VJ,L_Versie,H$8,L_Kengetal,"Omzet FY")=0,"n.b.",SUMIFS(L_Waarde,L_Actief,1,L_WBS,$A19,L_Doeljaar,Sel_Doeljaar,L_Versiejaar,P_VJ,L_Versie,H$8,L_Kengetal,"Omzet FY"))),IF(COUNTIFS(L_Actief,1,L_WBS,$A19,L_Doeljaar,Sel_Doeljaar,L_Versiejaar,P_VJ,L_Versie,H$8,L_Kengetal,"Omzet FY")=0,"n.b.",SUMIFS(L_Waarde,L_Actief,1,L_WBS,$A19,L_Doeljaar,Sel_Doeljaar,L_Versiejaar,P_VJ,L_Versie,H$8,L_Kengetal,"Omzet FY"))/P_Factor,IF(COUNTIFS(L_Actief,1,L_WBS,$A19,L_Doeljaar,Sel_Doeljaar,L_Versiejaar,P_VJ,L_Versie,H$8,L_Kengetal,"Omzet FY")=0,"n.b.",SUMIFS(L_Waarde,L_Actief,1,L_WBS,$A19,L_Doeljaar,Sel_Doeljaar,L_Versiejaar,P_VJ,L_Versie,H$8,L_Kengetal,"Omzet FY")))) -> 3132 | I19: =IF($A19="","",IF(ISNUMBER(IF(COUNTIFS(L_Actief,1,L_WBS,$A19,L_Doeljaar,Sel_Doeljaar,L_Versiejaar,P_VJ,L_Versie,I$8,L_Kengetal,"Omzet FY")=0,"n.b.",SUMIFS(L_Waarde,L_Actief,1,L_WBS,$A19,L_Doeljaar,Sel_Doeljaar,L_Versiejaar,P_VJ,L_Versie,I$8,L_Kengetal,"Omzet FY"))),IF(COUNTIFS(L_Actief,1,L_WBS,$A19,L_Doeljaar,Sel_Doeljaar,L_Versiejaar,P_VJ,L_Versie,I$8,L_Kengetal,"Omzet FY")=0,"n.b.",SUMIFS(L_Waarde,L_Actief,1,L_WBS,$A19,L_Doeljaar,Sel_Doeljaar,L_Versiejaar,P_VJ,L_Versie,I$8,L_Kengetal,"Omzet FY"))/P_Factor,IF(COUNTIFS(L_Actief,1,L_WBS,$A19,L_Doeljaar,Sel_Doeljaar,L_Versiejaar,P_VJ,L_Versie,I$8,L_Kengetal,"Omzet FY")=0,"n.b.",SUMIFS(L_Waarde,L_Actief,1,L_WBS,$A19,L_Doeljaar,Sel_Doeljaar,L_Versiejaar,P_VJ,L_Versie,I$8,L_Kengetal,"Omzet FY")))) -> n.b. | J19: =IF($A19="","",IF(ISNUMBER(IF(Sel_Doeljaar=P_RJ,VERW_Project!$P15,IF(Sel_Doeljaar=P_RJ+1,VERW_Project!$R15,"n.b."))),IF(Sel_Doeljaar=P_RJ,VERW_Project!$P15,IF(Sel_Doeljaar=P_RJ+1,VERW_Project!$R15,"n.b."))/P_Factor,IF(Sel_Doeljaar=P_RJ,VERW_Project!$P15,IF(Sel_Doeljaar=P_RJ+1,VERW_Project!$R15,"n.b.")))) -> 3132 | K19: =IF($A19="","",IF(Sel_Bron="Vastgesteld",INDEX($E19:$I19,MATCH(Sel_Versie,$E$8:$I$8,0)),IF(Sel_Bron="Concept",J19,"n.b."))) -> 3132 | L19: =IF($A19="","",IF(Sel_Doeljaar>P_VJ,"n.v.t.",IF(Sel_Bron="Vastgesteld",IF(ISNUMBER(IF(COUNTIFS(L_Actief,1,L_WBS,$A19,L_Doeljaar,Sel_Doeljaar,L_Versiejaar,P_VJ,L_Versie,Sel_Versie,L_Kengetal,"Omzet actual YTD")=0,"n.b.",SUMIFS(L_Waarde,L_Actief,1,L_WBS,$A19,L_Doeljaar,Sel_Doeljaar,L_Versiejaar,P_VJ,L_Versie,Sel_Versie,L_Kengetal,"Omzet actual YTD"))),IF(COUNTIFS(L_Actief,1,L_WBS,$A19,L_Doeljaar,Sel_Doeljaar,L_Versiejaar,P_VJ,L_Versie,Sel_Versie,L_Kengetal,"Omzet actual YTD")=0,"n.b.",SUMIFS(L_Waarde,L_Actief,1,L_WBS,$A19,L_Doeljaar,Sel_Doeljaar,L_Versiejaar,P_VJ,L_Versie,Sel_Versie,L_Kengetal,"Omzet actual YTD"))/P_Factor,IF(COUNTIFS(L_Actief,1,L_WBS,$A19,L_Doeljaar,Sel_Doeljaar,L_Versiejaar,P_VJ,L_Versie,Sel_Versie,L_Kengetal,"Omzet actual YTD")=0,"n.b.",SUMIFS(L_Waarde,L_Actief,1,L_WBS,$A19,L_Doeljaar,Sel_Doeljaar,L_Versiejaar,P_VJ,L_Versie,Sel_Versie,L_Kengetal,"Omzet actual YTD"))),IF(Sel_Bron="Concept",IF(ISNUMBER(IF(Sel_Doeljaar=P_RJ,VERW_Project!$L15,"n.v.t.")),IF(Sel_Doeljaar=P_RJ,VERW_Project!$L15,"n.v.t.")/P_Factor,IF(Sel_Doeljaar=P_RJ,VERW_Project!$L15,"n.v.t.")),"n.b.")))) -> 2035.8 | M19: =IF($A19="","",IF(L19="n.v.t.",K19,IF(AND(ISNUMBER(K19),ISNUMBER(L19)),K19-L19,"n.b."))) -> 1096.2 | N19: =IF($A19="","",IF(Sel_Bron="Vastgesteld",IF(ISNUMBER(IF(COUNTIFS(L_Actief,1,L_WBS,$A19,L_Doeljaar,Sel_Doeljaar,L_Versiejaar,P_VJ,L_Versie,Sel_Versie,L_Kengetal,"BOR FY")=0,"n.b.",SUMIFS(L_Waarde,L_Actief,1,L_WBS,$A19,L_Doeljaar,Sel_Doeljaar,L_Versiejaar,P_VJ,L_Versie,Sel_Versie,L_Kengetal,"BOR FY"))),IF(COUNTIFS(L_Actief,1,L_WBS,$A19,L_Doeljaar,Sel_Doeljaar,L_Versiejaar,P_VJ,L_Versie,Sel_Versie,L_Kengetal,"BOR FY")=0,"n.b.",SUMIFS(L_Waarde,L_Actief,1,L_WBS,$A19,L_Doeljaar,Sel_Doeljaar,L_Versiejaar,P_VJ,L_Versie,Sel_Versie,L_Kengetal,"BOR FY"))/P_Factor,IF(COUNTIFS(L_Actief,1,L_WBS,$A19,L_Doeljaar,Sel_Doeljaar,L_Versiejaar,P_VJ,L_Versie,Sel_Versie,L_Kengetal,"BOR FY")=0,"n.b.",SUMIFS(L_Waarde,L_Actief,1,L_WBS,$A19,L_Doeljaar,Sel_Doeljaar,L_Versiejaar,P_VJ,L_Versie,Sel_Versie,L_Kengetal,"BOR FY"))),IF(Sel_Bron="Concept",IF(ISNUMBER(IF(Sel_Doeljaar=P_RJ,VERW_Project!$Q15,IF(Sel_Doeljaar=P_RJ+1,VERW_Project!$S15,"n.b."))),IF(Sel_Doeljaar=P_RJ,VERW_Project!$Q15,IF(Sel_Doeljaar=P_RJ+1,VERW_Project!$S15,"n.b."))/P_Factor,IF(Sel_Doeljaar=P_RJ,VERW_Project!$Q15,IF(Sel_Doeljaar=P_RJ+1,VERW_Project!$S15,"n.b."))),"n.b."))) -> 407.16 | O19: =IF($A19="","",IF(AND(ISNUMBER(N19),ISNUMBER(K19)),IF(K19<>0,N19/K19,"n.b."),"n.b.")) -> 0.13 | P19: =IF($A19="","",IF(AND(ISNUMBER(K19),ISNUMBER(E19)),K19-E19,"n.b.")) -> 313.2 | Q19: =IF($A19="","",IF(AND(ISNUMBER(K19),ISNUMBER(W19)),K19-W19,"n.b.")) -> -93.96 | R19: =IF($A19="","",IF(ISNUMBER(N19),IF(N19<0,"Verlies",""),"")) | S19: =IF($A19="","",IFERROR(INDEX(T_Txt,MATCH($A19&"|"&Sel_Doeljaar&"|"&P_VJ&"|"&Sel_Versie,T_Key,0)),"")) | U19: =IF(AND(AND($A19<>"",OR(Sel_Type="Alle",$C19=Sel_Type),OR(Sel_Project="Alle",$B19=Sel_Project)),ISNUMBER(K19)),K19+ROW()/1000000000,"") -> 3132 | V19: =IF(AND(AND($A19<>"",OR(Sel_Type="Alle",$C19=Sel_Type),OR(Sel_Project="Alle",$B19=Sel_Project)),ISNUMBER(Q19)),ABS(Q19)+ROW()/1000000000,"") -> 93.96 | W19: =IF(OR($A19="",Sel_Prev=""),"n.b.",IF(ISNUMBER(IF(COUNTIFS(L_Actief,1,L_WBS,$A19,L_Doeljaar,Sel_Doeljaar,L_Versiejaar,P_VJ,L_Versie,Sel_Prev,L_Kengetal,"Omzet FY")=0,"n.b.",SUMIFS(L_Waarde,L_Actief,1,L_WBS,$A19,L_Doeljaar,Sel_Doeljaar,L_Versiejaar,P_VJ,L_Versie,Sel_Prev,L_Kengetal,"Omzet FY"))),IF(COUNTIFS(L_Actief,1,L_WBS,$A19,L_Doeljaar,Sel_Doeljaar,L_Versiejaar,P_VJ,L_Versie,Sel_Prev,L_Kengetal,"Omzet FY")=0,"n.b.",SUMIFS(L_Waarde,L_Actief,1,L_WBS,$A19,L_Doeljaar,Sel_Doeljaar,L_Versiejaar,P_VJ,L_Versie,Sel_Prev,L_Kengetal,"Omzet FY"))/P_Factor,IF(COUNTIFS(L_Actief,1,L_WBS,$A19,L_Doeljaar,Sel_Doeljaar,L_Versiejaar,P_VJ,L_Versie,Sel_Prev,L_Kengetal,"Omzet FY")=0,"n.b.",SUMIFS(L_Waarde,L_Actief,1,L_WBS,$A19,L_Doeljaar,Sel_Doeljaar,L_Versiejaar,P_VJ,L_Versie,Sel_Prev,L_Kengetal,"Omzet FY")))) -> 3225.96
A20: =IF(VERW_Project!$A16="","",VERW_Project!$A16) -> G.900011.8.9090 | B20: =IF($A20="","",VERW_Project!$C16) -> Meerhovenstad, Hofstaete | C20: =IF($A20="","",VERW_Project!$D16) -> Opstal | D20: =IF($A20="","",VERW_Project!$I16) -> J | E20: =IF($A20="","",IF(ISNUMBER(IF(COUNTIFS(L_Actief,1,L_WBS,$A20,L_Doeljaar,Sel_Doeljaar,L_Versiejaar,P_VJ,L_Versie,E$8,L_Kengetal,"Omzet FY")=0,"n.b.",SUMIFS(L_Waarde,L_Actief,1,L_WBS,$A20,L_Doeljaar,Sel_Doeljaar,L_Versiejaar,P_VJ,L_Versie,E$8,L_Kengetal,"Omzet FY"))),IF(COUNTIFS(L_Actief,1,L_WBS,$A20,L_Doeljaar,Sel_Doeljaar,L_Versiejaar,P_VJ,L_Versie,E$8,L_Kengetal,"Omzet FY")=0,"n.b.",SUMIFS(L_Waarde,L_Actief,1,L_WBS,$A20,L_Doeljaar,Sel_Doeljaar,L_Versiejaar,P_VJ,L_Versie,E$8,L_Kengetal,"Omzet FY"))/P_Factor,IF(COUNTIFS(L_Actief,1,L_WBS,$A20,L_Doeljaar,Sel_Doeljaar,L_Versiejaar,P_VJ,L_Versie,E$8,L_Kengetal,"Omzet FY")=0,"n.b.",SUMIFS(L_Waarde,L_Actief,1,L_WBS,$A20,L_Doeljaar,Sel_Doeljaar,L_Versiejaar,P_VJ,L_Versie,E$8,L_Kengetal,"Omzet FY")))) -> 16051.2 | F20: =IF($A20="","",IF(ISNUMBER(IF(COUNTIFS(L_Actief,1,L_WBS,$A20,L_Doeljaar,Sel_Doeljaar,L_Versiejaar,P_VJ,L_Versie,F$8,L_Kengetal,"Omzet FY")=0,"n.b.",SUMIFS(L_Waarde,L_Actief,1,L_WBS,$A20,L_Doeljaar,Sel_Doeljaar,L_Versiejaar,P_VJ,L_Versie,F$8,L_Kengetal,"Omzet FY"))),IF(COUNTIFS(L_Actief,1,L_WBS,$A20,L_Doeljaar,Sel_Doeljaar,L_Versiejaar,P_VJ,L_Versie,F$8,L_Kengetal,"Omzet FY")=0,"n.b.",SUMIFS(L_Waarde,L_Actief,1,L_WBS,$A20,L_Doeljaar,Sel_Doeljaar,L_Versiejaar,P_VJ,L_Versie,F$8,L_Kengetal,"Omzet FY"))/P_Factor,IF(COUNTIFS(L_Actief,1,L_WBS,$A20,L_Doeljaar,Sel_Doeljaar,L_Versiejaar,P_VJ,L_Versie,F$8,L_Kengetal,"Omzet FY")=0,"n.b.",SUMIFS(L_Waarde,L_Actief,1,L_WBS,$A20,L_Doeljaar,Sel_Doeljaar,L_Versiejaar,P_VJ,L_Versie,F$8,L_Kengetal,"Omzet FY")))) -> 15467.52 | G20: =IF($A20="","",IF(ISNUMBER(IF(COUNTIFS(L_Actief,1,L_WBS,$A20,L_Doeljaar,Sel_Doeljaar,L_Versiejaar,P_VJ,L_Versie,G$8,L_Kengetal,"Omzet FY")=0,"n.b.",SUMIFS(L_Waarde,L_Actief,1,L_WBS,$A20,L_Doeljaar,Sel_Doeljaar,L_Versiejaar,P_VJ,L_Versie,G$8,L_Kengetal,"Omzet FY"))),IF(COUNTIFS(L_Actief,1,L_WBS,$A20,L_Doeljaar,Sel_Doeljaar,L_Versiejaar,P_VJ,L_Versie,G$8,L_Kengetal,"Omzet FY")=0,"n.b.",SUMIFS(L_Waarde,L_Actief,1,L_WBS,$A20,L_Doeljaar,Sel_Doeljaar,L_Versiejaar,P_VJ,L_Versie,G$8,L_Kengetal,"Omzet FY"))/P_Factor,IF(COUNTIFS(L_Actief,1,L_WBS,$A20,L_Doeljaar,Sel_Doeljaar,L_Versiejaar,P_VJ,L_Versie,G$8,L_Kengetal,"Omzet FY")=0,"n.b.",SUMIFS(L_Waarde,L_Actief,1,L_WBS,$A20,L_Doeljaar,Sel_Doeljaar,L_Versiejaar,P_VJ,L_Versie,G$8,L_Kengetal,"Omzet FY")))) -> 14154.24 | H20: =IF($A20="","",IF(ISNUMBER(IF(COUNTIFS(L_Actief,1,L_WBS,$A20,L_Doeljaar,Sel_Doeljaar,L_Versiejaar,P_VJ,L_Versie,H$8,L_Kengetal,"Omzet FY")=0,"n.b.",SUMIFS(L_Waarde,L_Actief,1,L_WBS,$A20,L_Doeljaar,Sel_Doeljaar,L_Versiejaar,P_VJ,L_Versie,H$8,L_Kengetal,"Omzet FY"))),IF(COUNTIFS(L_Actief,1,L_WBS,$A20,L_Doeljaar,Sel_Doeljaar,L_Versiejaar,P_VJ,L_Versie,H$8,L_Kengetal,"Omzet FY")=0,"n.b.",SUMIFS(L_Waarde,L_Actief,1,L_WBS,$A20,L_Doeljaar,Sel_Doeljaar,L_Versiejaar,P_VJ,L_Versie,H$8,L_Kengetal,"Omzet FY"))/P_Factor,IF(COUNTIFS(L_Actief,1,L_WBS,$A20,L_Doeljaar,Sel_Doeljaar,L_Versiejaar,P_VJ,L_Versie,H$8,L_Kengetal,"Omzet FY")=0,"n.b.",SUMIFS(L_Waarde,L_Actief,1,L_WBS,$A20,L_Doeljaar,Sel_Doeljaar,L_Versiejaar,P_VJ,L_Versie,H$8,L_Kengetal,"Omzet FY")))) -> 14592 | I20: =IF($A20="","",IF(ISNUMBER(IF(COUNTIFS(L_Actief,1,L_WBS,$A20,L_Doeljaar,Sel_Doeljaar,L_Versiejaar,P_VJ,L_Versie,I$8,L_Kengetal,"Omzet FY")=0,"n.b.",SUMIFS(L_Waarde,L_Actief,1,L_WBS,$A20,L_Doeljaar,Sel_Doeljaar,L_Versiejaar,P_VJ,L_Versie,I$8,L_Kengetal,"Omzet FY"))),IF(COUNTIFS(L_Actief,1,L_WBS,$A20,L_Doeljaar,Sel_Doeljaar,L_Versiejaar,P_VJ,L_Versie,I$8,L_Kengetal,"Omzet FY")=0,"n.b.",SUMIFS(L_Waarde,L_Actief,1,L_WBS,$A20,L_Doeljaar,Sel_Doeljaar,L_Versiejaar,P_VJ,L_Versie,I$8,L_Kengetal,"Omzet FY"))/P_Factor,IF(COUNTIFS(L_Actief,1,L_WBS,$A20,L_Doeljaar,Sel_Doeljaar,L_Versiejaar,P_VJ,L_Versie,I$8,L_Kengetal,"Omzet FY")=0,"n.b.",SUMIFS(L_Waarde,L_Actief,1,L_WBS,$A20,L_Doeljaar,Sel_Doeljaar,L_Versiejaar,P_VJ,L_Versie,I$8,L_Kengetal,"Omzet FY")))) -> n.b. | J20: =IF($A20="","",IF(ISNUMBER(IF(Sel_Doeljaar=P_RJ,VERW_Project!$P16,IF(Sel_Doeljaar=P_RJ+1,VERW_Project!$R16,"n.b."))),IF(Sel_Doeljaar=P_RJ,VERW_Project!$P16,IF(Sel_Doeljaar=P_RJ+1,VERW_Project!$R16,"n.b."))/P_Factor,IF(Sel_Doeljaar=P_RJ,VERW_Project!$P16,IF(Sel_Doeljaar=P_RJ+1,VERW_Project!$R16,"n.b.")))) -> 14592 | K20: =IF($A20="","",IF(Sel_Bron="Vastgesteld",INDEX($E20:$I20,MATCH(Sel_Versie,$E$8:$I$8,0)),IF(Sel_Bron="Concept",J20,"n.b."))) -> 14592 | L20: =IF($A20="","",IF(Sel_Doeljaar>P_VJ,"n.v.t.",IF(Sel_Bron="Vastgesteld",IF(ISNUMBER(IF(COUNTIFS(L_Actief,1,L_WBS,$A20,L_Doeljaar,Sel_Doeljaar,L_Versiejaar,P_VJ,L_Versie,Sel_Versie,L_Kengetal,"Omzet actual YTD")=0,"n.b.",SUMIFS(L_Waarde,L_Actief,1,L_WBS,$A20,L_Doeljaar,Sel_Doeljaar,L_Versiejaar,P_VJ,L_Versie,Sel_Versie,L_Kengetal,"Omzet actual YTD"))),IF(COUNTIFS(L_Actief,1,L_WBS,$A20,L_Doeljaar,Sel_Doeljaar,L_Versiejaar,P_VJ,L_Versie,Sel_Versie,L_Kengetal,"Omzet actual YTD")=0,"n.b.",SUMIFS(L_Waarde,L_Actief,1,L_WBS,$A20,L_Doeljaar,Sel_Doeljaar,L_Versiejaar,P_VJ,L_Versie,Sel_Versie,L_Kengetal,"Omzet actual YTD"))/P_Factor,IF(COUNTIFS(L_Actief,1,L_WBS,$A20,L_Doeljaar,Sel_Doeljaar,L_Versiejaar,P_VJ,L_Versie,Sel_Versie,L_Kengetal,"Omzet actual YTD")=0,"n.b.",SUMIFS(L_Waarde,L_Actief,1,L_WBS,$A20,L_Doeljaar,Sel_Doeljaar,L_Versiejaar,P_VJ,L_Versie,Sel_Versie,L_Kengetal,"Omzet actual YTD"))),IF(Sel_Bron="Concept",IF(ISNUMBER(IF(Sel_Doeljaar=P_RJ,VERW_Project!$L16,"n.v.t.")),IF(Sel_Doeljaar=P_RJ,VERW_Project!$L16,"n.v.t.")/P_Factor,IF(Sel_Doeljaar=P_RJ,VERW_Project!$L16,"n.v.t.")),"n.b.")))) -> 9484.8 | M20: =IF($A20="","",IF(L20="n.v.t.",K20,IF(AND(ISNUMBER(K20),ISNUMBER(L20)),K20-L20,"n.b."))) -> 5107.2 | N20: =IF($A20="","",IF(Sel_Bron="Vastgesteld",IF(ISNUMBER(IF(COUNTIFS(L_Actief,1,L_WBS,$A20,L_Doeljaar,Sel_Doeljaar,L_Versiejaar,P_VJ,L_Versie,Sel_Versie,L_Kengetal,"BOR FY")=0,"n.b.",SUMIFS(L_Waarde,L_Actief,1,L_WBS,$A20,L_Doeljaar,Sel_Doeljaar,L_Versiejaar,P_VJ,L_Versie,Sel_Versie,L_Kengetal,"BOR FY"))),IF(COUNTIFS(L_Actief,1,L_WBS,$A20,L_Doeljaar,Sel_Doeljaar,L_Versiejaar,P_VJ,L_Versie,Sel_Versie,L_Kengetal,"BOR FY")=0,"n.b.",SUMIFS(L_Waarde,L_Actief,1,L_WBS,$A20,L_Doeljaar,Sel_Doeljaar,L_Versiejaar,P_VJ,L_Versie,Sel_Versie,L_Kengetal,"BOR FY"))/P_Factor,IF(COUNTIFS(L_Actief,1,L_WBS,$A20,L_Doeljaar,Sel_Doeljaar,L_Versiejaar,P_VJ,L_Versie,Sel_Versie,L_Kengetal,"BOR FY")=0,"n.b.",SUMIFS(L_Waarde,L_Actief,1,L_WBS,$A20,L_Doeljaar,Sel_Doeljaar,L_Versiejaar,P_VJ,L_Versie,Sel_Versie,L_Kengetal,"BOR FY"))),IF(Sel_Bron="Concept",IF(ISNUMBER(IF(Sel_Doeljaar=P_RJ,VERW_Project!$Q16,IF(Sel_Doeljaar=P_RJ+1,VERW_Project!$S16,"n.b."))),IF(Sel_Doeljaar=P_RJ,VERW_Project!$Q16,IF(Sel_Doeljaar=P_RJ+1,VERW_Project!$S16,"n.b."))/P_Factor,IF(Sel_Doeljaar=P_RJ,VERW_Project!$Q16,IF(Sel_Doeljaar=P_RJ+1,VERW_Project!$S16,"n.b."))),"n.b."))) -> 1313.28 | O20: =IF($A20="","",IF(AND(ISNUMBER(N20),ISNUMBER(K20)),IF(K20<>0,N20/K20,"n.b."),"n.b.")) -> 0.09 | P20: =IF($A20="","",IF(AND(ISNUMBER(K20),ISNUMBER(E20)),K20-E20,"n.b.")) -> -1459.2 | Q20: =IF($A20="","",IF(AND(ISNUMBER(K20),ISNUMBER(W20)),K20-W20,"n.b.")) -> 437.76 | R20: =IF($A20="","",IF(ISNUMBER(N20),IF(N20<0,"Verlies",""),"")) | S20: =IF($A20="","",IFERROR(INDEX(T_Txt,MATCH($A20&"|"&Sel_Doeljaar&"|"&P_VJ&"|"&Sel_Versie,T_Key,0)),"")) | U20: =IF(AND(AND($A20<>"",OR(Sel_Type="Alle",$C20=Sel_Type),OR(Sel_Project="Alle",$B20=Sel_Project)),ISNUMBER(K20)),K20+ROW()/1000000000,"") -> 14592 | V20: =IF(AND(AND($A20<>"",OR(Sel_Type="Alle",$C20=Sel_Type),OR(Sel_Project="Alle",$B20=Sel_Project)),ISNUMBER(Q20)),ABS(Q20)+ROW()/1000000000,"") -> 437.76 | W20: =IF(OR($A20="",Sel_Prev=""),"n.b.",IF(ISNUMBER(IF(COUNTIFS(L_Actief,1,L_WBS,$A20,L_Doeljaar,Sel_Doeljaar,L_Versiejaar,P_VJ,L_Versie,Sel_Prev,L_Kengetal,"Omzet FY")=0,"n.b.",SUMIFS(L_Waarde,L_Actief,1,L_WBS,$A20,L_Doeljaar,Sel_Doeljaar,L_Versiejaar,P_VJ,L_Versie,Sel_Prev,L_Kengetal,"Omzet FY"))),IF(COUNTIFS(L_Actief,1,L_WBS,$A20,L_Doeljaar,Sel_Doeljaar,L_Versiejaar,P_VJ,L_Versie,Sel_Prev,L_Kengetal,"Omzet FY")=0,"n.b.",SUMIFS(L_Waarde,L_Actief,1,L_WBS,$A20,L_Doeljaar,Sel_Doeljaar,L_Versiejaar,P_VJ,L_Versie,Sel_Prev,L_Kengetal,"Omzet FY"))/P_Factor,IF(COUNTIFS(L_Actief,1,L_WBS,$A20,L_Doeljaar,Sel_Doeljaar,L_Versiejaar,P_VJ,L_Versie,Sel_Prev,L_Kengetal,"Omzet FY")=0,"n.b.",SUMIFS(L_Waarde,L_Actief,1,L_WBS,$A20,L_Doeljaar,Sel_Doeljaar,L_Versiejaar,P_VJ,L_Versie,Sel_Prev,L_Kengetal,"Omzet FY")))) -> 14154.24
A21: =IF(VERW_Project!$A17="","",VERW_Project!$A17) -> G.900012.8.9090 | B21: =IF($A21="","",VERW_Project!$C17) -> Zilverdam, De Werf | C21: =IF($A21="","",VERW_Project!$D17) -> Deelneming | D21: =IF($A21="","",VERW_Project!$I17) -> N | E21: =IF($A21="","",IF(ISNUMBER(IF(COUNTIFS(L_Actief,1,L_WBS,$A21,L_Doeljaar,Sel_Doeljaar,L_Versiejaar,P_VJ,L_Versie,E$8,L_Kengetal,"Omzet FY")=0,"n.b.",SUMIFS(L_Waarde,L_Actief,1,L_WBS,$A21,L_Doeljaar,Sel_Doeljaar,L_Versiejaar,P_VJ,L_Versie,E$8,L_Kengetal,"Omzet FY"))),IF(COUNTIFS(L_Actief,1,L_WBS,$A21,L_Doeljaar,Sel_Doeljaar,L_Versiejaar,P_VJ,L_Versie,E$8,L_Kengetal,"Omzet FY")=0,"n.b.",SUMIFS(L_Waarde,L_Actief,1,L_WBS,$A21,L_Doeljaar,Sel_Doeljaar,L_Versiejaar,P_VJ,L_Versie,E$8,L_Kengetal,"Omzet FY"))/P_Factor,IF(COUNTIFS(L_Actief,1,L_WBS,$A21,L_Doeljaar,Sel_Doeljaar,L_Versiejaar,P_VJ,L_Versie,E$8,L_Kengetal,"Omzet FY")=0,"n.b.",SUMIFS(L_Waarde,L_Actief,1,L_WBS,$A21,L_Doeljaar,Sel_Doeljaar,L_Versiejaar,P_VJ,L_Versie,E$8,L_Kengetal,"Omzet FY")))) -> 1291.5 | F21: =IF($A21="","",IF(ISNUMBER(IF(COUNTIFS(L_Actief,1,L_WBS,$A21,L_Doeljaar,Sel_Doeljaar,L_Versiejaar,P_VJ,L_Versie,F$8,L_Kengetal,"Omzet FY")=0,"n.b.",SUMIFS(L_Waarde,L_Actief,1,L_WBS,$A21,L_Doeljaar,Sel_Doeljaar,L_Versiejaar,P_VJ,L_Versie,F$8,L_Kengetal,"Omzet FY"))),IF(COUNTIFS(L_Actief,1,L_WBS,$A21,L_Doeljaar,Sel_Doeljaar,L_Versiejaar,P_VJ,L_Versie,F$8,L_Kengetal,"Omzet FY")=0,"n.b.",SUMIFS(L_Waarde,L_Actief,1,L_WBS,$A21,L_Doeljaar,Sel_Doeljaar,L_Versiejaar,P_VJ,L_Versie,F$8,L_Kengetal,"Omzet FY"))/P_Factor,IF(COUNTIFS(L_Actief,1,L_WBS,$A21,L_Doeljaar,Sel_Doeljaar,L_Versiejaar,P_VJ,L_Versie,F$8,L_Kengetal,"Omzet FY")=0,"n.b.",SUMIFS(L_Waarde,L_Actief,1,L_WBS,$A21,L_Doeljaar,Sel_Doeljaar,L_Versiejaar,P_VJ,L_Versie,F$8,L_Kengetal,"Omzet FY")))) -> 1348.9 | G21: =IF($A21="","",IF(ISNUMBER(IF(COUNTIFS(L_Actief,1,L_WBS,$A21,L_Doeljaar,Sel_Doeljaar,L_Versiejaar,P_VJ,L_Versie,G$8,L_Kengetal,"Omzet FY")=0,"n.b.",SUMIFS(L_Waarde,L_Actief,1,L_WBS,$A21,L_Doeljaar,Sel_Doeljaar,L_Versiejaar,P_VJ,L_Versie,G$8,L_Kengetal,"Omzet FY"))),IF(COUNTIFS(L_Actief,1,L_WBS,$A21,L_Doeljaar,Sel_Doeljaar,L_Versiejaar,P_VJ,L_Versie,G$8,L_Kengetal,"Omzet FY")=0,"n.b.",SUMIFS(L_Waarde,L_Actief,1,L_WBS,$A21,L_Doeljaar,Sel_Doeljaar,L_Versiejaar,P_VJ,L_Versie,G$8,L_Kengetal,"Omzet FY"))/P_Factor,IF(COUNTIFS(L_Actief,1,L_WBS,$A21,L_Doeljaar,Sel_Doeljaar,L_Versiejaar,P_VJ,L_Versie,G$8,L_Kengetal,"Omzet FY")=0,"n.b.",SUMIFS(L_Waarde,L_Actief,1,L_WBS,$A21,L_Doeljaar,Sel_Doeljaar,L_Versiejaar,P_VJ,L_Versie,G$8,L_Kengetal,"Omzet FY")))) -> 1478.05 | H21: =IF($A21="","",IF(ISNUMBER(IF(COUNTIFS(L_Actief,1,L_WBS,$A21,L_Doeljaar,Sel_Doeljaar,L_Versiejaar,P_VJ,L_Versie,H$8,L_Kengetal,"Omzet FY")=0,"n.b.",SUMIFS(L_Waarde,L_Actief,1,L_WBS,$A21,L_Doeljaar,Sel_Doeljaar,L_Versiejaar,P_VJ,L_Versie,H$8,L_Kengetal,"Omzet FY"))),IF(COUNTIFS(L_Actief,1,L_WBS,$A21,L_Doeljaar,Sel_Doeljaar,L_Versiejaar,P_VJ,L_Versie,H$8,L_Kengetal,"Omzet FY")=0,"n.b.",SUMIFS(L_Waarde,L_Actief,1,L_WBS,$A21,L_Doeljaar,Sel_Doeljaar,L_Versiejaar,P_VJ,L_Versie,H$8,L_Kengetal,"Omzet FY"))/P_Factor,IF(COUNTIFS(L_Actief,1,L_WBS,$A21,L_Doeljaar,Sel_Doeljaar,L_Versiejaar,P_VJ,L_Versie,H$8,L_Kengetal,"Omzet FY")=0,"n.b.",SUMIFS(L_Waarde,L_Actief,1,L_WBS,$A21,L_Doeljaar,Sel_Doeljaar,L_Versiejaar,P_VJ,L_Versie,H$8,L_Kengetal,"Omzet FY")))) -> 1435 | I21: =IF($A21="","",IF(ISNUMBER(IF(COUNTIFS(L_Actief,1,L_WBS,$A21,L_Doeljaar,Sel_Doeljaar,L_Versiejaar,P_VJ,L_Versie,I$8,L_Kengetal,"Omzet FY")=0,"n.b.",SUMIFS(L_Waarde,L_Actief,1,L_WBS,$A21,L_Doeljaar,Sel_Doeljaar,L_Versiejaar,P_VJ,L_Versie,I$8,L_Kengetal,"Omzet FY"))),IF(COUNTIFS(L_Actief,1,L_WBS,$A21,L_Doeljaar,Sel_Doeljaar,L_Versiejaar,P_VJ,L_Versie,I$8,L_Kengetal,"Omzet FY")=0,"n.b.",SUMIFS(L_Waarde,L_Actief,1,L_WBS,$A21,L_Doeljaar,Sel_Doeljaar,L_Versiejaar,P_VJ,L_Versie,I$8,L_Kengetal,"Omzet FY"))/P_Factor,IF(COUNTIFS(L_Actief,1,L_WBS,$A21,L_Doeljaar,Sel_Doeljaar,L_Versiejaar,P_VJ,L_Versie,I$8,L_Kengetal,"Omzet FY")=0,"n.b.",SUMIFS(L_Waarde,L_Actief,1,L_WBS,$A21,L_Doeljaar,Sel_Doeljaar,L_Versiejaar,P_VJ,L_Versie,I$8,L_Kengetal,"Omzet FY")))) -> n.b. | J21: =IF($A21="","",IF(ISNUMBER(IF(Sel_Doeljaar=P_RJ,VERW_Project!$P17,IF(Sel_Doeljaar=P_RJ+1,VERW_Project!$R17,"n.b."))),IF(Sel_Doeljaar=P_RJ,VERW_Project!$P17,IF(Sel_Doeljaar=P_RJ+1,VERW_Project!$R17,"n.b."))/P_Factor,IF(Sel_Doeljaar=P_RJ,VERW_Project!$P17,IF(Sel_Doeljaar=P_RJ+1,VERW_Project!$R17,"n.b.")))) -> 1435 | K21: =IF($A21="","",IF(Sel_Bron="Vastgesteld",INDEX($E21:$I21,MATCH(Sel_Versie,$E$8:$I$8,0)),IF(Sel_Bron="Concept",J21,"n.b."))) -> 1435 | L21: =IF($A21="","",IF(Sel_Doeljaar>P_VJ,"n.v.t.",IF(Sel_Bron="Vastgesteld",IF(ISNUMBER(IF(COUNTIFS(L_Actief,1,L_WBS,$A21,L_Doeljaar,Sel_Doeljaar,L_Versiejaar,P_VJ,L_Versie,Sel_Versie,L_Kengetal,"Omzet actual YTD")=0,"n.b.",SUMIFS(L_Waarde,L_Actief,1,L_WBS,$A21,L_Doeljaar,Sel_Doeljaar,L_Versiejaar,P_VJ,L_Versie,Sel_Versie,L_Kengetal,"Omzet actual YTD"))),IF(COUNTIFS(L_Actief,1,L_WBS,$A21,L_Doeljaar,Sel_Doeljaar,L_Versiejaar,P_VJ,L_Versie,Sel_Versie,L_Kengetal,"Omzet actual YTD")=0,"n.b.",SUMIFS(L_Waarde,L_Actief,1,L_WBS,$A21,L_Doeljaar,Sel_Doeljaar,L_Versiejaar,P_VJ,L_Versie,Sel_Versie,L_Kengetal,"Omzet actual YTD"))/P_Factor,IF(COUNTIFS(L_Actief,1,L_WBS,$A21,L_Doeljaar,Sel_Doeljaar,L_Versiejaar,P_VJ,L_Versie,Sel_Versie,L_Kengetal,"Omzet actual YTD")=0,"n.b.",SUMIFS(L_Waarde,L_Actief,1,L_WBS,$A21,L_Doeljaar,Sel_Doeljaar,L_Versiejaar,P_VJ,L_Versie,Sel_Versie,L_Kengetal,"Omzet actual YTD"))),IF(Sel_Bron="Concept",IF(ISNUMBER(IF(Sel_Doeljaar=P_RJ,VERW_Project!$L17,"n.v.t.")),IF(Sel_Doeljaar=P_RJ,VERW_Project!$L17,"n.v.t.")/P_Factor,IF(Sel_Doeljaar=P_RJ,VERW_Project!$L17,"n.v.t.")),"n.b.")))) -> 932.75 | M21: =IF($A21="","",IF(L21="n.v.t.",K21,IF(AND(ISNUMBER(K21),ISNUMBER(L21)),K21-L21,"n.b."))) -> 502.25 | N21: =IF($A21="","",IF(Sel_Bron="Vastgesteld",IF(ISNUMBER(IF(COUNTIFS(L_Actief,1,L_WBS,$A21,L_Doeljaar,Sel_Doeljaar,L_Versiejaar,P_VJ,L_Versie,Sel_Versie,L_Kengetal,"BOR FY")=0,"n.b.",SUMIFS(L_Waarde,L_Actief,1,L_WBS,$A21,L_Doeljaar,Sel_Doeljaar,L_Versiejaar,P_VJ,L_Versie,Sel_Versie,L_Kengetal,"BOR FY"))),IF(COUNTIFS(L_Actief,1,L_WBS,$A21,L_Doeljaar,Sel_Doeljaar,L_Versiejaar,P_VJ,L_Versie,Sel_Versie,L_Kengetal,"BOR FY")=0,"n.b.",SUMIFS(L_Waarde,L_Actief,1,L_WBS,$A21,L_Doeljaar,Sel_Doeljaar,L_Versiejaar,P_VJ,L_Versie,Sel_Versie,L_Kengetal,"BOR FY"))/P_Factor,IF(COUNTIFS(L_Actief,1,L_WBS,$A21,L_Doeljaar,Sel_Doeljaar,L_Versiejaar,P_VJ,L_Versie,Sel_Versie,L_Kengetal,"BOR FY")=0,"n.b.",SUMIFS(L_Waarde,L_Actief,1,L_WBS,$A21,L_Doeljaar,Sel_Doeljaar,L_Versiejaar,P_VJ,L_Versie,Sel_Versie,L_Kengetal,"BOR FY"))),IF(Sel_Bron="Concept",IF(ISNUMBER(IF(Sel_Doeljaar=P_RJ,VERW_Project!$Q17,IF(Sel_Doeljaar=P_RJ+1,VERW_Project!$S17,"n.b."))),IF(Sel_Doeljaar=P_RJ,VERW_Project!$Q17,IF(Sel_Doeljaar=P_RJ+1,VERW_Project!$S17,"n.b."))/P_Factor,IF(Sel_Doeljaar=P_RJ,VERW_Project!$Q17,IF(Sel_Doeljaar=P_RJ+1,VERW_Project!$S17,"n.b."))),"n.b."))) -> 172.2 | O21: =IF($A21="","",IF(AND(ISNUMBER(N21),ISNUMBER(K21)),IF(K21<>0,N21/K21,"n.b."),"n.b.")) -> 0.12 | P21: =IF($A21="","",IF(AND(ISNUMBER(K21),ISNUMBER(E21)),K21-E21,"n.b.")) -> 143.5 | Q21: =IF($A21="","",IF(AND(ISNUMBER(K21),ISNUMBER(W21)),K21-W21,"n.b.")) -> -43.05 | R21: =IF($A21="","",IF(ISNUMBER(N21),IF(N21<0,"Verlies",""),"")) | S21: =IF($A21="","",IFERROR(INDEX(T_Txt,MATCH($A21&"|"&Sel_Doeljaar&"|"&P_VJ&"|"&Sel_Versie,T_Key,0)),"")) | U21: =IF(AND(AND($A21<>"",OR(Sel_Type="Alle",$C21=Sel_Type),OR(Sel_Project="Alle",$B21=Sel_Project)),ISNUMBER(K21)),K21+ROW()/1000000000,"") -> 1435 | V21: =IF(AND(AND($A21<>"",OR(Sel_Type="Alle",$C21=Sel_Type),OR(Sel_Project="Alle",$B21=Sel_Project)),ISNUMBER(Q21)),ABS(Q21)+ROW()/1000000000,"") -> 43.05 | W21: =IF(OR($A21="",Sel_Prev=""),"n.b.",IF(ISNUMBER(IF(COUNTIFS(L_Actief,1,L_WBS,$A21,L_Doeljaar,Sel_Doeljaar,L_Versiejaar,P_VJ,L_Versie,Sel_Prev,L_Kengetal,"Omzet FY")=0,"n.b.",SUMIFS(L_Waarde,L_Actief,1,L_WBS,$A21,L_Doeljaar,Sel_Doeljaar,L_Versiejaar,P_VJ,L_Versie,Sel_Prev,L_Kengetal,"Omzet FY"))),IF(COUNTIFS(L_Actief,1,L_WBS,$A21,L_Doeljaar,Sel_Doeljaar,L_Versiejaar,P_VJ,L_Versie,Sel_Prev,L_Kengetal,"Omzet FY")=0,"n.b.",SUMIFS(L_Waarde,L_Actief,1,L_WBS,$A21,L_Doeljaar,Sel_Doeljaar,L_Versiejaar,P_VJ,L_Versie,Sel_Prev,L_Kengetal,"Omzet FY"))/P_Factor,IF(COUNTIFS(L_Actief,1,L_WBS,$A21,L_Doeljaar,Sel_Doeljaar,L_Versiejaar,P_VJ,L_Versie,Sel_Prev,L_Kengetal,"Omzet FY")=0,"n.b.",SUMIFS(L_Waarde,L_Actief,1,L_WBS,$A21,L_Doeljaar,Sel_Doeljaar,L_Versiejaar,P_VJ,L_Versie,Sel_Prev,L_Kengetal,"Omzet FY")))) -> 1478.05
... A109: =IF(VERW_Project!$A105="","",VERW_Project!$A105) | B109: =IF($A109="","",VERW_Project!$C105) | C109: =IF($A109="","",VERW_Project!$D105) | D109: =IF($A109="","",VERW_Project!$I105) | E109: =IF($A109="","",IF(ISNUMBER(IF(COUNTIFS(L_Actief,1,L_WBS,$A109,L_Doeljaar,Sel_Doeljaar,L_Versiejaar,P_VJ,L_Versie,E$8,L_Kengetal,"Omzet FY")=0,"n.b.",SUMIFS(L_Waarde,L_Actief,1,L_WBS,$A109,L_Doeljaar,Sel_Doeljaar,L_Versiejaar,P_VJ,L_Versie,E$8,L_Kengetal,"Omzet FY"))),IF(COUNTIFS(L_Actief,1,L_WBS,$A109,L_Doeljaar,Sel_Doeljaar,L_Versiejaar,P_VJ,L_Versie,E$8,L_Kengetal,"Omzet FY")=0,"n.b.",SUMIFS(L_Waarde,L_Actief,1,L_WBS,$A109,L_Doeljaar,Sel_Doeljaar,L_Versiejaar,P_VJ,L_Versie,E$8,L_Kengetal,"Omzet FY"))/P_Factor,IF(COUNTIFS(L_Actief,1,L_WBS,$A109,L_Doeljaar,Sel_Doeljaar,L_Versiejaar,P_VJ,L_Versie,E$8,L_Kengetal,"Omzet FY")=0,"n.b.",SUMIFS(L_Waarde,L_Actief,1,L_WBS,$A109,L_Doeljaar,Sel_Doeljaar,L_Versiejaar,P_VJ,L_Versie,E$8,L_Kengetal,"Omzet FY")))) | F109: =IF($A109="","",IF(ISNUMBER(IF(COUNTIFS(L_Actief,1,L_WBS,$A109,L_Doeljaar,Sel_Doeljaar,L_Versiejaar,P_VJ,L_Versie,F$8,L_Kengetal,"Omzet FY")=0,"n.b.",SUMIFS(L_Waarde,L_Actief,1,L_WBS,$A109,L_Doeljaar,Sel_Doeljaar,L_Versiejaar,P_VJ,L_Versie,F$8,L_Kengetal,"Omzet FY"))),IF(COUNTIFS(L_Actief,1,L_WBS,$A109,L_Doeljaar,Sel_Doeljaar,L_Versiejaar,P_VJ,L_Versie,F$8,L_Kengetal,"Omzet FY")=0,"n.b.",SUMIFS(L_Waarde,L_Actief,1,L_WBS,$A109,L_Doeljaar,Sel_Doeljaar,L_Versiejaar,P_VJ,L_Versie,F$8,L_Kengetal,"Omzet FY"))/P_Factor,IF(COUNTIFS(L_Actief,1,L_WBS,$A109,L_Doeljaar,Sel_Doeljaar,L_Versiejaar,P_VJ,L_Versie,F$8,L_Kengetal,"Omzet FY")=0,"n.b.",SUMIFS(L_Waarde,L_Actief,1,L_WBS,$A109,L_Doeljaar,Sel_Doeljaar,L_Versiejaar,P_VJ,L_Versie,F$8,L_Kengetal,"Omzet FY")))) | G109: =IF($A109="","",IF(ISNUMBER(IF(COUNTIFS(L_Actief,1,L_WBS,$A109,L_Doeljaar,Sel_Doeljaar,L_Versiejaar,P_VJ,L_Versie,G$8,L_Kengetal,"Omzet FY")=0,"n.b.",SUMIFS(L_Waarde,L_Actief,1,L_WBS,$A109,L_Doeljaar,Sel_Doeljaar,L_Versiejaar,P_VJ,L_Versie,G$8,L_Kengetal,"Omzet FY"))),IF(COUNTIFS(L_Actief,1,L_WBS,$A109,L_Doeljaar,Sel_Doeljaar,L_Versiejaar,P_VJ,L_Versie,G$8,L_Kengetal,"Omzet FY")=0,"n.b.",SUMIFS(L_Waarde,L_Actief,1,L_WBS,$A109,L_Doeljaar,Sel_Doeljaar,L_Versiejaar,P_VJ,L_Versie,G$8,L_Kengetal,"Omzet FY"))/P_Factor,IF(COUNTIFS(L_Actief,1,L_WBS,$A109,L_Doeljaar,Sel_Doeljaar,L_Versiejaar,P_VJ,L_Versie,G$8,L_Kengetal,"Omzet FY")=0,"n.b.",SUMIFS(L_Waarde,L_Actief,1,L_WBS,$A109,L_Doeljaar,Sel_Doeljaar,L_Versiejaar,P_VJ,L_Versie,G$8,L_Kengetal,"Omzet FY")))) | H109: =IF($A109="","",IF(ISNUMBER(IF(COUNTIFS(L_Actief,1,L_WBS,$A109,L_Doeljaar,Sel_Doeljaar,L_Versiejaar,P_VJ,L_Versie,H$8,L_Kengetal,"Omzet FY")=0,"n.b.",SUMIFS(L_Waarde,L_Actief,1,L_WBS,$A109,L_Doeljaar,Sel_Doeljaar,L_Versiejaar,P_VJ,L_Versie,H$8,L_Kengetal,"Omzet FY"))),IF(COUNTIFS(L_Actief,1,L_WBS,$A109,L_Doeljaar,Sel_Doeljaar,L_Versiejaar,P_VJ,L_Versie,H$8,L_Kengetal,"Omzet FY")=0,"n.b.",SUMIFS(L_Waarde,L_Actief,1,L_WBS,$A109,L_Doeljaar,Sel_Doeljaar,L_Versiejaar,P_VJ,L_Versie,H$8,L_Kengetal,"Omzet FY"))/P_Factor,IF(COUNTIFS(L_Actief,1,L_WBS,$A109,L_Doeljaar,Sel_Doeljaar,L_Versiejaar,P_VJ,L_Versie,H$8,L_Kengetal,"Omzet FY")=0,"n.b.",SUMIFS(L_Waarde,L_Actief,1,L_WBS,$A109,L_Doeljaar,Sel_Doeljaar,L_Versiejaar,P_VJ,L_Versie,H$8,L_Kengetal,"Omzet FY")))) | I109: =IF($A109="","",IF(ISNUMBER(IF(COUNTIFS(L_Actief,1,L_WBS,$A109,L_Doeljaar,Sel_Doeljaar,L_Versiejaar,P_VJ,L_Versie,I$8,L_Kengetal,"Omzet FY")=0,"n.b.",SUMIFS(L_Waarde,L_Actief,1,L_WBS,$A109,L_Doeljaar,Sel_Doeljaar,L_Versiejaar,P_VJ,L_Versie,I$8,L_Kengetal,"Omzet FY"))),IF(COUNTIFS(L_Actief,1,L_WBS,$A109,L_Doeljaar,Sel_Doeljaar,L_Versiejaar,P_VJ,L_Versie,I$8,L_Kengetal,"Omzet FY")=0,"n.b.",SUMIFS(L_Waarde,L_Actief,1,L_WBS,$A109,L_Doeljaar,Sel_Doeljaar,L_Versiejaar,P_VJ,L_Versie,I$8,L_Kengetal,"Omzet FY"))/P_Factor,IF(COUNTIFS(L_Actief,1,L_WBS,$A109,L_Doeljaar,Sel_Doeljaar,L_Versiejaar,P_VJ,L_Versie,I$8,L_Kengetal,"Omzet FY")=0,"n.b.",SUMIFS(L_Waarde,L_Actief,1,L_WBS,$A109,L_Doeljaar,Sel_Doeljaar,L_Versiejaar,P_VJ,L_Versie,I$8,L_Kengetal,"Omzet FY")))) | J109: =IF($A109="","",IF(ISNUMBER(IF(Sel_Doeljaar=P_RJ,VERW_Project!$P105,IF(Sel_Doeljaar=P_RJ+1,VERW_Project!$R105,"n.b."))),IF(Sel_Doeljaar=P_RJ,VERW_Project!$P105,IF(Sel_Doeljaar=P_RJ+1,VERW_Project!$R105,"n.b."))/P_Factor,IF(Sel_Doeljaar=P_RJ,VERW_Project!$P105,IF(Sel_Doeljaar=P_RJ+1,VERW_Project!$R105,"n.b.")))) | K109: =IF($A109="","",IF(Sel_Bron="Vastgesteld",INDEX($E109:$I109,MATCH(Sel_Versie,$E$8:$I$8,0)),IF(Sel_Bron="Concept",J109,"n.b."))) | L109: =IF($A109="","",IF(Sel_Doeljaar>P_VJ,"n.v.t.",IF(Sel_Bron="Vastgesteld",IF(ISNUMBER(IF(COUNTIFS(L_Actief,1,L_WBS,$A109,L_Doeljaar,Sel_Doeljaar,L_Versiejaar,P_VJ,L_Versie,Sel_Versie,L_Kengetal,"Omzet actual YTD")=0,"n.b.",SUMIFS(L_Waarde,L_Actief,1,L_WBS,$A109,L_Doeljaar,Sel_Doeljaar,L_Versiejaar,P_VJ,L_Versie,Sel_Versie,L_Kengetal,"Omzet actual YTD"))),IF(COUNTIFS(L_Actief,1,L_WBS,$A109,L_Doeljaar,Sel_Doeljaar,L_Versiejaar,P_VJ,L_Versie,Sel_Versie,L_Kengetal,"Omzet actual YTD")=0,"n.b.",SUMIFS(L_Waarde,L_Actief,1,L_WBS,$A109,L_Doeljaar,Sel_Doeljaar,L_Versiejaar,P_VJ,L_Versie,Sel_Versie,L_Kengetal,"Omzet actual YTD"))/P_Factor,IF(COUNTIFS(L_Actief,1,L_WBS,$A109,L_Doeljaar,Sel_Doeljaar,L_Versiejaar,P_VJ,L_Versie,Sel_Versie,L_Kengetal,"Omzet actual YTD")=0,"n.b.",SUMIFS(L_Waarde,L_Actief,1,L_WBS,$A109,L_Doeljaar,Sel_Doeljaar,L_Versiejaar,P_VJ,L_Versie,Sel_Versie,L_Kengetal,"Omzet actual YTD"))),IF(Sel_Bron="Concept",IF(ISNUMBER(IF(Sel_Doeljaar=P_RJ,VERW_Project!$L105,"n.v.t.")),IF(Sel_Doeljaar=P_RJ,VERW_Project!$L105,"n.v.t.")/P_Factor,IF(Sel_Doeljaar=P_RJ,VERW_Project!$L105,"n.v.t.")),"n.b.")))) | M109: =IF($A109="","",IF(L109="n.v.t.",K109,IF(AND(ISNUMBER(K109),ISNUMBER(L109)),K109-L109,"n.b."))) | N109: =IF($A109="","",IF(Sel_Bron="Vastgesteld",IF(ISNUMBER(IF(COUNTIFS(L_Actief,1,L_WBS,$A109,L_Doeljaar,Sel_Doeljaar,L_Versiejaar,P_VJ,L_Versie,Sel_Versie,L_Kengetal,"BOR FY")=0,"n.b.",SUMIFS(L_Waarde,L_Actief,1,L_WBS,$A109,L_Doeljaar,Sel_Doeljaar,L_Versiejaar,P_VJ,L_Versie,Sel_Versie,L_Kengetal,"BOR FY"))),IF(COUNTIFS(L_Actief,1,L_WBS,$A109,L_Doeljaar,Sel_Doeljaar,L_Versiejaar,P_VJ,L_Versie,Sel_Versie,L_Kengetal,"BOR FY")=0,"n.b.",SUMIFS(L_Waarde,L_Actief,1,L_WBS,$A109,L_Doeljaar,Sel_Doeljaar,L_Versiejaar,P_VJ,L_Versie,Sel_Versie,L_Kengetal,"BOR FY"))/P_Factor,IF(COUNTIFS(L_Actief,1,L_WBS,$A109,L_Doeljaar,Sel_Doeljaar,L_Versiejaar,P_VJ,L_Versie,Sel_Versie,L_Kengetal,"BOR FY")=0,"n.b.",SUMIFS(L_Waarde,L_Actief,1,L_WBS,$A109,L_Doeljaar,Sel_Doeljaar,L_Versiejaar,P_VJ,L_Versie,Sel_Versie,L_Kengetal,"BOR FY"))),IF(Sel_Bron="Concept",IF(ISNUMBER(IF(Sel_Doeljaar=P_RJ,VERW_Project!$Q105,IF(Sel_Doeljaar=P_RJ+1,VERW_Project!$S105,"n.b."))),IF(Sel_Doeljaar=P_RJ,VERW_Project!$Q105,IF(Sel_Doeljaar=P_RJ+1,VERW_Project!$S105,"n.b."))/P_Factor,IF(Sel_Doeljaar=P_RJ,VERW_Project!$Q105,IF(Sel_Doeljaar=P_RJ+1,VERW_Project!$S105,"n.b."))),"n.b."))) | O109: =IF($A109="","",IF(AND(ISNUMBER(N109),ISNUMBER(K109)),IF(K109<>0,N109/K109,"n.b."),"n.b.")) | P109: =IF($A109="","",IF(AND(ISNUMBER(K109),ISNUMBER(E109)),K109-E109,"n.b.")) | Q109: =IF($A109="","",IF(AND(ISNUMBER(K109),ISNUMBER(W109)),K109-W109,"n.b.")) | R109: =IF($A109="","",IF(ISNUMBER(N109),IF(N109<0,"Verlies",""),"")) | S109: =IF($A109="","",IFERROR(INDEX(T_Txt,MATCH($A109&"|"&Sel_Doeljaar&"|"&P_VJ&"|"&Sel_Versie,T_Key,0)),"")) | U109: =IF(AND(AND($A109<>"",OR(Sel_Type="Alle",$C109=Sel_Type),OR(Sel_Project="Alle",$B109=Sel_Project)),ISNUMBER(K109)),K109+ROW()/1000000000,"") | V109: =IF(AND(AND($A109<>"",OR(Sel_Type="Alle",$C109=Sel_Type),OR(Sel_Project="Alle",$B109=Sel_Project)),ISNUMBER(Q109)),ABS(Q109)+ROW()/1000000000,"") | W109: =IF(OR($A109="",Sel_Prev=""),"n.b.",IF(ISNUMBER(IF(COUNTIFS(L_Actief,1,L_WBS,$A109,L_Doeljaar,Sel_Doeljaar,L_Versiejaar,P_VJ,L_Versie,Sel_Prev,L_Kengetal,"Omzet FY")=0,"n.b.",SUMIFS(L_Waarde,L_Actief,1,L_WBS,$A109,L_Doeljaar,Sel_Doeljaar,L_Versiejaar,P_VJ,L_Versie,Sel_Prev,L_Kengetal,"Omzet FY"))),IF(COUNTIFS(L_Actief,1,L_WBS,$A109,L_Doeljaar,Sel_Doeljaar,L_Versiejaar,P_VJ,L_Versie,Sel_Prev,L_Kengetal,"Omzet FY")=0,"n.b.",SUMIFS(L_Waarde,L_Actief,1,L_WBS,$A109,L_Doeljaar,Sel_Doeljaar,L_Versiejaar,P_VJ,L_Versie,Sel_Prev,L_Kengetal,"Omzet FY"))/P_Factor,IF(COUNTIFS(L_Actief,1,L_WBS,$A109,L_Doeljaar,Sel_Doeljaar,L_Versiejaar,P_VJ,L_Versie,Sel_Prev,L_Kengetal,"Omzet FY")=0,"n.b.",SUMIFS(L_Waarde,L_Actief,1,L_WBS,$A109,L_Doeljaar,Sel_Doeljaar,L_Versiejaar,P_VJ,L_Versie,Sel_Prev,L_Kengetal,"Omzet FY")))) -> n.b.

Sheet Projectdetail
B1: ="Projectdetail — "&Det_Project -> Projectdetail — Lindehaven, Parkzoom fase 1
B2: ="Doeljaar "&Sel_Doeljaar&" · versiejaar "&P_VJ&" · bedragen in "&P_Eenheid&" · upload peildatum "&P_PeilTxt -> Doeljaar 2026 · versiejaar 2026 · bedragen in EUR x 1.000 · upload peildatum 30-09-2026
B4: Kies project: | C4: Lindehaven, Parkzoom fase 1 | H4: =IFERROR(MATCH(Det_Project,V_Naam,0),0) -> 1 | I4: =IF(Det_Idx=0,"(project niet gevonden)",INDEX(V_WBS,Det_Idx)) -> G.900001.8.9090
B6: WBS-element | C6: =IF(Det_Idx=0,"n.b.",INDEX(V_WBS,Det_Idx)) -> G.900001.8.9090 | E6: Kans % | F6: =IF(Det_Idx=0,"n.b.",INDEX(V_I_Kans,Det_Idx)) -> 100
B7: Projectdefinitie | C7: =IF(Det_Idx=0,"n.b.",INDEX(V_Projdef,Det_Idx)) -> G.900001 | E7: Risicoklasse | F7: =IF(Det_Idx=0,"n.b.",INDEX(V_I_Risico,Det_Idx)) -> 1
B8: Type | C8: =IF(Det_Idx=0,"n.b.",INDEX(V_Type,Det_Idx)) -> Opstal | E8: POC % | F8: =IF(Det_Idx=0,"n.b.",INDEX(V_I_POC,Det_Idx)) -> 39.7
B9: IFRS J/N | C9: =IF(Det_Idx=0,"n.b.",INDEX(V_IFRS,Det_Idx)) -> J | E9: Orderintake | F9: =IF(Det_Idx=0,"n.b.",INDEX(V_I_Orderintake,Det_Idx)) -> 45658
B10: Segment (demo) | C10: =IF(Det_Idx=0,"n.b.",INDEX(V_Segment,Det_Idx)) -> Grondgebonden | E10: Start verkoop | F10: =IF(Det_Idx=0,"n.b.",INDEX(V_I_StartVerk,Det_Idx)) -> 45931
B11: Aandeel % (info) | C11: =IF(Det_Idx=0,"n.b.",INDEX(V_Aandeel,Det_Idx)) -> 100 | E11: Start bouw | F11: =IF(Det_Idx=0,"n.b.",INDEX(V_I_StartBouw,Det_Idx)) -> 46023
B12: Marktsegment | C12: =IF(Det_Idx=0,"n.b.",INDEX(V_I_Marktsegment,Det_Idx)) -> WO-Wonen | E12: Maand oplevering (bron) | F12: =IF(Det_Idx=0,"n.b.",INDEX(V_I_Oplevering,Det_Idx)) -> 202812
B13: Status WBS | C13: =IF(Det_Idx=0,"n.b.",INDEX(V_I_StatusWBS,Det_Idx)) -> VRIJ VEN3 | E13: Eind oplevering | F13: =IF(Det_Idx=0,"n.b.",INDEX(V_I_EindOpl,Det_Idx)) -> 47088
B15: Jaarprognoseverloop (vastgelegde versies) en upload
B16: Versie | C16: Omzet FY | D16: BOR FY | E16: Marge % | F16: Realisatie YTD | G16: To go | H16: Woningverk. FY | I16: Toelichting | K16: ="Omzet en BOR "&Sel_Doeljaar&" per versie ("&P_Eenheid&")" -> Omzet en BOR 2026 per versie (EUR x 1.000) | Q16: Omzet FY | R16: BOR FY
B17: Budget | C17: =IF(ISNUMBER(IF(COUNTIFS(L_Actief,1,L_WBS,Det_WBS,L_Doeljaar,Sel_Doeljaar,L_Versiejaar,P_VJ,L_Versie,"Budget",L_Kengetal,"Omzet FY")=0,"n.b.",SUMIFS(L_Waarde,L_Actief,1,L_WBS,Det_WBS,L_Doeljaar,Sel_Doeljaar,L_Versiejaar,P_VJ,L_Versie,"Budget",L_Kengetal,"Omzet FY"))),IF(COUNTIFS(L_Actief,1,L_WBS,Det_WBS,L_Doeljaar,Sel_Doeljaar,L_Versiejaar,P_VJ,L_Versie,"Budget",L_Kengetal,"Omzet FY")=0,"n.b.",SUMIFS(L_Waarde,L_Actief,1,L_WBS,Det_WBS,L_Doeljaar,Sel_Doeljaar,L_Versiejaar,P_VJ,L_Versie,"Budget",L_Kengetal,"Omzet FY"))/P_Factor,IF(COUNTIFS(L_Actief,1,L_WBS,Det_WBS,L_Doeljaar,Sel_Doeljaar,L_Versiejaar,P_VJ,L_Versie,"Budget",L_Kengetal,"Omzet FY")=0,"n.b.",SUMIFS(L_Waarde,L_Actief,1,L_WBS,Det_WBS,L_Doeljaar,Sel_Doeljaar,L_Versiejaar,P_VJ,L_Versie,"Budget",L_Kengetal,"Omzet FY"))) -> 6152.96 | D17: =IF(ISNUMBER(IF(COUNTIFS(L_Actief,1,L_WBS,Det_WBS,L_Doeljaar,Sel_Doeljaar,L_Versiejaar,P_VJ,L_Versie,"Budget",L_Kengetal,"BOR FY")=0,"n.b.",SUMIFS(L_Waarde,L_Actief,1,L_WBS,Det_WBS,L_Doeljaar,Sel_Doeljaar,L_Versiejaar,P_VJ,L_Versie,"Budget",L_Kengetal,"BOR FY"))),IF(COUNTIFS(L_Actief,1,L_WBS,Det_WBS,L_Doeljaar,Sel_Doeljaar,L_Versiejaar,P_VJ,L_Versie,"Budget",L_Kengetal,"BOR FY")=0,"n.b.",SUMIFS(L_Waarde,L_Actief,1,L_WBS,Det_WBS,L_Doeljaar,Sel_Doeljaar,L_Versiejaar,P_VJ,L_Versie,"Budget",L_Kengetal,"BOR FY"))/P_Factor,IF(COUNTIFS(L_Actief,1,L_WBS,Det_WBS,L_Doeljaar,Sel_Doeljaar,L_Versiejaar,P_VJ,L_Versie,"Budget",L_Kengetal,"BOR FY")=0,"n.b.",SUMIFS(L_Waarde,L_Actief,1,L_WBS,Det_WBS,L_Doeljaar,Sel_Doeljaar,L_Versiejaar,P_VJ,L_Versie,"Budget",L_Kengetal,"BOR FY"))) -> 553.7664 | E17: =IF(AND(ISNUMBER(C17),ISNUMBER(D17)),IF(C17<>0,D17/C17,"n.b."),"n.b.") -> 0.09 | F17: =IF(ISNUMBER(IF(Sel_Doeljaar>P_VJ,"n.v.t.",IF(COUNTIFS(L_Actief,1,L_WBS,Det_WBS,L_Doeljaar,Sel_Doeljaar,L_Versiejaar,P_VJ,L_Versie,"Budget",L_Kengetal,"Omzet actual YTD")=0,"n.b.",SUMIFS(L_Waarde,L_Actief,1,L_WBS,Det_WBS,L_Doeljaar,Sel_Doeljaar,L_Versiejaar,P_VJ,L_Versie,"Budget",L_Kengetal,"Omzet actual YTD")))),IF(Sel_Doeljaar>P_VJ,"n.v.t.",IF(COUNTIFS(L_Actief,1,L_WBS,Det_WBS,L_Doeljaar,Sel_Doeljaar,L_Versiejaar,P_VJ,L_Versie,"Budget",L_Kengetal,"Omzet actual YTD")=0,"n.b.",SUMIFS(L_Waarde,L_Actief,1,L_WBS,Det_WBS,L_Doeljaar,Sel_Doeljaar,L_Versiejaar,P_VJ,L_Versie,"Budget",L_Kengetal,"Omzet actual YTD")))/P_Factor,IF(Sel_Doeljaar>P_VJ,"n.v.t.",IF(COUNTIFS(L_Actief,1,L_WBS,Det_WBS,L_Doeljaar,Sel_Doeljaar,L_Versiejaar,P_VJ,L_Versie,"Budget",L_Kengetal,"Omzet actual YTD")=0,"n.b.",SUMIFS(L_Waarde,L_Actief,1,L_WBS,Det_WBS,L_Doeljaar,Sel_Doeljaar,L_Versiejaar,P_VJ,L_Versie,"Budget",L_Kengetal,"Omzet actual YTD")))) -> n.b. | G17: =IF(F17="n.v.t.",C17,IF(AND(ISNUMBER(C17),ISNUMBER(F17)),C17-F17,"n.b.")) -> n.b. | H17: =IF(COUNTIFS(L_Actief,1,L_WBS,Det_WBS,L_Doeljaar,Sel_Doeljaar,L_Versiejaar,P_VJ,L_Versie,"Budget",L_Kengetal,"Woningverkopen FY")=0,"n.b.",SUMIFS(L_Waarde,L_Actief,1,L_WBS,Det_WBS,L_Doeljaar,Sel_Doeljaar,L_Versiejaar,P_VJ,L_Versie,"Budget",L_Kengetal,"Woningverkopen FY")) -> 9 | I17: =IFERROR(INDEX(T_Txt,MATCH(Det_WBS&"|"&Sel_Doeljaar&"|"&P_VJ&"|Budget",T_Key,0)),"") | P17: =B17&IF(ISNUMBER(C17),""," (n.b.)") -> Budget | Q17: =IF(ISNUMBER(C17),C17,0) -> 6152.96 | R17: =IF(ISNUMBER(D17),D17,0) -> 553.7664
B18: Q1 | C18: =IF(ISNUMBER(IF(COUNTIFS(L_Actief,1,L_WBS,Det_WBS,L_Doeljaar,Sel_Doeljaar,L_Versiejaar,P_VJ,L_Versie,"Q1",L_Kengetal,"Omzet FY")=0,"n.b.",SUMIFS(L_Waarde,L_Actief,1,L_WBS,Det_WBS,L_Doeljaar,Sel_Doeljaar,L_Versiejaar,P_VJ,L_Versie,"Q1",L_Kengetal,"Omzet FY"))),IF(COUNTIFS(L_Actief,1,L_WBS,Det_WBS,L_Doeljaar,Sel_Doeljaar,L_Versiejaar,P_VJ,L_Versie,"Q1",L_Kengetal,"Omzet FY")=0,"n.b.",SUMIFS(L_Waarde,L_Actief,1,L_WBS,Det_WBS,L_Doeljaar,Sel_Doeljaar,L_Versiejaar,P_VJ,L_Versie,"Q1",L_Kengetal,"Omzet FY"))/P_Factor,IF(COUNTIFS(L_Actief,1,L_WBS,Det_WBS,L_Doeljaar,Sel_Doeljaar,L_Versiejaar,P_VJ,L_Versie,"Q1",L_Kengetal,"Omzet FY")=0,"n.b.",SUMIFS(L_Waarde,L_Actief,1,L_WBS,Det_WBS,L_Doeljaar,Sel_Doeljaar,L_Versiejaar,P_VJ,L_Versie,"Q1",L_Kengetal,"Omzet FY"))) -> 5929.216 | D18: =IF(ISNUMBER(IF(COUNTIFS(L_Actief,1,L_WBS,Det_WBS,L_Doeljaar,Sel_Doeljaar,L_Versiejaar,P_VJ,L_Versie,"Q1",L_Kengetal,"BOR FY")=0,"n.b.",SUMIFS(L_Waarde,L_Actief,1,L_WBS,Det_WBS,L_Doeljaar,Sel_Doeljaar,L_Versiejaar,P_VJ,L_Versie,"Q1",L_Kengetal,"BOR FY"))),IF(COUNTIFS(L_Actief,1,L_WBS,Det_WBS,L_Doeljaar,Sel_Doeljaar,L_Versiejaar,P_VJ,L_Versie,"Q1",L_Kengetal,"BOR FY")=0,"n.b.",SUMIFS(L_Waarde,L_Actief,1,L_WBS,Det_WBS,L_Doeljaar,Sel_Doeljaar,L_Versiejaar,P_VJ,L_Versie,"Q1",L_Kengetal,"BOR FY"))/P_Factor,IF(COUNTIFS(L_Actief,1,L_WBS,Det_WBS,L_Doeljaar,Sel_Doeljaar,L_Versiejaar,P_VJ,L_Versie,"Q1",L_Kengetal,"BOR FY")=0,"n.b.",SUMIFS(L_Waarde,L_Actief,1,L_WBS,Det_WBS,L_Doeljaar,Sel_Doeljaar,L_Versiejaar,P_VJ,L_Versie,"Q1",L_Kengetal,"BOR FY"))) -> 533.62944 | E18: =IF(AND(ISNUMBER(C18),ISNUMBER(D18)),IF(C18<>0,D18/C18,"n.b."),"n.b.") -> 0.09 | F18: =IF(ISNUMBER(IF(Sel_Doeljaar>P_VJ,"n.v.t.",IF(COUNTIFS(L_Actief,1,L_WBS,Det_WBS,L_Doeljaar,Sel_Doeljaar,L_Versiejaar,P_VJ,L_Versie,"Q1",L_Kengetal,"Omzet actual YTD")=0,"n.b.",SUMIFS(L_Waarde,L_Actief,1,L_WBS,Det_WBS,L_Doeljaar,Sel_Doeljaar,L_Versiejaar,P_VJ,L_Versie,"Q1",L_Kengetal,"Omzet actual YTD")))),IF(Sel_Doeljaar>P_VJ,"n.v.t.",IF(COUNTIFS(L_Actief,1,L_WBS,Det_WBS,L_Doeljaar,Sel_Doeljaar,L_Versiejaar,P_VJ,L_Versie,"Q1",L_Kengetal,"Omzet actual YTD")=0,"n.b.",SUMIFS(L_Waarde,L_Actief,1,L_WBS,Det_WBS,L_Doeljaar,Sel_Doeljaar,L_Versiejaar,P_VJ,L_Versie,"Q1",L_Kengetal,"Omzet actual YTD")))/P_Factor,IF(Sel_Doeljaar>P_VJ,"n.v.t.",IF(COUNTIFS(L_Actief,1,L_WBS,Det_WBS,L_Doeljaar,Sel_Doeljaar,L_Versiejaar,P_VJ,L_Versie,"Q1",L_Kengetal,"Omzet actual YTD")=0,"n.b.",SUMIFS(L_Waarde,L_Actief,1,L_WBS,Det_WBS,L_Doeljaar,Sel_Doeljaar,L_Versiejaar,P_VJ,L_Versie,"Q1",L_Kengetal,"Omzet actual YTD")))) -> n.b. | G18: =IF(F18="n.v.t.",C18,IF(AND(ISNUMBER(C18),ISNUMBER(F18)),C18-F18,"n.b.")) -> n.b. | H18: =IF(COUNTIFS(L_Actief,1,L_WBS,Det_WBS,L_Doeljaar,Sel_Doeljaar,L_Versiejaar,P_VJ,L_Versie,"Q1",L_Kengetal,"Woningverkopen FY")=0,"n.b.",SUMIFS(L_Waarde,L_Actief,1,L_WBS,Det_WBS,L_Doeljaar,Sel_Doeljaar,L_Versiejaar,P_VJ,L_Versie,"Q1",L_Kengetal,"Woningverkopen FY")) -> 8 | I18: =IFERROR(INDEX(T_Txt,MATCH(Det_WBS&"|"&Sel_Doeljaar&"|"&P_VJ&"|Q1",T_Key,0)),"") | P18: =B18&IF(ISNUMBER(C18),""," (n.b.)") -> Q1 | Q18: =IF(ISNUMBER(C18),C18,0) -> 5929.216 | R18: =IF(ISNUMBER(D18),D18,0) -> 533.62944
B19: Q2 | C19: =IF(ISNUMBER(IF(COUNTIFS(L_Actief,1,L_WBS,Det_WBS,L_Doeljaar,Sel_Doeljaar,L_Versiejaar,P_VJ,L_Versie,"Q2",L_Kengetal,"Omzet FY")=0,"n.b.",SUMIFS(L_Waarde,L_Actief,1,L_WBS,Det_WBS,L_Doeljaar,Sel_Doeljaar,L_Versiejaar,P_VJ,L_Versie,"Q2",L_Kengetal,"Omzet FY"))),IF(COUNTIFS(L_Actief,1,L_WBS,Det_WBS,L_Doeljaar,Sel_Doeljaar,L_Versiejaar,P_VJ,L_Versie,"Q2",L_Kengetal,"Omzet FY")=0,"n.b.",SUMIFS(L_Waarde,L_Actief,1,L_WBS,Det_WBS,L_Doeljaar,Sel_Doeljaar,L_Versiejaar,P_VJ,L_Versie,"Q2",L_Kengetal,"Omzet FY"))/P_Factor,IF(COUNTIFS(L_Actief,1,L_WBS,Det_WBS,L_Doeljaar,Sel_Doeljaar,L_Versiejaar,P_VJ,L_Versie,"Q2",L_Kengetal,"Omzet FY")=0,"n.b.",SUMIFS(L_Waarde,L_Actief,1,L_WBS,Det_WBS,L_Doeljaar,Sel_Doeljaar,L_Versiejaar,P_VJ,L_Versie,"Q2",L_Kengetal,"Omzet FY"))) -> 5425.792 | D19: =IF(ISNUMBER(IF(COUNTIFS(L_Actief,1,L_WBS,Det_WBS,L_Doeljaar,Sel_Doeljaar,L_Versiejaar,P_VJ,L_Versie,"Q2",L_Kengetal,"BOR FY")=0,"n.b.",SUMIFS(L_Waarde,L_Actief,1,L_WBS,Det_WBS,L_Doeljaar,Sel_Doeljaar,L_Versiejaar,P_VJ,L_Versie,"Q2",L_Kengetal,"BOR FY"))),IF(COUNTIFS(L_Actief,1,L_WBS,Det_WBS,L_Doeljaar,Sel_Doeljaar,L_Versiejaar,P_VJ,L_Versie,"Q2",L_Kengetal,"BOR FY")=0,"n.b.",SUMIFS(L_Waarde,L_Actief,1,L_WBS,Det_WBS,L_Doeljaar,Sel_Doeljaar,L_Versiejaar,P_VJ,L_Versie,"Q2",L_Kengetal,"BOR FY"))/P_Factor,IF(COUNTIFS(L_Actief,1,L_WBS,Det_WBS,L_Doeljaar,Sel_Doeljaar,L_Versiejaar,P_VJ,L_Versie,"Q2",L_Kengetal,"BOR FY")=0,"n.b.",SUMIFS(L_Waarde,L_Actief,1,L_WBS,Det_WBS,L_Doeljaar,Sel_Doeljaar,L_Versiejaar,P_VJ,L_Versie,"Q2",L_Kengetal,"BOR FY"))) -> 488.32128 | E19: =IF(AND(ISNUMBER(C19),ISNUMBER(D19)),IF(C19<>0,D19/C19,"n.b."),"n.b.") -> 0.09 | F19: =IF(ISNUMBER(IF(Sel_Doeljaar>P_VJ,"n.v.t.",IF(COUNTIFS(L_Actief,1,L_WBS,Det_WBS,L_Doeljaar,Sel_Doeljaar,L_Versiejaar,P_VJ,L_Versie,"Q2",L_Kengetal,"Omzet actual YTD")=0,"n.b.",SUMIFS(L_Waarde,L_Actief,1,L_WBS,Det_WBS,L_Doeljaar,Sel_Doeljaar,L_Versiejaar,P_VJ,L_Versie,"Q2",L_Kengetal,"Omzet actual YTD")))),IF(Sel_Doeljaar>P_VJ,"n.v.t.",IF(COUNTIFS(L_Actief,1,L_WBS,Det_WBS,L_Doeljaar,Sel_Doeljaar,L_Versiejaar,P_VJ,L_Versie,"Q2",L_Kengetal,"Omzet actual YTD")=0,"n.b.",SUMIFS(L_Waarde,L_Actief,1,L_WBS,Det_WBS,L_Doeljaar,Sel_Doeljaar,L_Versiejaar,P_VJ,L_Versie,"Q2",L_Kengetal,"Omzet actual YTD")))/P_Factor,IF(Sel_Doeljaar>P_VJ,"n.v.t.",IF(COUNTIFS(L_Actief,1,L_WBS,Det_WBS,L_Doeljaar,Sel_Doeljaar,L_Versiejaar,P_VJ,L_Versie,"Q2",L_Kengetal,"Omzet actual YTD")=0,"n.b.",SUMIFS(L_Waarde,L_Actief,1,L_WBS,Det_WBS,L_Doeljaar,Sel_Doeljaar,L_Versiejaar,P_VJ,L_Versie,"Q2",L_Kengetal,"Omzet actual YTD")))) -> n.b. | G19: =IF(F19="n.v.t.",C19,IF(AND(ISNUMBER(C19),ISNUMBER(F19)),C19-F19,"n.b.")) -> n.b. | H19: =IF(COUNTIFS(L_Actief,1,L_WBS,Det_WBS,L_Doeljaar,Sel_Doeljaar,L_Versiejaar,P_VJ,L_Versie,"Q2",L_Kengetal,"Woningverkopen FY")=0,"n.b.",SUMIFS(L_Waarde,L_Actief,1,L_WBS,Det_WBS,L_Doeljaar,Sel_Doeljaar,L_Versiejaar,P_VJ,L_Versie,"Q2",L_Kengetal,"Woningverkopen FY")) -> 8 | I19: =IFERROR(INDEX(T_Txt,MATCH(Det_WBS&"|"&Sel_Doeljaar&"|"&P_VJ&"|Q2",T_Key,0)),"") | P19: =B19&IF(ISNUMBER(C19),""," (n.b.)") -> Q2 | Q19: =IF(ISNUMBER(C19),C19,0) -> 5425.792 | R19: =IF(ISNUMBER(D19),D19,0) -> 488.32128
B20: Q3 | C20: =IF(ISNUMBER(IF(COUNTIFS(L_Actief,1,L_WBS,Det_WBS,L_Doeljaar,Sel_Doeljaar,L_Versiejaar,P_VJ,L_Versie,"Q3",L_Kengetal,"Omzet FY")=0,"n.b.",SUMIFS(L_Waarde,L_Actief,1,L_WBS,Det_WBS,L_Doeljaar,Sel_Doeljaar,L_Versiejaar,P_VJ,L_Versie,"Q3",L_Kengetal,"Omzet FY"))),IF(COUNTIFS(L_Actief,1,L_WBS,Det_WBS,L_Doeljaar,Sel_Doeljaar,L_Versiejaar,P_VJ,L_Versie,"Q3",L_Kengetal,"Omzet FY")=0,"n.b.",SUMIFS(L_Waarde,L_Actief,1,L_WBS,Det_WBS,L_Doeljaar,Sel_Doeljaar,L_Versiejaar,P_VJ,L_Versie,"Q3",L_Kengetal,"Omzet FY"))/P_Factor,IF(COUNTIFS(L_Actief,1,L_WBS,Det_WBS,L_Doeljaar,Sel_Doeljaar,L_Versiejaar,P_VJ,L_Versie,"Q3",L_Kengetal,"Omzet FY")=0,"n.b.",SUMIFS(L_Waarde,L_Actief,1,L_WBS,Det_WBS,L_Doeljaar,Sel_Doeljaar,L_Versiejaar,P_VJ,L_Versie,"Q3",L_Kengetal,"Omzet FY"))) -> 5593.6 | D20: =IF(ISNUMBER(IF(COUNTIFS(L_Actief,1,L_WBS,Det_WBS,L_Doeljaar,Sel_Doeljaar,L_Versiejaar,P_VJ,L_Versie,"Q3",L_Kengetal,"BOR FY")=0,"n.b.",SUMIFS(L_Waarde,L_Actief,1,L_WBS,Det_WBS,L_Doeljaar,Sel_Doeljaar,L_Versiejaar,P_VJ,L_Versie,"Q3",L_Kengetal,"BOR FY"))),IF(COUNTIFS(L_Actief,1,L_WBS,Det_WBS,L_Doeljaar,Sel_Doeljaar,L_Versiejaar,P_VJ,L_Versie,"Q3",L_Kengetal,"BOR FY")=0,"n.b.",SUMIFS(L_Waarde,L_Actief,1,L_WBS,Det_WBS,L_Doeljaar,Sel_Doeljaar,L_Versiejaar,P_VJ,L_Versie,"Q3",L_Kengetal,"BOR FY"))/P_Factor,IF(COUNTIFS(L_Actief,1,L_WBS,Det_WBS,L_Doeljaar,Sel_Doeljaar,L_Versiejaar,P_VJ,L_Versie,"Q3",L_Kengetal,"BOR FY")=0,"n.b.",SUMIFS(L_Waarde,L_Actief,1,L_WBS,Det_WBS,L_Doeljaar,Sel_Doeljaar,L_Versiejaar,P_VJ,L_Versie,"Q3",L_Kengetal,"BOR FY"))) -> 503.424 | E20: =IF(AND(ISNUMBER(C20),ISNUMBER(D20)),IF(C20<>0,D20/C20,"n.b."),"n.b.") -> 0.09 | F20: =IF(ISNUMBER(IF(Sel_Doeljaar>P_VJ,"n.v.t.",IF(COUNTIFS(L_Actief,1,L_WBS,Det_WBS,L_Doeljaar,Sel_Doeljaar,L_Versiejaar,P_VJ,L_Versie,"Q3",L_Kengetal,"Omzet actual YTD")=0,"n.b.",SUMIFS(L_Waarde,L_Actief,1,L_WBS,Det_WBS,L_Doeljaar,Sel_Doeljaar,L_Versiejaar,P_VJ,L_Versie,"Q3",L_Kengetal,"Omzet actual YTD")))),IF(Sel_Doeljaar>P_VJ,"n.v.t.",IF(COUNTIFS(L_Actief,1,L_WBS,Det_WBS,L_Doeljaar,Sel_Doeljaar,L_Versiejaar,P_VJ,L_Versie,"Q3",L_Kengetal,"Omzet actual YTD")=0,"n.b.",SUMIFS(L_Waarde,L_Actief,1,L_WBS,Det_WBS,L_Doeljaar,Sel_Doeljaar,L_Versiejaar,P_VJ,L_Versie,"Q3",L_Kengetal,"Omzet actual YTD")))/P_Factor,IF(Sel_Doeljaar>P_VJ,"n.v.t.",IF(COUNTIFS(L_Actief,1,L_WBS,Det_WBS,L_Doeljaar,Sel_Doeljaar,L_Versiejaar,P_VJ,L_Versie,"Q3",L_Kengetal,"Omzet actual YTD")=0,"n.b.",SUMIFS(L_Waarde,L_Actief,1,L_WBS,Det_WBS,L_Doeljaar,Sel_Doeljaar,L_Versiejaar,P_VJ,L_Versie,"Q3",L_Kengetal,"Omzet actual YTD")))) -> 3635.84 | G20: =IF(F20="n.v.t.",C20,IF(AND(ISNUMBER(C20),ISNUMBER(F20)),C20-F20,"n.b.")) -> 1957.76 | H20: =IF(COUNTIFS(L_Actief,1,L_WBS,Det_WBS,L_Doeljaar,Sel_Doeljaar,L_Versiejaar,P_VJ,L_Versie,"Q3",L_Kengetal,"Woningverkopen FY")=0,"n.b.",SUMIFS(L_Waarde,L_Actief,1,L_WBS,Det_WBS,L_Doeljaar,Sel_Doeljaar,L_Versiejaar,P_VJ,L_Versie,"Q3",L_Kengetal,"Woningverkopen FY")) -> 8 | I20: =IFERROR(INDEX(T_Txt,MATCH(Det_WBS&"|"&Sel_Doeljaar&"|"&P_VJ&"|Q3",T_Key,0)),"") | P20: =B20&IF(ISNUMBER(C20),""," (n.b.)") -> Q3 | Q20: =IF(ISNUMBER(C20),C20,0) -> 5593.6 | R20: =IF(ISNUMBER(D20),D20,0) -> 503.424
B21: Q4 | C21: =IF(ISNUMBER(IF(COUNTIFS(L_Actief,1,L_WBS,Det_WBS,L_Doeljaar,Sel_Doeljaar,L_Versiejaar,P_VJ,L_Versie,"Q4",L_Kengetal,"Omzet FY")=0,"n.b.",SUMIFS(L_Waarde,L_Actief,1,L_WBS,Det_WBS,L_Doeljaar,Sel_Doeljaar,L_Versiejaar,P_VJ,L_Versie,"Q4",L_Kengetal,"Omzet FY"))),IF(COUNTIFS(L_Actief,1,L_WBS,Det_WBS,L_Doeljaar,Sel_Doeljaar,L_Versiejaar,P_VJ,L_Versie,"Q4",L_Kengetal,"Omzet FY")=0,"n.b.",SUMIFS(L_Waarde,L_Actief,1,L_WBS,Det_WBS,L_Doeljaar,Sel_Doeljaar,L_Versiejaar,P_VJ,L_Versie,"Q4",L_Kengetal,"Omzet FY"))/P_Factor,IF(COUNTIFS(L_Actief,1,L_WBS,Det_WBS,L_Doeljaar,Sel_Doeljaar,L_Versiejaar,P_VJ,L_Versie,"Q4",L_Kengetal,"Omzet FY")=0,"n.b.",SUMIFS(L_Waarde,L_Actief,1,L_WBS,Det_WBS,L_Doeljaar,Sel_Doeljaar,L_Versiejaar,P_VJ,L_Versie,"Q4",L_Kengetal,"Omzet FY"))) -> n.b. | D21: =IF(ISNUMBER(IF(COUNTIFS(L_Actief,1,L_WBS,Det_WBS,L_Doeljaar,Sel_Doeljaar,L_Versiejaar,P_VJ,L_Versie,"Q4",L_Kengetal,"BOR FY")=0,"n.b.",SUMIFS(L_Waarde,L_Actief,1,L_WBS,Det_WBS,L_Doeljaar,Sel_Doeljaar,L_Versiejaar,P_VJ,L_Versie,"Q4",L_Kengetal,"BOR FY"))),IF(COUNTIFS(L_Actief,1,L_WBS,Det_WBS,L_Doeljaar,Sel_Doeljaar,L_Versiejaar,P_VJ,L_Versie,"Q4",L_Kengetal,"BOR FY")=0,"n.b.",SUMIFS(L_Waarde,L_Actief,1,L_WBS,Det_WBS,L_Doeljaar,Sel_Doeljaar,L_Versiejaar,P_VJ,L_Versie,"Q4",L_Kengetal,"BOR FY"))/P_Factor,IF(COUNTIFS(L_Actief,1,L_WBS,Det_WBS,L_Doeljaar,Sel_Doeljaar,L_Versiejaar,P_VJ,L_Versie,"Q4",L_Kengetal,"BOR FY")=0,"n.b.",SUMIFS(L_Waarde,L_Actief,1,L_WBS,Det_WBS,L_Doeljaar,Sel_Doeljaar,L_Versiejaar,P_VJ,L_Versie,"Q4",L_Kengetal,"BOR FY"))) -> n.b. | E21: =IF(AND(ISNUMBER(C21),ISNUMBER(D21)),IF(C21<>0,D21/C21,"n.b."),"n.b.") -> n.b. | F21: =IF(ISNUMBER(IF(Sel_Doeljaar>P_VJ,"n.v.t.",IF(COUNTIFS(L_Actief,1,L_WBS,Det_WBS,L_Doeljaar,Sel_Doeljaar,L_Versiejaar,P_VJ,L_Versie,"Q4",L_Kengetal,"Omzet actual YTD")=0,"n.b.",SUMIFS(L_Waarde,L_Actief,1,L_WBS,Det_WBS,L_Doeljaar,Sel_Doeljaar,L_Versiejaar,P_VJ,L_Versie,"Q4",L_Kengetal,"Omzet actual YTD")))),IF(Sel_Doeljaar>P_VJ,"n.v.t.",IF(COUNTIFS(L_Actief,1,L_WBS,Det_WBS,L_Doeljaar,Sel_Doeljaar,L_Versiejaar,P_VJ,L_Versie,"Q4",L_Kengetal,"Omzet actual YTD")=0,"n.b.",SUMIFS(L_Waarde,L_Actief,1,L_WBS,Det_WBS,L_Doeljaar,Sel_Doeljaar,L_Versiejaar,P_VJ,L_Versie,"Q4",L_Kengetal,"Omzet actual YTD")))/P_Factor,IF(Sel_Doeljaar>P_VJ,"n.v.t.",IF(COUNTIFS(L_Actief,1,L_WBS,Det_WBS,L_Doeljaar,Sel_Doeljaar,L_Versiejaar,P_VJ,L_Versie,"Q4",L_Kengetal,"Omzet actual YTD")=0,"n.b.",SUMIFS(L_Waarde,L_Actief,1,L_WBS,Det_WBS,L_Doeljaar,Sel_Doeljaar,L_Versiejaar,P_VJ,L_Versie,"Q4",L_Kengetal,"Omzet actual YTD")))) -> n.b. | G21: =IF(F21="n.v.t.",C21,IF(AND(ISNUMBER(C21),ISNUMBER(F21)),C21-F21,"n.b.")) -> n.b. | H21: =IF(COUNTIFS(L_Actief,1,L_WBS,Det_WBS,L_Doeljaar,Sel_Doeljaar,L_Versiejaar,P_VJ,L_Versie,"Q4",L_Kengetal,"Woningverkopen FY")=0,"n.b.",SUMIFS(L_Waarde,L_Actief,1,L_WBS,Det_WBS,L_Doeljaar,Sel_Doeljaar,L_Versiejaar,P_VJ,L_Versie,"Q4",L_Kengetal,"Woningverkopen FY")) -> n.b. | I21: =IFERROR(INDEX(T_Txt,MATCH(Det_WBS&"|"&Sel_Doeljaar&"|"&P_VJ&"|Q4",T_Key,0)),"") | P21: =B21&IF(ISNUMBER(C21),""," (n.b.)") -> Q4 (n.b.) | Q21: =IF(ISNUMBER(C21),C21,0) -> 0 | R21: =IF(ISNUMBER(D21),D21,0) -> 0
B22: Upload (concept) | C22: =IF(ISNUMBER(IF(Sel_Doeljaar=P_RJ,IF(Det_Idx=0,"n.b.",INDEX(V_OmzFY,Det_Idx)),IF(Sel_Doeljaar=P_RJ+1,IF(Det_Idx=0,"n.b.",INDEX(V_OmzFY1,Det_Idx)),"n.b."))),IF(Sel_Doeljaar=P_RJ,IF(Det_Idx=0,"n.b.",INDEX(V_OmzFY,Det_Idx)),IF(Sel_Doeljaar=P_RJ+1,IF(Det_Idx=0,"n.b.",INDEX(V_OmzFY1,Det_Idx)),"n.b."))/P_Factor,IF(Sel_Doeljaar=P_RJ,IF(Det_Idx=0,"n.b.",INDEX(V_OmzFY,Det_Idx)),IF(Sel_Doeljaar=P_RJ+1,IF(Det_Idx=0,"n.b.",INDEX(V_OmzFY1,Det_Idx)),"n.b."))) -> 5593.6 | D22: =IF(ISNUMBER(IF(Sel_Doeljaar=P_RJ,IF(Det_Idx=0,"n.b.",INDEX(V_BorFY,Det_Idx)),IF(Sel_Doeljaar=P_RJ+1,IF(Det_Idx=0,"n.b.",INDEX(V_BorFY1,Det_Idx)),"n.b."))),IF(Sel_Doeljaar=P_RJ,IF(Det_Idx=0,"n.b.",INDEX(V_BorFY,Det_Idx)),IF(Sel_Doeljaar=P_RJ+1,IF(Det_Idx=0,"n.b.",INDEX(V_BorFY1,Det_Idx)),"n.b."))/P_Factor,IF(Sel_Doeljaar=P_RJ,IF(Det_Idx=0,"n.b.",INDEX(V_BorFY,Det_Idx)),IF(Sel_Doeljaar=P_RJ+1,IF(Det_Idx=0,"n.b.",INDEX(V_BorFY1,Det_Idx)),"n.b."))) -> 503.424 | E22: =IF(AND(ISNUMBER(C22),ISNUMBER(D22)),IF(C22<>0,D22/C22,"n.b."),"n.b.") -> 0.09 | F22: =IF(ISNUMBER(IF(Sel_Doeljaar=P_RJ,IF(Det_Idx=0,"n.b.",INDEX(V_OmzYTD,Det_Idx)),"n.v.t.")),IF(Sel_Doeljaar=P_RJ,IF(Det_Idx=0,"n.b.",INDEX(V_OmzYTD,Det_Idx)),"n.v.t.")/P_Factor,IF(Sel_Doeljaar=P_RJ,IF(Det_Idx=0,"n.b.",INDEX(V_OmzYTD,Det_Idx)),"n.v.t.")) -> 3635.84 | G22: =IF(F22="n.v.t.",C22,IF(AND(ISNUMBER(C22),ISNUMBER(F22)),C22-F22,"n.b.")) -> 1957.76 | H22: =IF(Sel_Doeljaar=P_RJ,IF(Det_Idx=0,"n.b.",INDEX(V_W_HuidigJaar,Det_Idx)),IF(Sel_Doeljaar=P_RJ+1,IF(Det_Idx=0,"n.b.",INDEX(V_W_VolgendJaar,Det_Idx)),"n.b.")) -> 8 | I22: ="" | P22: =B22&IF(ISNUMBER(C22),""," (n.b.)") -> Upload (concept) | Q22: =IF(ISNUMBER(C22),C22,0) -> 5593.6 | R22: =IF(ISNUMBER(D22),D22,0) -> 503.424
B31: Planning omzet en BOR volgens upload (managementteken; realisatie apart van prognose)
B32: Kengetal | C32: ="Realisatie t/m "&P_PeilTxt -> Realisatie t/m 30-09-2026 | D32: ="Q4 "&P_RJ&" (rest)" -> Q4 2026 (rest) | E32: ="Q1 "&(P_RJ+1) -> Q1 2027 | F32: ="Q2 "&(P_RJ+1) -> Q2 2027 | G32: ="Q3 "&(P_RJ+1) -> Q3 2027 | H32: ="Q4 "&(P_RJ+1) -> Q4 2027 | I32: =(P_RJ+2)&"" -> 2028 | J32: =(P_RJ+3)&"" -> 2029 | K32: =(P_RJ+4)&"" -> 2030 | L32: =(P_RJ+5)&"" -> 2031 | M32: =(P_RJ+6)&"" -> 2032 | N32: =(P_RJ+7)&"" -> 2033 | O32: =(P_RJ+8)&"" -> 2034 | P32: Onverdeeld | Q32: Totaal resterend
B33: Omzet | C33: =IF(ISNUMBER(IF(Det_Idx=0,"n.b.",INDEX(V_OmzYTD,Det_Idx))),IF(Det_Idx=0,"n.b.",INDEX(V_OmzYTD,Det_Idx))/P_Factor,IF(Det_Idx=0,"n.b.",INDEX(V_OmzYTD,Det_Idx))) -> 3635.84 | D33: =IF(ISNUMBER(IF(Det_Idx=0,"n.b.",INDEX(V_OmzQ4,Det_Idx))),IF(Det_Idx=0,"n.b.",INDEX(V_OmzQ4,Det_Idx))/P_Factor,IF(Det_Idx=0,"n.b.",INDEX(V_OmzQ4,Det_Idx))) -> 1957.76 | E33: =IF(ISNUMBER(IF(Det_Idx=0,"n.b.",INDEX(V_OmzRJ1_Q1,Det_Idx))),IF(Det_Idx=0,"n.b.",INDEX(V_OmzRJ1_Q1,Det_Idx))/P_Factor,IF(Det_Idx=0,"n.b.",INDEX(V_OmzRJ1_Q1,Det_Idx))) -> 899.392 | F33: =IF(ISNUMBER(IF(Det_Idx=0,"n.b.",INDEX(V_OmzRJ1_Q2,Det_Idx))),IF(Det_Idx=0,"n.b.",INDEX(V_OmzRJ1_Q2,Det_Idx))/P_Factor,IF(Det_Idx=0,"n.b.",INDEX(V_OmzRJ1_Q2,Det_Idx))) -> 1124.24 | G33: =IF(ISNUMBER(IF(Det_Idx=0,"n.b.",INDEX(V_OmzRJ1_Q3,Det_Idx))),IF(Det_Idx=0,"n.b.",INDEX(V_OmzRJ1_Q3,Det_Idx))/P_Factor,IF(Det_Idx=0,"n.b.",INDEX(V_OmzRJ1_Q3,Det_Idx))) -> 1349.088 | H33: =IF(ISNUMBER(IF(Det_Idx=0,"n.b.",INDEX(V_OmzRJ1_Q4,Det_Idx))),IF(Det_Idx=0,"n.b.",INDEX(V_OmzRJ1_Q4,Det_Idx))/P_Factor,IF(Det_Idx=0,"n.b.",INDEX(V_OmzRJ1_Q4,Det_Idx))) -> 1124.24 | I33: =IF(ISNUMBER(IF(Det_Idx=0,"n.b.",INDEX(V_OmzRJ2,Det_Idx))),IF(Det_Idx=0,"n.b.",INDEX(V_OmzRJ2,Det_Idx))/P_Factor,IF(Det_Idx=0,"n.b.",INDEX(V_OmzRJ2,Det_Idx))) -> 2421.44 | J33: =IF(ISNUMBER(IF(Det_Idx=0,"n.b.",INDEX(V_OmzRJ3,Det_Idx))),IF(Det_Idx=0,"n.b.",INDEX(V_OmzRJ3,Det_Idx))/P_Factor,IF(Det_Idx=0,"n.b.",INDEX(V_OmzRJ3,Det_Idx))) -> 0 | K33: =IF(ISNUMBER(IF(Det_Idx=0,"n.b.",INDEX(V_OmzRJ4,Det_Idx))),IF(Det_Idx=0,"n.b.",INDEX(V_OmzRJ4,Det_Idx))/P_Factor,IF(Det_Idx=0,"n.b.",INDEX(V_OmzRJ4,Det_Idx))) -> 0 | L33: =IF(ISNUMBER(IF(Det_Idx=0,"n.b.",INDEX(V_OmzRJ5,Det_Idx))),IF(Det_Idx=0,"n.b.",INDEX(V_OmzRJ5,Det_Idx))/P_Factor,IF(Det_Idx=0,"n.b.",INDEX(V_OmzRJ5,Det_Idx))) -> 0 | M33: =IF(ISNUMBER(IF(Det_Idx=0,"n.b.",INDEX(V_OmzRJ6,Det_Idx))),IF(Det_Idx=0,"n.b.",INDEX(V_OmzRJ6,Det_Idx))/P_Factor,IF(Det_Idx=0,"n.b.",INDEX(V_OmzRJ6,Det_Idx))) -> 0 | N33: =IF(ISNUMBER(IF(Det_Idx=0,"n.b.",INDEX(V_OmzRJ7,Det_Idx))),IF(Det_Idx=0,"n.b.",INDEX(V_OmzRJ7,Det_Idx))/P_Factor,IF(Det_Idx=0,"n.b.",INDEX(V_OmzRJ7,Det_Idx))) -> 0 | O33: =IF(ISNUMBER(IF(Det_Idx=0,"n.b.",INDEX(V_OmzRJ8,Det_Idx))),IF(Det_Idx=0,"n.b.",INDEX(V_OmzRJ8,Det_Idx))/P_Factor,IF(Det_Idx=0,"n.b.",INDEX(V_OmzRJ8,Det_Idx))) -> 0 | P33: =IF(ISNUMBER(IF(Det_Idx=0,"n.b.",INDEX(V_OmzONV,Det_Idx))),IF(Det_Idx=0,"n.b.",INDEX(V_OmzONV,Det_Idx))/P_Factor,IF(Det_Idx=0,"n.b.",INDEX(V_OmzONV,Det_Idx))) -> 0 | Q33: =SUM(D33:P33) -> 8876.16
B34: BOR | C34: =IF(ISNUMBER(IF(Det_Idx=0,"n.b.",INDEX(V_BorYTD,Det_Idx))),IF(Det_Idx=0,"n.b.",INDEX(V_BorYTD,Det_Idx))/P_Factor,IF(Det_Idx=0,"n.b.",INDEX(V_BorYTD,Det_Idx))) -> 327.2256 | D34: =IF(ISNUMBER(IF(Det_Idx=0,"n.b.",INDEX(V_BorQ4,Det_Idx))),IF(Det_Idx=0,"n.b.",INDEX(V_BorQ4,Det_Idx))/P_Factor,IF(Det_Idx=0,"n.b.",INDEX(V_BorQ4,Det_Idx))) -> 176.1984 | E34: =IF(ISNUMBER(IF(Det_Idx=0,"n.b.",INDEX(V_BorRJ1_Q1,Det_Idx))),IF(Det_Idx=0,"n.b.",INDEX(V_BorRJ1_Q1,Det_Idx))/P_Factor,IF(Det_Idx=0,"n.b.",INDEX(V_BorRJ1_Q1,Det_Idx))) -> 80.94528 | F34: =IF(ISNUMBER(IF(Det_Idx=0,"n.b.",INDEX(V_BorRJ1_Q2,Det_Idx))),IF(Det_Idx=0,"n.b.",INDEX(V_BorRJ1_Q2,Det_Idx))/P_Factor,IF(Det_Idx=0,"n.b.",INDEX(V_BorRJ1_Q2,Det_Idx))) -> 101.1816 | G34: =IF(ISNUMBER(IF(Det_Idx=0,"n.b.",INDEX(V_BorRJ1_Q3,Det_Idx))),IF(Det_Idx=0,"n.b.",INDEX(V_BorRJ1_Q3,Det_Idx))/P_Factor,IF(Det_Idx=0,"n.b.",INDEX(V_BorRJ1_Q3,Det_Idx))) -> 121.41792 | H34: =IF(ISNUMBER(IF(Det_Idx=0,"n.b.",INDEX(V_BorRJ1_Q4,Det_Idx))),IF(Det_Idx=0,"n.b.",INDEX(V_BorRJ1_Q4,Det_Idx))/P_Factor,IF(Det_Idx=0,"n.b.",INDEX(V_BorRJ1_Q4,Det_Idx))) -> 101.1816 | I34: =IF(ISNUMBER(IF(Det_Idx=0,"n.b.",INDEX(V_BorRJ2,Det_Idx))),IF(Det_Idx=0,"n.b.",INDEX(V_BorRJ2,Det_Idx))/P_Factor,IF(Det_Idx=0,"n.b.",INDEX(V_BorRJ2,Det_Idx))) -> 217.9296 | J34: =IF(ISNUMBER(IF(Det_Idx=0,"n.b.",INDEX(V_BorRJ3,Det_Idx))),IF(Det_Idx=0,"n.b.",INDEX(V_BorRJ3,Det_Idx))/P_Factor,IF(Det_Idx=0,"n.b.",INDEX(V_BorRJ3,Det_Idx))) -> 0 | K34: =IF(ISNUMBER(IF(Det_Idx=0,"n.b.",INDEX(V_BorRJ4,Det_Idx))),IF(Det_Idx=0,"n.b.",INDEX(V_BorRJ4,Det_Idx))/P_Factor,IF(Det_Idx=0,"n.b.",INDEX(V_BorRJ4,Det_Idx))) -> 0 | L34: =IF(ISNUMBER(IF(Det_Idx=0,"n.b.",INDEX(V_BorRJ5,Det_Idx))),IF(Det_Idx=0,"n.b.",INDEX(V_BorRJ5,Det_Idx))/P_Factor,IF(Det_Idx=0,"n.b.",INDEX(V_BorRJ5,Det_Idx))) -> 0 | M34: =IF(ISNUMBER(IF(Det_Idx=0,"n.b.",INDEX(V_BorRJ6,Det_Idx))),IF(Det_Idx=0,"n.b.",INDEX(V_BorRJ6,Det_Idx))/P_Factor,IF(Det_Idx=0,"n.b.",INDEX(V_BorRJ6,Det_Idx))) -> 0 | N34: =IF(ISNUMBER(IF(Det_Idx=0,"n.b.",INDEX(V_BorRJ7,Det_Idx))),IF(Det_Idx=0,"n.b.",INDEX(V_BorRJ7,Det_Idx))/P_Factor,IF(Det_Idx=0,"n.b.",INDEX(V_BorRJ7,Det_Idx))) -> 0 | O34: =IF(ISNUMBER(IF(Det_Idx=0,"n.b.",INDEX(V_BorRJ8,Det_Idx))),IF(Det_Idx=0,"n.b.",INDEX(V_BorRJ8,Det_Idx))/P_Factor,IF(Det_Idx=0,"n.b.",INDEX(V_BorRJ8,Det_Idx))) -> 0 | P34: =IF(ISNUMBER(IF(Det_Idx=0,"n.b.",INDEX(V_BorONV,Det_Idx))),IF(Det_Idx=0,"n.b.",INDEX(V_BorONV,Det_Idx))/P_Factor,IF(Det_Idx=0,"n.b.",INDEX(V_BorONV,Det_Idx))) -> 0 | Q34: =SUM(D34:P34) -> 798.8544
B37: Woningverkopen project (aantal, aandeelbasis)
B38: Periode | C38: =P_RJ&"-01" -> 2026-01 | D38: =P_RJ&"-02" -> 2026-02 | E38: =P_RJ&"-03" -> 2026-03 | F38: =P_RJ&"-04" -> 2026-04 | G38: =P_RJ&"-05" -> 2026-05 | H38: =P_RJ&"-06" -> 2026-06 | I38: =P_RJ&"-07" -> 2026-07 | J38: =P_RJ&"-08" -> 2026-08 | K38: =P_RJ&"-09" -> 2026-09 | L38: =P_RJ&"-10" -> 2026-10 | M38: =P_RJ&"-11" -> 2026-11 | N38: =P_RJ&"-12" -> 2026-12 | O38: ="Q1 "&(P_RJ+1) -> Q1 2027 | P38: ="Q2 "&(P_RJ+1) -> Q2 2027 | Q38: ="Q3 "&(P_RJ+1) -> Q3 2027 | R38: ="Q4 "&(P_RJ+1) -> Q4 2027 | S38: =(P_RJ+2)&"" -> 2028
B39: Actual | C39: =IF(1<=P_PeilMaand,IF(Det_Idx=0,"n.b.",INDEX(V_W_M01,Det_Idx)),0) -> 0 | D39: =IF(2<=P_PeilMaand,IF(Det_Idx=0,"n.b.",INDEX(V_W_M02,Det_Idx)),0) -> 0 | E39: =IF(3<=P_PeilMaand,IF(Det_Idx=0,"n.b.",INDEX(V_W_M03,Det_Idx)),0) -> 0 | F39: =IF(4<=P_PeilMaand,IF(Det_Idx=0,"n.b.",INDEX(V_W_M04,Det_Idx)),0) -> 0 | G39: =IF(5<=P_PeilMaand,IF(Det_Idx=0,"n.b.",INDEX(V_W_M05,Det_Idx)),0) -> 1 | H39: =IF(6<=P_PeilMaand,IF(Det_Idx=0,"n.b.",INDEX(V_W_M06,Det_Idx)),0) -> 0 | I39: =IF(7<=P_PeilMaand,IF(Det_Idx=0,"n.b.",INDEX(V_W_M07,Det_Idx)),0) -> 0 | J39: =IF(8<=P_PeilMaand,IF(Det_Idx=0,"n.b.",INDEX(V_W_M08,Det_Idx)),0) -> 1 | K39: =IF(9<=P_PeilMaand,IF(Det_Idx=0,"n.b.",INDEX(V_W_M09,Det_Idx)),0) -> 0 | L39: =IF(10<=P_PeilMaand,IF(Det_Idx=0,"n.b.",INDEX(V_W_M10,Det_Idx)),0) -> 0 | M39: =IF(11<=P_PeilMaand,IF(Det_Idx=0,"n.b.",INDEX(V_W_M11,Det_Idx)),0) -> 0 | N39: =IF(12<=P_PeilMaand,IF(Det_Idx=0,"n.b.",INDEX(V_W_M12,Det_Idx)),0) -> 0 | O39: 0 | P39: 0 | Q39: 0 | R39: 0 | S39: 0
B40: Prognose | C40: =IF(1>P_PeilMaand,IF(Det_Idx=0,"n.b.",INDEX(V_W_M01,Det_Idx)),0) -> 0 | D40: =IF(2>P_PeilMaand,IF(Det_Idx=0,"n.b.",INDEX(V_W_M02,Det_Idx)),0) -> 0 | E40: =IF(3>P_PeilMaand,IF(Det_Idx=0,"n.b.",INDEX(V_W_M03,Det_Idx)),0) -> 0 | F40: =IF(4>P_PeilMaand,IF(Det_Idx=0,"n.b.",INDEX(V_W_M04,Det_Idx)),0) -> 0 | G40: =IF(5>P_PeilMaand,IF(Det_Idx=0,"n.b.",INDEX(V_W_M05,Det_Idx)),0) -> 0 | H40: =IF(6>P_PeilMaand,IF(Det_Idx=0,"n.b.",INDEX(V_W_M06,Det_Idx)),0) -> 0 | I40: =IF(7>P_PeilMaand,IF(Det_Idx=0,"n.b.",INDEX(V_W_M07,Det_Idx)),0) -> 0 | J40: =IF(8>P_PeilMaand,IF(Det_Idx=0,"n.b.",INDEX(V_W_M08,Det_Idx)),0) -> 0 | K40: =IF(9>P_PeilMaand,IF(Det_Idx=0,"n.b.",INDEX(V_W_M09,Det_Idx)),0) -> 0 | L40: =IF(10>P_PeilMaand,IF(Det_Idx=0,"n.b.",INDEX(V_W_M10,Det_Idx)),0) -> 0 | M40: =IF(11>P_PeilMaand,IF(Det_Idx=0,"n.b.",INDEX(V_W_M11,Det_Idx)),0) -> 0 | N40: =IF(12>P_PeilMaand,IF(Det_Idx=0,"n.b.",INDEX(V_W_M12,Det_Idx)),0) -> 6 | O40: =IF(Det_Idx=0,"n.b.",INDEX(V_W_VQ1,Det_Idx)) -> 3 | P40: =IF(Det_Idx=0,"n.b.",INDEX(V_W_VQ2,Det_Idx)) -> 3 | Q40: =IF(Det_Idx=0,"n.b.",INDEX(V_W_VQ3,Det_Idx)) -> 3 | R40: =IF(Det_Idx=0,"n.b.",INDEX(V_W_VQ4,Det_Idx)) -> 3 | S40: =IF(Det_Idx=0,"n.b.",INDEX(V_W_Y_RJ2,Det_Idx)) -> 6
B42: ="Woningverkopen per periode (aantal): actual t/m "&P_PeilTxt&", daarna prognose" -> Woningverkopen per periode (aantal): actual t/m 30-09-2026, daarna prognose | N42: Samenvatting woningen | T42: grafiekdata | U42: Actual | V42: Prognose
N43: Totaal (aandeelbasis) | Q43: =IF(Det_Idx=0,"n.b.",INDEX(V_W_Aantal,Det_Idx)) -> 32 | T43: =C38 -> 2026-01 | U43: =C39 -> 0 | V43: =C40 -> 0
N44: Verkocht t/m vorig jaar | Q44: =IF(Det_Idx=0,"n.b.",INDEX(V_W_VJ_T,Det_Idx)) -> 6 | T44: =D38 -> 2026-02 | U44: =D39 -> 0 | V44: =D40 -> 0
N45: Verkocht huidig jaar (actual) | Q45: =IF(Det_Idx=0,"n.b.",INDEX(V_W_HJ_T,Det_Idx)) -> 2 | T45: =E38 -> 2026-03 | U45: =E39 -> 0 | V45: =E40 -> 0
N46: Cumulatief verkocht | Q46: =IF(Det_Idx=0,"n.b.",INDEX(V_W_Cum_T,Det_Idx)) -> 8 | T46: =F38 -> 2026-04 | U46: =F39 -> 0 | V46: =F40 -> 0
N47: Etalage | Q47: =IF(Det_Idx=0,"n.b.",INDEX(V_W_Etalage,Det_Idx)) -> 24 | T47: =G38 -> 2026-05 | U47: =G39 -> 1 | V47: =G40 -> 0
N48: Beleggers cumulatief | Q48: =IF(Det_Idx=0,"n.b.",INDEX(V_W_Cum_B,Det_Idx)) -> 0 | T48: =H38 -> 2026-06 | U48: =H39 -> 0 | V48: =H40 -> 0
N49: Particulier cumulatief | Q49: =IF(Det_Idx=0,"n.b.",INDEX(V_W_Cum_P,Det_Idx)) -> 8 | T49: =I38 -> 2026-07 | U49: =I39 -> 0 | V49: =I40 -> 0
T50: =J38 -> 2026-08 | U50: =J39 -> 1 | V50: =J40 -> 0
T51: =K38 -> 2026-09 | U51: =K39 -> 0 | V51: =K40 -> 0
T52: =L38 -> 2026-10 | U52: =L39 -> 0 | V52: =L40 -> 0
T53: =M38 -> 2026-11 | U53: =M39 -> 0 | V53: =M40 -> 0
T54: =N38 -> 2026-12 | U54: =N39 -> 0 | V54: =N40 -> 6
T55: =O38 -> Q1 2027 | U55: =O39 -> 0 | V55: =O40 -> 3
T56: =P38 -> Q2 2027 | U56: =P39 -> 0 | V56: =P40 -> 3
T57: =Q38 -> Q3 2027 | U57: =Q39 -> 0 | V57: =Q40 -> 3
T58: =R38 -> Q4 2027 | U58: =R39 -> 0 | V58: =R40 -> 3
T59: =S38 -> 2028 | U59: =S39 -> 0 | V59: =S40 -> 6

Sheet Woningen
B1: ="Woningverkopen "&P_Regio&" — "&P_RJ&" en "&(P_RJ+1)&" (aantallen op aandeelbasis)" -> Woningverkopen Demo Regio — 2026 en 2027 (aantallen op aandeelbasis)
B2: ="Bron: Woningetalage, peildatum "&P_PeilTxt&" · filter: "&Sel_FiltLabel&" · verkopen ≠ opleveringen/transporten/startbouw · projecten met Woningen meetellen = Nee uitgesloten" -> Bron: Woningetalage, peildatum 30-09-2026 · filter: geen filter · verkopen ≠ opleveringen/transporten/startbouw · projecten met Woningen meetellen = Nee uitgesloten
B4: Totaal woningen (aandeelbasis) | E4: ="Verkocht t/m "&(P_RJ-1) -> Verkocht t/m 2025 | H4: ="Verkocht "&P_RJ&" t/m "&P_PeilTxt -> Verkocht 2026 t/m 30-09-2026 | K4: ="Jaarverwachting "&P_RJ -> Jaarverwachting 2026 | N4: Cumulatief verkocht | Q4: Resterende etalage
B5: =SUMIFS(V_W_Aantal,V_Meetellen,"Ja",V_Type,Sel_TypeCrit,V_WBS,Sel_WBS) -> 1160 | E5: =SUMIFS(V_W_VJ_T,V_Meetellen,"Ja",V_Type,Sel_TypeCrit,V_WBS,Sel_WBS) -> 65 | H5: =SUMIFS(V_W_ActYTD,V_Meetellen,"Ja",V_Type,Sel_TypeCrit,V_WBS,Sel_WBS) -> 193 | K5: =SUMIFS(V_W_HuidigJaar,V_Meetellen,"Ja",V_Type,Sel_TypeCrit,V_WBS,Sel_WBS) -> 360 | N5: =SUMIFS(V_W_Cum_T,V_Meetellen,"Ja",V_Type,Sel_TypeCrit,V_WBS,Sel_WBS) -> 258 | Q5: =SUMIFS(V_W_Etalage,V_Meetellen,"Ja",V_Type,Sel_TypeCrit,V_WBS,Sel_WBS) -> 902
B6: ="bruto (afgeleid): "&FIXED(SUMIFS(V_W_Bruto,V_Meetellen,"Ja",V_Type,Sel_TypeCrit,V_WBS,Sel_WBS),0) -> bruto (afgeleid): 1,268 | E6: actual | H6: actual (hjr t/m peilmaand) | K6: ="waarvan prognose: "&SUMIFS(V_W_PrognoseRest,V_Meetellen,"Ja",V_Type,Sel_TypeCrit,V_WBS,Sel_WBS) -> waarvan prognose: 167 | N6: =IF(SUMIFS(V_W_Aantal,V_Meetellen,"Ja",V_Type,Sel_TypeCrit,V_WBS,Sel_WBS)=0,"n.b.",FIXED(SUMIFS(V_W_Cum_T,V_Meetellen,"Ja",V_Type,Sel_TypeCrit,V_WBS,Sel_WBS)/SUMIFS(V_W_Aantal,V_Meetellen,"Ja",V_Type,Sel_TypeCrit,V_WBS,Sel_WBS)*100,0)&"% van totaal") -> 22% van totaal | Q6: totaal − cumulatief actual
B7: ="niet nogmaals × aandeel" -> niet nogmaals × aandeel | K7: ="volgend jaar: "&SUMIFS(V_W_VolgendJaar,V_Meetellen,"Ja",V_Type,Sel_TypeCrit,V_WBS,Sel_WBS) -> volgend jaar: 483 | N7: =IF(SUMIFS(V_W_Aantal,V_Meetellen,"Ja",V_Type,Sel_TypeCrit,V_WBS,Sel_WBS)=0,0,SUMIFS(V_W_Cum_T,V_Meetellen,"Ja",V_Type,Sel_TypeCrit,V_WBS,Sel_WBS)/SUMIFS(V_W_Aantal,V_Meetellen,"Ja",V_Type,Sel_TypeCrit,V_WBS,Sel_WBS)) -> 0.22241379
B10: Verkopen per maand en kwartaal (actual t/m peilmaand, daarna prognose)
B11: Periode | C11: Actual | D11: Prognose | E11: Totaal | F11: Status | H11: ="Verkopen per kwartaal "&P_RJ&"–"&(P_RJ+1)&" (aantal): actual vs prognose" -> Verkopen per kwartaal 2026–2027 (aantal): actual vs prognose
B12: =P_RJ&"-"&RIGHT("01",2) -> 2026-01 | C12: =IF(1<=P_PeilMaand,SUMIFS(V_W_M01,V_Meetellen,"Ja",V_Type,Sel_TypeCrit,V_WBS,Sel_WBS),0) -> 6 | D12: =IF(1>P_PeilMaand,SUMIFS(V_W_M01,V_Meetellen,"Ja",V_Type,Sel_TypeCrit,V_WBS,Sel_WBS),0) -> 0 | E12: =C12+D12 -> 6 | F12: =IF(1<=P_PeilMaand,"actual","prognose") -> actual
B13: =P_RJ&"-"&RIGHT("02",2) -> 2026-02 | C13: =IF(2<=P_PeilMaand,SUMIFS(V_W_M02,V_Meetellen,"Ja",V_Type,Sel_TypeCrit,V_WBS,Sel_WBS),0) -> 6 | D13: =IF(2>P_PeilMaand,SUMIFS(V_W_M02,V_Meetellen,"Ja",V_Type,Sel_TypeCrit,V_WBS,Sel_WBS),0) -> 0 | E13: =C13+D13 -> 6 | F13: =IF(2<=P_PeilMaand,"actual","prognose") -> actual
B14: =P_RJ&"-"&RIGHT("03",2) -> 2026-03 | C14: =IF(3<=P_PeilMaand,SUMIFS(V_W_M03,V_Meetellen,"Ja",V_Type,Sel_TypeCrit,V_WBS,Sel_WBS),0) -> 21 | D14: =IF(3>P_PeilMaand,SUMIFS(V_W_M03,V_Meetellen,"Ja",V_Type,Sel_TypeCrit,V_WBS,Sel_WBS),0) -> 0 | E14: =C14+D14 -> 21 | F14: =IF(3<=P_PeilMaand,"actual","prognose") -> actual
B15: =P_RJ&"-"&RIGHT("04",2) -> 2026-04 | C15: =IF(4<=P_PeilMaand,SUMIFS(V_W_M04,V_Meetellen,"Ja",V_Type,Sel_TypeCrit,V_WBS,Sel_WBS),0) -> 21 | D15: =IF(4>P_PeilMaand,SUMIFS(V_W_M04,V_Meetellen,"Ja",V_Type,Sel_TypeCrit,V_WBS,Sel_WBS),0) -> 0 | E15: =C15+D15 -> 21 | F15: =IF(4<=P_PeilMaand,"actual","prognose") -> actual
B16: =P_RJ&"-"&RIGHT("05",2) -> 2026-05 | C16: =IF(5<=P_PeilMaand,SUMIFS(V_W_M05,V_Meetellen,"Ja",V_Type,Sel_TypeCrit,V_WBS,Sel_WBS),0) -> 38 | D16: =IF(5>P_PeilMaand,SUMIFS(V_W_M05,V_Meetellen,"Ja",V_Type,Sel_TypeCrit,V_WBS,Sel_WBS),0) -> 0 | E16: =C16+D16 -> 38 | F16: =IF(5<=P_PeilMaand,"actual","prognose") -> actual
B17: =P_RJ&"-"&RIGHT("06",2) -> 2026-06 | C17: =IF(6<=P_PeilMaand,SUMIFS(V_W_M06,V_Meetellen,"Ja",V_Type,Sel_TypeCrit,V_WBS,Sel_WBS),0) -> 21 | D17: =IF(6>P_PeilMaand,SUMIFS(V_W_M06,V_Meetellen,"Ja",V_Type,Sel_TypeCrit,V_WBS,Sel_WBS),0) -> 0 | E17: =C17+D17 -> 21 | F17: =IF(6<=P_PeilMaand,"actual","prognose") -> actual
B18: =P_RJ&"-"&RIGHT("07",2) -> 2026-07 | C18: =IF(7<=P_PeilMaand,SUMIFS(V_W_M07,V_Meetellen,"Ja",V_Type,Sel_TypeCrit,V_WBS,Sel_WBS),0) -> 21 | D18: =IF(7>P_PeilMaand,SUMIFS(V_W_M07,V_Meetellen,"Ja",V_Type,Sel_TypeCrit,V_WBS,Sel_WBS),0) -> 0 | E18: =C18+D18 -> 21 | F18: =IF(7<=P_PeilMaand,"actual","prognose") -> actual
B19: =P_RJ&"-"&RIGHT("08",2) -> 2026-08 | C19: =IF(8<=P_PeilMaand,SUMIFS(V_W_M08,V_Meetellen,"Ja",V_Type,Sel_TypeCrit,V_WBS,Sel_WBS),0) -> 38 | D19: =IF(8>P_PeilMaand,SUMIFS(V_W_M08,V_Meetellen,"Ja",V_Type,Sel_TypeCrit,V_WBS,Sel_WBS),0) -> 0 | E19: =C19+D19 -> 38 | F19: =IF(8<=P_PeilMaand,"actual","prognose") -> actual
B20: =P_RJ&"-"&RIGHT("09",2) -> 2026-09 | C20: =IF(9<=P_PeilMaand,SUMIFS(V_W_M09,V_Meetellen,"Ja",V_Type,Sel_TypeCrit,V_WBS,Sel_WBS),0) -> 21 | D20: =IF(9>P_PeilMaand,SUMIFS(V_W_M09,V_Meetellen,"Ja",V_Type,Sel_TypeCrit,V_WBS,Sel_WBS),0) -> 0 | E20: =C20+D20 -> 21 | F20: =IF(9<=P_PeilMaand,"actual","prognose") -> actual
B21: =P_RJ&"-"&RIGHT("010",2) -> 2026-10 | C21: =IF(10<=P_PeilMaand,SUMIFS(V_W_M10,V_Meetellen,"Ja",V_Type,Sel_TypeCrit,V_WBS,Sel_WBS),0) -> 0 | D21: =IF(10>P_PeilMaand,SUMIFS(V_W_M10,V_Meetellen,"Ja",V_Type,Sel_TypeCrit,V_WBS,Sel_WBS),0) -> 6 | E21: =C21+D21 -> 6 | F21: =IF(10<=P_PeilMaand,"actual","prognose") -> prognose
B22: =P_RJ&"-"&RIGHT("011",2) -> 2026-11 | C22: =IF(11<=P_PeilMaand,SUMIFS(V_W_M11,V_Meetellen,"Ja",V_Type,Sel_TypeCrit,V_WBS,Sel_WBS),0) -> 0 | D22: =IF(11>P_PeilMaand,SUMIFS(V_W_M11,V_Meetellen,"Ja",V_Type,Sel_TypeCrit,V_WBS,Sel_WBS),0) -> 6 | E22: =C22+D22 -> 6 | F22: =IF(11<=P_PeilMaand,"actual","prognose") -> prognose
B23: =P_RJ&"-"&RIGHT("012",2) -> 2026-12 | C23: =IF(12<=P_PeilMaand,SUMIFS(V_W_M12,V_Meetellen,"Ja",V_Type,Sel_TypeCrit,V_WBS,Sel_WBS),0) -> 0 | D23: =IF(12>P_PeilMaand,SUMIFS(V_W_M12,V_Meetellen,"Ja",V_Type,Sel_TypeCrit,V_WBS,Sel_WBS),0) -> 155 | E23: =C23+D23 -> 155 | F23: =IF(12<=P_PeilMaand,"actual","prognose") -> prognose
B24: Kwartaal | C24: Actual | D24: Prognose | E24: Totaal | F24: Status
B25: =P_RJ&" Q1" -> 2026 Q1 | C25: =SUM(C12:C14) -> 33 | D25: =SUM(D12:D14) -> 0 | E25: =C25+D25 -> 33 | F25: =IF(D25=0,"actual",IF(C25=0,"prognose","deels actual")) -> actual
B26: =P_RJ&" Q2" -> 2026 Q2 | C26: =SUM(C15:C17) -> 80 | D26: =SUM(D15:D17) -> 0 | E26: =C26+D26 -> 80 | F26: =IF(D26=0,"actual",IF(C26=0,"prognose","deels actual")) -> actual
B27: =P_RJ&" Q3" -> 2026 Q3 | C27: =SUM(C18:C20) -> 80 | D27: =SUM(D18:D20) -> 0 | E27: =C27+D27 -> 80 | F27: =IF(D27=0,"actual",IF(C27=0,"prognose","deels actual")) -> actual
B28: =P_RJ&" Q4" -> 2026 Q4 | C28: =SUM(C21:C23) -> 0 | D28: =SUM(D21:D23) -> 167 | E28: =C28+D28 -> 167 | F28: =IF(D28=0,"actual",IF(C28=0,"prognose","deels actual")) -> prognose
B29: =(P_RJ+1)&" Q1" -> 2027 Q1 | C29: 0 | D29: =SUMIFS(V_W_VQ1,V_Meetellen,"Ja",V_Type,Sel_TypeCrit,V_WBS,Sel_WBS) -> 135 | E29: =C29+D29 -> 135 | F29: prognose
B30: =(P_RJ+1)&" Q2" -> 2027 Q2 | C30: 0 | D30: =SUMIFS(V_W_VQ2,V_Meetellen,"Ja",V_Type,Sel_TypeCrit,V_WBS,Sel_WBS) -> 115 | E30: =C30+D30 -> 115 | F30: prognose
B31: =(P_RJ+1)&" Q3" -> 2027 Q3 | C31: 0 | D31: =SUMIFS(V_W_VQ3,V_Meetellen,"Ja",V_Type,Sel_TypeCrit,V_WBS,Sel_WBS) -> 115 | E31: =C31+D31 -> 115 | F31: prognose
B32: =(P_RJ+1)&" Q4" -> 2027 Q4 | C32: 0 | D32: =SUMIFS(V_W_VQ4,V_Meetellen,"Ja",V_Type,Sel_TypeCrit,V_WBS,Sel_WBS) -> 118 | E32: =C32+D32 -> 118 | F32: prognose
B34: Jaarverwachting woningverkopen per prognoseversie (doeljaar volgens Dashboard)
B35: Versie | C35: Label | D35: Verkopen FY | E35: Actual YTD | F35: Δ vs Budget | H35: ="Jaarverwachting verkopen "&Sel_Doeljaar&" per versie (aantal)" -> Jaarverwachting verkopen 2026 per versie (aantal) | Q35: Verkopen FY
B36: Budget | C36: =B36&IF(ISNUMBER(CALC_Versies!$W$5),""," (n.b.)") -> Budget | D36: =CALC_Versies!$W$5 -> 372 | E36: =CALC_Versies!$X$5 -> n.b. | F36: =IF(AND(ISNUMBER(D36),ISNUMBER($D$36)),D36-$D$36,"n.b.") -> 0 | Q36: =IF(ISNUMBER(D36),D36,0) -> 372
B37: Q1 | C37: =B37&IF(ISNUMBER(CALC_Versies!$W$6),""," (n.b.)") -> Q1 | D37: =CALC_Versies!$W$6 -> 366 | E37: =CALC_Versies!$X$6 -> n.b. | F37: =IF(AND(ISNUMBER(D37),ISNUMBER($D$36)),D37-$D$36,"n.b.") -> -6 | Q37: =IF(ISNUMBER(D37),D37,0) -> 366
B38: Q2 | C38: =B38&IF(ISNUMBER(CALC_Versies!$W$7),""," (n.b.)") -> Q2 | D38: =CALC_Versies!$W$7 -> 355 | E38: =CALC_Versies!$X$7 -> n.b. | F38: =IF(AND(ISNUMBER(D38),ISNUMBER($D$36)),D38-$D$36,"n.b.") -> -17 | Q38: =IF(ISNUMBER(D38),D38,0) -> 355
B39: Q3 | C39: =B39&IF(ISNUMBER(CALC_Versies!$W$8),""," (n.b.)") -> Q3 | D39: =CALC_Versies!$W$8 -> 360 | E39: =CALC_Versies!$X$8 -> 193 | F39: =IF(AND(ISNUMBER(D39),ISNUMBER($D$36)),D39-$D$36,"n.b.") -> -12 | Q39: =IF(ISNUMBER(D39),D39,0) -> 360
